
  0            0 RESUME                   0

  1            2 LOAD_CONST               0 (0)
               4 LOAD_CONST               1 (None)
               6 IMPORT_NAME              0 (requests)
               8 STORE_NAME               0 (requests)
              10 LOAD_CONST               0 (0)
              12 LOAD_CONST               1 (None)
              14 IMPORT_NAME              1 (random)
              16 STORE_NAME               1 (random)
              18 LOAD_CONST               0 (0)
              20 LOAD_CONST               1 (None)
              22 IMPORT_NAME              2 (datetime)
              24 STORE_NAME               2 (datetime)
              26 LOAD_CONST               0 (0)
              28 LOAD_CONST               1 (None)
              30 IMPORT_NAME              3 (binascii)
              32 STORE_NAME               3 (binascii)
              34 LOAD_CONST               0 (0)
              36 LOAD_CONST               1 (None)
              38 IMPORT_NAME              4 (os)
              40 STORE_NAME               4 (os)
              42 LOAD_CONST               0 (0)
              44 LOAD_CONST               1 (None)
              46 IMPORT_NAME              5 (threading)
              48 STORE_NAME               5 (threading)
              50 LOAD_CONST               0 (0)
              52 LOAD_CONST               1 (None)
              54 IMPORT_NAME              6 (names)
              56 STORE_NAME               6 (names)
              58 LOAD_CONST               0 (0)
              60 LOAD_CONST               1 (None)
              62 IMPORT_NAME              7 (secrets)
              64 STORE_NAME               7 (secrets)
              66 LOAD_CONST               0 (0)
              68 LOAD_CONST               1 (None)
              70 IMPORT_NAME              8 (sys)
              72 STORE_NAME               8 (sys)

  2           74 LOAD_CONST               0 (0)
              76 LOAD_CONST               1 (None)
              78 IMPORT_NAME              9 (hashlib)
              80 STORE_NAME               9 (hashlib)

  3           82 LOAD_CONST               0 (0)
              84 LOAD_CONST               1 (None)
              86 IMPORT_NAME             10 (json)
              88 STORE_NAME              10 (json)

  4           90 LOAD_CONST               0 (0)
              92 LOAD_CONST               1 (None)
              94 IMPORT_NAME             11 (time)
              96 STORE_NAME              11 (time)

  5           98 LOAD_CONST               0 (0)
             100 LOAD_CONST               2 (('urlencode',))
             102 IMPORT_NAME             12 (urllib.parse)
             104 IMPORT_FROM             13 (urlencode)
             106 STORE_NAME              13 (urlencode)
             108 POP_TOP

  6          110 LOAD_CONST               0 (0)
             112 LOAD_CONST               1 (None)
             114 IMPORT_NAME              0 (requests)
             116 STORE_NAME               0 (requests)
             118 LOAD_CONST               0 (0)
             120 LOAD_CONST               1 (None)
             122 IMPORT_NAME              8 (sys)
             124 STORE_NAME               8 (sys)
             126 LOAD_CONST               0 (0)
             128 LOAD_CONST               1 (None)
             130 IMPORT_NAME              4 (os)
             132 STORE_NAME               4 (os)
             134 LOAD_CONST               0 (0)
             136 LOAD_CONST               1 (None)
             138 IMPORT_NAME             11 (time)
             140 STORE_NAME              11 (time)

  8          142 PUSH_NULL
             144 LOAD_NAME                0 (requests)
             146 LOAD_ATTR               14 (Session)
             156 PRECALL                  0
             160 CALL                     0
             170 STORE_NAME              15 (session)

 12          172 BUILD_LIST               0
             174 STORE_NAME              16 (soso)

 13          176 BUILD_LIST               0
             178 STORE_NAME              17 (loop)

 14          180 BUILD_LIST               0
             182 STORE_NAME              18 (tar)

 15          184 BUILD_LIST               0
             186 STORE_NAME              19 (x_)

 16          188 BUILD_LIST               0
             190 STORE_NAME              20 (ls)

 17          192 LOAD_CONST               3 ('91383afcf29c9b4e414057b526b5f4dc')
             194 BUILD_LIST               1
             196 STORE_NAME              21 (sisn)

 18          198 LOAD_CONST               4 ((0, 0, 0))
             200 UNPACK_SEQUENCE          3
             204 STORE_GLOBAL            22 (tr)
             206 STORE_GLOBAL            23 (fa)
             208 STORE_GLOBAL            24 (er)

 19          210 PUSH_NULL
             212 LOAD_BUILD_CLASS
             214 LOAD_CONST               5 (<code object ttsign at 0x7cb6352af0, file "", line 19>)
             216 MAKE_FUNCTION            0
             218 LOAD_CONST               6 ('ttsign')
             220 PRECALL                  2
             224 CALL                     2
             234 STORE_NAME              25 (ttsign)

118          236 LOAD_CONST               7 ('\x1b[1;97m')
             238 STORE_NAME              26 (P)

119          240 LOAD_CONST               8 ('\x1b[1;94m')
             242 STORE_NAME              27 (B)

120          244 LOAD_CONST               9 ('\x1b[1;96m')
             246 STORE_NAME              28 (O)

121          248 LOAD_CONST              10 ('\x1b[1;30m')
             250 STORE_NAME              29 (Z)

122          252 LOAD_CONST              11 ('\x1b[1;33m')
             254 STORE_NAME              30 (X)

123          256 LOAD_CONST              12 ('\x1b[2;32m')
             258 STORE_NAME              31 (F)

124          260 LOAD_CONST              13 ('\x1b[1;31m')
             262 STORE_NAME              29 (Z)

125          264 LOAD_CONST              14 ('\x1b[1;95m')
             266 STORE_NAME              32 (L)

126          268 LOAD_CONST              15 ('\x1b[2;35m')
             270 STORE_NAME              33 (C)

127          272 LOAD_CONST              16 ('\x1b[2;39m')
             274 STORE_NAME              34 (A)

128          276 LOAD_CONST              17 ('\x1b[38;5;231m')
             278 STORE_NAME              26 (P)

129          280 LOAD_CONST              18 ('\x1b[38;5;208m')
             282 STORE_NAME              35 (J)

130          284 LOAD_CONST              19 ('\x1b[38;5;202m')
             286 STORE_NAME              36 (J1)

131          288 LOAD_CONST              20 ('\x1b[38;5;203m')
             290 STORE_NAME              37 (J2)

132          292 LOAD_CONST              21 ('\x1b[38;5;204m')
             294 STORE_NAME              38 (J21)

133          296 LOAD_CONST              22 ('\x1b[38;5;209m')
             298 STORE_NAME              39 (J22)

134          300 LOAD_CONST              23 ('\x1b[38;5;76m')
             302 STORE_NAME              40 (F1)

135          304 LOAD_CONST              24 ('\x1b[38;5;120m')
             306 STORE_NAME              41 (C1)

136          308 LOAD_CONST              25 ('\x1b[38;5;150m')
             310 STORE_NAME              42 (P1)

137          312 LOAD_CONST              26 ('\x1b[38;5;190m')
             314 STORE_NAME              43 (P2)

138          316 LOAD_CONST              27 (<code object clear at 0x7e4648a2f0, file "", line 138>)
             318 MAKE_FUNCTION            0
             320 STORE_NAME              44 (clear)

181          322 PUSH_NULL
             324 LOAD_NAME               44 (clear)
             326 PRECALL                  0
             330 CALL                     0
             340 POP_TOP

182          342 PUSH_NULL
             344 LOAD_NAME               45 (print)
             346 LOAD_NAME               29 (Z)
             348 FORMAT_VALUE             0
             350 LOAD_CONST              28 ('[')
             352 LOAD_NAME               31 (F)
             354 FORMAT_VALUE             0
             356 LOAD_CONST              29 ('1')
             358 LOAD_NAME               29 (Z)
             360 FORMAT_VALUE             0
             362 LOAD_CONST              30 ('] ')
             364 LOAD_NAME               41 (C1)
             366 FORMAT_VALUE             0
             368 LOAD_CONST              31 ('سحب سيزن ايدي')
             370 BUILD_STRING             8
             372 PRECALL                  1
             376 CALL                     1
             386 POP_TOP

183          388 PUSH_NULL
             390 LOAD_NAME               45 (print)
             392 LOAD_NAME               29 (Z)
             394 FORMAT_VALUE             0
             396 LOAD_CONST              28 ('[')
             398 LOAD_NAME               31 (F)
             400 FORMAT_VALUE             0
             402 LOAD_CONST              32 ('2')
             404 LOAD_NAME               29 (Z)
             406 FORMAT_VALUE             0
             408 LOAD_CONST              30 ('] ')
             410 LOAD_NAME               41 (C1)
             412 FORMAT_VALUE             0
             414 LOAD_CONST              33 ('سحب بروكسي〽️')
             416 BUILD_STRING             8
             418 PRECALL                  1
             422 CALL                     1
             432 POP_TOP

184          434 PUSH_NULL
             436 LOAD_NAME               45 (print)
             438 LOAD_NAME               29 (Z)
             440 FORMAT_VALUE             0
             442 LOAD_CONST              28 ('[')
             444 LOAD_NAME               31 (F)
             446 FORMAT_VALUE             0
             448 LOAD_CONST              34 ('3')
             450 LOAD_NAME               29 (Z)
             452 FORMAT_VALUE             0
             454 LOAD_CONST              30 ('] ')
             456 LOAD_NAME               41 (C1)
             458 FORMAT_VALUE             0
             460 LOAD_CONST              35 ('معومات مهمه عن التطيير والادات')
             462 BUILD_STRING             8
             464 PRECALL                  1
             468 CALL                     1
             478 POP_TOP

185          480 PUSH_NULL
             482 LOAD_NAME               45 (print)
             484 LOAD_NAME               29 (Z)
             486 FORMAT_VALUE             0
             488 LOAD_CONST              28 ('[')
             490 LOAD_NAME               31 (F)
             492 FORMAT_VALUE             0
             494 LOAD_CONST              36 ('4')
             496 LOAD_NAME               29 (Z)
             498 FORMAT_VALUE             0
             500 LOAD_CONST              30 ('] ')
             502 LOAD_NAME               41 (C1)
             504 FORMAT_VALUE             0
             506 LOAD_CONST              37 ('قسم البلاغات❗')
             508 BUILD_STRING             8
             510 PRECALL                  1
             514 CALL                     1
             524 POP_TOP

186          526 PUSH_NULL
             528 LOAD_NAME               46 (input)
             530 LOAD_NAME               30 (X)
             532 FORMAT_VALUE             0
             534 LOAD_CONST              28 ('[')
             536 LOAD_NAME               31 (F)
             538 FORMAT_VALUE             0
             540 LOAD_CONST              38 ('×')
             542 LOAD_NAME               30 (X)
             544 FORMAT_VALUE             0
             546 LOAD_CONST              39 (']')
             548 LOAD_NAME               29 (Z)
             550 FORMAT_VALUE             0
             552 LOAD_CONST              40 (' اختار : ')
             554 BUILD_STRING             8
             556 LOAD_NAME               32 (L)
             558 BINARY_OP                0 (+)
             562 PRECALL                  1
             566 CALL                     1
             576 STORE_NAME              47 (Get_aobsh)

187          578 PUSH_NULL
             580 LOAD_NAME               44 (clear)
             582 PRECALL                  0
             586 CALL                     0
             596 POP_TOP

188          598 LOAD_NAME               47 (Get_aobsh)
             600 LOAD_CONST              29 ('1')
             602 CONTAINS_OP              0
             604 EXTENDED_ARG             4
             606 POP_JUMP_FORWARD_IF_FALSE  1110 (to 2828)

189          608 LOAD_CONST               0 (0)
             610 LOAD_CONST              41 (('uuid4',))
             612 IMPORT_NAME             48 (uuid)
             614 IMPORT_FROM             49 (uuid4)
             616 STORE_NAME              49 (uuid4)
             618 POP_TOP

190          620 PUSH_NULL
             622 LOAD_NAME               50 (str)
             624 PUSH_NULL
             626 LOAD_NAME                3 (binascii)
             628 LOAD_ATTR               51 (hexlify)
             638 PUSH_NULL
             640 LOAD_NAME                4 (os)
             642 LOAD_ATTR               52 (urandom)
             652 LOAD_CONST              42 (8)
             654 PRECALL                  1
             658 CALL                     1
             668 PRECALL                  1
             672 CALL                     1
             682 LOAD_METHOD             53 (decode)
             704 PRECALL                  0
             708 CALL                     0
             718 PRECALL                  1
             722 CALL                     1
             732 STORE_NAME              54 (openudid)

191          734 PUSH_NULL
             736 LOAD_NAME                1 (random)
             738 LOAD_ATTR               55 (choice)
             748 BUILD_LIST               0
             750 LOAD_CONST              43 (('SM-G975F', 'SM-G532G', 'SM-N975F', 'SM-G988U', 'SM-G977U', 'SM-A705FN', 'SM-A515U1', 'SM-G955F', 'SM-A750G', 'SM-N960F', 'SM-G960U', 'SM-J600F', 'SM-A908B', 'SM-A705GM', 'SM-G970U', 'SM-A307FN', 'SM-G965U1', 'SM-A217F', 'SM-G986B', 'SM-A207M', 'SM-A515W', 'SM-A505G', 'SM-A315G', 'SM-A507FN', 'SM-A505U1', 'SM-G977T', 'SM-A025G', 'SM-J320F', 'SM-A715W', 'SM-A908N', 'SM-A205F', 'SM-G988B', 'SM-N986B', 'SM-A715F', 'SM-A515F', 'SM-G965F', 'SM-G960F', 'SM-A505F', 'SM-A207F', 'SM-A307G', 'SM-G970F', 'SM-A107F', 'SM-G935F', 'SM-G935A', 'SM-A310F', 'SM-J320FN'))
             752 LIST_EXTEND              1
             754 PRECALL                  1
             758 CALL                     1
             768 STORE_NAME              56 (device_samsung)

193          770 PUSH_NULL
             772 LOAD_NAME                1 (random)
             774 LOAD_ATTR               57 (randrange)
             784 LOAD_CONST              44 (7334285683765348101)
             786 LOAD_CONST              45 (7334285999999999999)
             788 PRECALL                  2
             792 CALL                     2
             802 STORE_NAME              58 (install_id)

194          804 PUSH_NULL
             806 LOAD_NAME                1 (random)
             808 LOAD_ATTR               57 (randrange)
             818 LOAD_CONST              46 (7283928371561793029)
             820 LOAD_CONST              47 (7283929999999999999)
             822 PRECALL                  2
             826 CALL                     2
             836 STORE_NAME              59 (device_id)

195          838 LOAD_CONST              48 ('1$')
             840 LOAD_CONST              49 ('')
             842 LOAD_METHOD             60 (join)
             864 LOAD_CONST              50 (<code object <genexpr> at 0x7cb61e1430, file "", line 195>)
             866 MAKE_FUNCTION            0
             868 PUSH_NULL
             870 LOAD_NAME               61 (range)
             872 LOAD_CONST              51 (40)
             874 PRECALL                  1
             878 CALL                     1
             888 GET_ITER
             890 PRECALL                  0
             894 CALL                     0
             904 PRECALL                  1
             908 CALL                     1
             918 BINARY_OP                0 (+)
             922 STORE_NAME              62 (ttreq)

197          924 PUSH_NULL
             926 LOAD_NAME               50 (str)
             928 PUSH_NULL
             930 LOAD_NAME               49 (uuid4)
             932 PRECALL                  0
             936 CALL                     0
             946 PRECALL                  1
             950 CALL                     1
             960 STORE_NAME              63 (uid)

199          962 LOAD_CONST              52 ('https://mssdk-va.tiktok.com/web/report?msToken=ua8RoU-MTeGPDGbFM3SAs6gya9qj47EJdMC71Fq68J74ATLBRh43bGe7h5vC2XvbNpB7Ollah4W8I3idrB0g9DNMhlWZnYtGpGJVLIZH4G8Bf0FM61FFdDFO5QzXwZDGo9k=&X-Bogus=DFSzsIVO7SRa09Y/S4L0Yt8kBPMk')
             964 STORE_NAME              64 (url99)

202          966 LOAD_CONST              53 ('User-Agent')
             968 LOAD_CONST              54 ('Mozilla/5.0 (Windows NT 10.0; Win64; x64; rv:108.0) Gecko/20100101 Firefox/108.0')

201          970 BUILD_MAP                1
             972 STORE_NAME              65 (ha99)

206          974 PUSH_NULL
             976 LOAD_NAME                0 (requests)
             978 LOAD_ATTR               66 (get)
             988 LOAD_NAME               64 (url99)
             990 LOAD_NAME               65 (ha99)
             992 KW_NAMES                55
             994 PRECALL                  2
             998 CALL                     2
            1008 LOAD_ATTR               67 (cookies)
            1018 LOAD_METHOD             68 (get_dict)
            1040 PRECALL                  0
            1044 CALL                     0
            1054 LOAD_CONST              56 ('msToken')
            1056 BINARY_SUBSCR
            1066 STORE_NAME              69 (r199)

207         1068 PUSH_NULL
            1070 LOAD_NAME               70 (int)
            1072 PUSH_NULL
            1074 LOAD_NAME               11 (time)
            1076 LOAD_ATTR               11 (time)
            1086 PRECALL                  0
            1090 CALL                     0
            1100 LOAD_CONST              57 (1000)
            1102 BINARY_OP                5 (*)
            1106 PRECALL                  1
            1110 CALL                     1
            1120 STORE_NAME              71 (_rticket)

208         1122 PUSH_NULL
            1124 LOAD_NAME               50 (str)
            1126 PUSH_NULL
            1128 LOAD_NAME               70 (int)
            1130 PUSH_NULL
            1132 LOAD_NAME               11 (time)
            1134 LOAD_ATTR               11 (time)
            1144 PRECALL                  0
            1148 CALL                     0
            1158 LOAD_CONST              57 (1000)
            1160 BINARY_OP                5 (*)
            1164 PRECALL                  1
            1168 CALL                     1
            1178 PRECALL                  1
            1182 CALL                     1
            1192 LOAD_CONST               1 (None)
            1194 LOAD_CONST              58 (10)
            1196 BUILD_SLICE              2
            1198 BINARY_SUBSCR
            1208 STORE_NAME              72 (ts)

209         1210 PUSH_NULL
            1212 LOAD_NAME                1 (random)
            1214 LOAD_ATTR               55 (choice)
            1224 BUILD_LIST               0
            1226 LOAD_CONST              59 (('US', 'UK', 'CA', 'AU', 'IN', 'BR', 'FR', 'DE', 'IT', 'ES'))
            1228 LIST_EXTEND              1
            1230 PRECALL                  1
            1234 CALL                     1
            1244 STORE_NAME              73 (region)

210         1246 PUSH_NULL
            1248 LOAD_NAME                1 (random)
            1250 LOAD_ATTR               55 (choice)
            1260 BUILD_LIST               0
            1262 LOAD_CONST              59 (('US', 'UK', 'CA', 'AU', 'IN', 'BR', 'FR', 'DE', 'IT', 'ES'))
            1264 LIST_EXTEND              1
            1266 PRECALL                  1
            1270 CALL                     1
            1280 STORE_NAME              74 (region2)

211         1282 PUSH_NULL
            1284 LOAD_NAME                1 (random)
            1286 LOAD_ATTR               55 (choice)
            1296 BUILD_LIST               0
            1298 LOAD_CONST              60 (('us', 'ik', 'ca', 'au', 'in', 'br', 'fr', 'de', 'it', 'es'))
            1300 LIST_EXTEND              1
            1302 PRECALL                  1
            1306 CALL                     1
            1316 STORE_NAME              75 (reeee)

213         1318 LOAD_CONST              49 ('')
            1320 LOAD_METHOD             60 (join)
            1342 BUILD_LIST               0
            1344 LOAD_CONST              61 ('https://api16-normal-c-useast1a.tiktokv.com/passport/email/send_code/?passport-sdk-version=19&iid=')
            1346 LIST_APPEND              1
            1348 LOAD_NAME               58 (install_id)
            1350 FORMAT_VALUE             0
            1352 LIST_APPEND              1
            1354 LOAD_CONST              62 ('&device_id=')
            1356 LIST_APPEND              1
            1358 LOAD_NAME               59 (device_id)
            1360 FORMAT_VALUE             0
            1362 LIST_APPEND              1
            1364 LOAD_CONST              63 ('&ac=wifi&channel=googleplay&aid=1233&app_name=musical_ly&version_code=330603&version_name=33.6.3&device_platform=android&os=android&ab_version=33.6.3&ssmix=a&device_type=')
            1366 LIST_APPEND              1
            1368 LOAD_NAME               56 (device_samsung)
            1370 FORMAT_VALUE             0
            1372 LIST_APPEND              1
            1374 LOAD_CONST              64 ('&device_brand=samsung&language=en&os_api=32&os_version=12&openudid=')
            1376 LIST_APPEND              1
            1378 LOAD_NAME               54 (openudid)
            1380 FORMAT_VALUE             0
            1382 LIST_APPEND              1
            1384 LOAD_CONST              65 ('&manifest_version_code=2023306030&resolution=720*1280&dpi=240&update_version_code=2023306030&_rticket=')
            1386 LIST_APPEND              1
            1388 LOAD_NAME               71 (_rticket)
            1390 FORMAT_VALUE             0
            1392 LIST_APPEND              1
            1394 LOAD_CONST              66 ('&is_pad=0&current_region=')
            1396 LIST_APPEND              1
            1398 LOAD_NAME               73 (region)
            1400 FORMAT_VALUE             0
            1402 LIST_APPEND              1
            1404 LOAD_CONST              67 ('&app_type=normal&sys_region=')
            1406 LIST_APPEND              1
            1408 LOAD_NAME               73 (region)
            1410 FORMAT_VALUE             0
            1412 LIST_APPEND              1
            1414 LOAD_CONST              68 ('&mcc_mnc=')
            1416 LIST_APPEND              1
            1418 PUSH_NULL
            1420 LOAD_NAME                1 (random)
            1422 LOAD_ATTR               55 (choice)
            1432 LOAD_CONST              69 ('31002')
            1434 LOAD_CONST              70 ('41532')
            1436 BUILD_LIST               2
            1438 PRECALL                  1
            1442 CALL                     1
            1452 FORMAT_VALUE             0
            1454 LIST_APPEND              1
            1456 LOAD_CONST              71 ('&timezone_name=Africa%2FNairobi&carrier_region_v2=310&residence=')
            1458 LIST_APPEND              1
            1460 LOAD_NAME               74 (region2)
            1462 FORMAT_VALUE             0
            1464 LIST_APPEND              1
            1466 LOAD_CONST              72 ('&app_language=en&carrier_region=')
            1468 LIST_APPEND              1
            1470 LOAD_NAME               74 (region2)
            1472 FORMAT_VALUE             0
            1474 LIST_APPEND              1
            1476 LOAD_CONST              73 ('&ac2=wifi5g&uoo=0&op_region=')
            1478 LIST_APPEND              1
            1480 LOAD_NAME               74 (region2)
            1482 FORMAT_VALUE             0
            1484 LIST_APPEND              1
            1486 LOAD_CONST              74 ('&timezone_offset=10800&build_number=33.6.3&host_abi=arm64-v8a&locale=en&region=')
            1488 LIST_APPEND              1
            1490 LOAD_NAME               73 (region)
            1492 FORMAT_VALUE             0
            1494 LIST_APPEND              1
            1496 LOAD_CONST              75 ('&ts=')
            1498 LIST_APPEND              1
            1500 LOAD_NAME               72 (ts)
            1502 FORMAT_VALUE             0
            1504 LIST_APPEND              1
            1506 LOAD_CONST              76 ('&cdid=')
            1508 LIST_APPEND              1
            1510 LOAD_NAME               63 (uid)
            1512 FORMAT_VALUE             0
            1514 LIST_APPEND              1
            1516 LOAD_CONST              77 ('&&support_webview=1&reg_store_region=')
            1518 LIST_APPEND              1
            1520 LOAD_NAME               75 (reeee)
            1522 FORMAT_VALUE             0
            1524 LIST_APPEND              1
            1526 LOAD_CONST              78 ('&user_selected_region=0&okhttp_version=4.2.137.49-tiktok&use_store_region_cookie=1')
            1528 LIST_APPEND              1
            1530 PRECALL                  1
            1534 CALL                     1
            1544 STORE_NAME              76 (u)

215         1546 LOAD_CONST              79 ('{}')
            1548 LOAD_METHOD             77 (format)
            1570 PUSH_NULL
            1572 LOAD_NAME               50 (str)
            1574 PUSH_NULL
            1576 LOAD_NAME                7 (secrets)
            1578 LOAD_ATTR               78 (token_hex)
            1588 LOAD_CONST              42 (8)
            1590 PRECALL                  1
            1594 CALL                     1
            1604 LOAD_CONST              80 (2)
            1606 BINARY_OP                5 (*)
            1610 PRECALL                  1
            1614 CALL                     1
            1624 PRECALL                  1
            1628 CALL                     1
            1638 STORE_NAME              79 (sessionid)

216         1640 PUSH_NULL
            1642 LOAD_NAME               50 (str)
            1644 PUSH_NULL
            1646 LOAD_NAME                1 (random)
            1648 LOAD_ATTR               80 (randint)
            1658 LOAD_CONST              57 (1000)
            1660 LOAD_CONST              81 (2500)
            1662 PRECALL                  2
            1666 CALL                     2
            1676 PRECALL                  1
            1680 CALL                     1
            1690 STORE_NAME              81 (pns_event_id)

218         1692 PUSH_NULL
            1694 LOAD_NAME                0 (requests)
            1696 LOAD_ATTR               66 (get)
            1706 LOAD_CONST              82 ('https://api16-normal-c-useast1a.tiktokv.com/passport/email/send_code/?')
            1708 LOAD_CONST              53 ('User-Agent')
            1710 LOAD_CONST              83 ('com.zhiliaoapp.musically/2023303040 (Linux; U; Android 9; en; SM-N975F; Build/PI;tt-ok/3.12.13.4-tiktok)')
            1712 BUILD_MAP                1
            1714 KW_NAMES                55
            1716 PRECALL                  2
            1720 CALL                     2
            1730 LOAD_ATTR               67 (cookies)
            1740 LOAD_METHOD             68 (get_dict)
            1762 PRECALL                  0
            1766 CALL                     0
            1776 LOAD_CONST              84 ('passport_csrf_token')
            1778 BINARY_SUBSCR
            1788 STORE_NAME              82 (passport_csrf_token)

219         1790 PUSH_NULL
            1792 LOAD_NAME               44 (clear)
            1794 PRECALL                  0
            1798 CALL                     0
            1808 POP_TOP

220         1810 PUSH_NULL
            1812 LOAD_NAME               46 (input)
            1814 LOAD_CONST              85 ('يرجا ادخال الاميل : ')
            1816 PRECALL                  1
            1820 CALL                     1
            1830 STORE_NAME              83 (email)

222         1832 LOAD_CONST              86 ('v2')

223         1834 LOAD_CONST              87 ('app')

224         1836 LOAD_CONST              29 ('1')

225         1838 LOAD_CONST              29 ('1')

226         1840 LOAD_CONST              88 ('3436')

227         1842 LOAD_NAME               83 (email)

228         1844 LOAD_CONST              32 ('2')

221         1846 LOAD_CONST              89 (('rules_version', 'account_sdk_source', 'mix_mode', 'multi_login', 'type', 'email', 'email_theme'))
            1848 BUILD_CONST_KEY_MAP      7
            1850 STORE_NAME              84 (d)

231         1852 LOAD_NAME               76 (u)
            1854 STORE_NAME              85 (url)

232         1856 LOAD_CONST              90 ('rules_version=v2&account_sdk_source=app&mix_mode=1&multi_login=1&type=3436&email=')
            1858 LOAD_NAME               83 (email)
            1860 FORMAT_VALUE             0
            1862 LOAD_CONST              91 ('&email_theme=2')
            1864 BUILD_STRING             3
            1866 STORE_NAME              86 (payload)

233         1868 PUSH_NULL
            1870 LOAD_NAME               25 (ttsign)
            1872 LOAD_NAME               85 (url)
            1874 LOAD_METHOD             87 (split)
            1896 LOAD_CONST              92 ('?')
            1898 PRECALL                  1
            1902 CALL                     1
            1912 LOAD_CONST              93 (1)
            1914 BINARY_SUBSCR
            1924 LOAD_NAME               86 (payload)
            1926 LOAD_CONST               1 (None)
            1928 PRECALL                  3
            1932 CALL                     3
            1942 LOAD_METHOD             88 (get_value)
            1964 PRECALL                  0
            1968 CALL                     0
            1978 STORE_NAME              89 (signed)

234         1980 LOAD_NAME               89 (signed)
            1982 LOAD_CONST              94 ('x-gorgon')
            1984 BINARY_SUBSCR
            1994 STORE_NAME              90 (x_gorgon)

236         1996 LOAD_NAME               89 (signed)
            1998 LOAD_CONST              95 ('x-ss-req-ticket')            2000 BINARY_SUBSCR
            2010 STORE_NAME              91 (xss)

237         2012 LOAD_NAME               89 (signed)
            2014 LOAD_CONST              96 ('x-khronos')
            2016 BINARY_SUBSCR
            2026 STORE_NAME              92 (x_khronos)

238         2028 LOAD_NAME               56 (device_samsung)
            2030 LOAD_METHOD             87 (split)
            2052 LOAD_CONST              97 ('-')
            2054 PRECALL                  1
            2058 CALL                     1
            2068 LOAD_CONST              93 (1)
            2070 BINARY_SUBSCR
            2080 STORE_NAME              93 (dev)

240         2082 LOAD_CONST              98 ('store-idc=maliva; store-country-code=iq; install_id=')
            2084 LOAD_NAME               58 (install_id)
            2086 FORMAT_VALUE             0
            2088 LOAD_CONST              99 ('; ttreq=')
            2090 LOAD_NAME               62 (ttreq)
            2092 FORMAT_VALUE             0
            2094 LOAD_CONST             100 ('; passport_csrf_token=')
            2096 LOAD_NAME               82 (passport_csrf_token)
            2098 FORMAT_VALUE             0
            2100 LOAD_CONST             101 ('; passport_csrf_token_default=')
            2102 LOAD_NAME               82 (passport_csrf_token)
            2104 FORMAT_VALUE             0
            2106 LOAD_CONST             102 ('; tt-target-idc=useast1a; d_ticket=5be60d8965e48ce1c19f08b380267389761c4; store-country-code-src=uid; multi_sids=7272516454783714309%3Addadff58d5b29c40f968536697d8a651%7C6755478888983938054%')
            2108 LOAD_NAME               79 (sessionid)
            2110 FORMAT_VALUE             0
            2112 LOAD_CONST             103 ('; cmpl_token=AgQQAPPdF-RPsI3-puZhux0__3QvcLvLv4c5YNHWXw; sid_guard=')
            2114 LOAD_NAME               79 (sessionid)
            2116 FORMAT_VALUE             0
            2118 LOAD_CONST             104 ('%7C1707765785%7C15552000%7CSat%2C+10-Aug-2024+19%3A23%3A05+GMT; uid_tt=ed985d10991a75161799529ed5af4b54385a574e89023fc98f496dd539cdb31e; uid_tt_ss=ed985d10991a75161799529ed5af4b54385a574e89023fc98f496dd539cdb31e; sid_tt=')
            2120 LOAD_NAME               79 (sessionid)
            2122 FORMAT_VALUE             0
            2124 LOAD_CONST             105 ('; sessionid=')
            2126 LOAD_NAME               79 (sessionid)
            2128 FORMAT_VALUE             0
            2130 LOAD_CONST             106 ('; sessionid_ss=')            2132 LOAD_NAME               79 (sessionid)
            2134 FORMAT_VALUE             0
            2136 LOAD_CONST             107 ('; tt-target-idc-sign=S-RP2IHgGFyWT7JhWkGYjNxdMHg-SlI8gmLUoPYQh-xdNQ77-NEOtiIBcY3LQ9Y2oFDtzy2tdDman7948qZOJxgjb9_qEl2s-DmF1wgE02nkio6DV4Sd33rGXDjHNm69BjnuL0uPO9qRjH9lnLgbxhpN2ZDlsbM-ngaySIt9bbDTr8M7tJyHWxqYHoTSGq-OYjeRZmnUQbppq-oDDDfuzwQnQU-MX503k94QXbLC7whfNomrpDUcqLSpi12TOw1-1kpbn8Yf1aDh0DWrOAePhJEFxovM7Txitd9SC1RaV3ATMKkknp1PoZGdQR32UqNAhlW7cZc3VUnqVRGDdFZ38vsI8wr0nwvlG6f1nx85hg2p1sBLGbAfz78fOdRnJ6ILd0tCwaYJA5eYzaQn0ON0-YUYXagMq4DXVnTW2VSNlC9xNIfoTAHA8gE7vVuncl8TU4-ws2MlPkWstH8sRatdzZH1G6qzQCf0s343TtppaTunTliHFVa6J6fzHjvGi8MI; msToken=')
            2138 LOAD_NAME               69 (r199)
            2140 FORMAT_VALUE             0
            2142 BUILD_STRING            20

241         2144 LOAD_NAME               81 (pns_event_id)

243         2146 LOAD_CONST             108 ('com.zhiliaoapp.musically/2023306030 (Linux; U; Android 12; en; ')
            2148 LOAD_NAME               56 (device_samsung)
            2150 FORMAT_VALUE             0
            2152 LOAD_CONST             109 ('; Build/NRD90M.')            2154 LOAD_NAME               93 (dev)
            2156 FORMAT_VALUE             0
            2158 LOAD_CONST             110 ('KSU1AQDC;tt-ok/3.12.13.4-tiktok)')
            2160 BUILD_STRING             5

244         2162 LOAD_NAME               90 (x_gorgon)

245         2164 LOAD_NAME               92 (x_khronos)

246         2166 LOAD_NAME               91 (xss)

239         2168 LOAD_CONST             111 (('Cookie', 'pns_event_id', 'User-Agent', 'X-Gorgon', 'X-Khronos', 'X-SS-REQ-TICKET'))
            2170 BUILD_CONST_KEY_MAP      6
            2172 STORE_NAME              94 (h)

249         2174 PUSH_NULL
            2176 LOAD_NAME                0 (requests)
            2178 LOAD_ATTR               95 (post)
            2188 LOAD_NAME               76 (u)
            2190 LOAD_NAME               94 (h)
            2192 LOAD_NAME               84 (d)
            2194 KW_NAMES               112
            2196 PRECALL                  3
            2200 CALL                     3
            2210 LOAD_ATTR               96 (text)
            2220 STORE_NAME              97 (r)

250         2222 LOAD_CONST             113 ('success')
            2224 LOAD_NAME               97 (r)
            2226 CONTAINS_OP              0
            2228 EXTENDED_ARG             1
            2230 POP_JUMP_FORWARD_IF_FALSE   260 (to 2752)

252         2232 PUSH_NULL
            2234 LOAD_NAME               44 (clear)
            2236 PRECALL                  0
            2240 CALL                     0
            2250 POP_TOP

254         2252 LOAD_CONST             114 ('https://api16-normal-c-useast1a.tiktokv.com/passport/app/email/code_login/?passport-sdk-version=19&iid=')
            2254 LOAD_NAME               58 (install_id)
            2256 FORMAT_VALUE             0
            2258 LOAD_CONST              62 ('&device_id=')
            2260 LOAD_NAME               59 (device_id)
            2262 FORMAT_VALUE             0
            2264 LOAD_CONST              63 ('&ac=wifi&channel=googleplay&aid=1233&app_name=musical_ly&version_code=330603&version_name=33.6.3&device_platform=android&os=android&ab_version=33.6.3&ssmix=a&device_type=')
            2266 LOAD_NAME               56 (device_samsung)
            2268 FORMAT_VALUE             0
            2270 LOAD_CONST              64 ('&device_brand=samsung&language=en&os_api=32&os_version=12&openudid=')
            2272 LOAD_NAME               54 (openudid)
            2274 FORMAT_VALUE             0
            2276 LOAD_CONST              65 ('&manifest_version_code=2023306030&resolution=720*1280&dpi=240&update_version_code=2023306030&_rticket=')
            2278 LOAD_NAME               71 (_rticket)
            2280 FORMAT_VALUE             0
            2282 LOAD_CONST              66 ('&is_pad=0&current_region=')
            2284 LOAD_NAME               73 (region)
            2286 FORMAT_VALUE             0
            2288 LOAD_CONST              67 ('&app_type=normal&sys_region=')
            2290 LOAD_NAME               73 (region)
            2292 FORMAT_VALUE             0
            2294 LOAD_CONST              68 ('&mcc_mnc=')
            2296 PUSH_NULL
            2298 LOAD_NAME                1 (random)
            2300 LOAD_ATTR               55 (choice)
            2310 LOAD_CONST              69 ('31002')
            2312 LOAD_CONST              70 ('41532')
            2314 BUILD_LIST               2
            2316 PRECALL                  1
            2320 CALL                     1
            2330 FORMAT_VALUE             0
            2332 LOAD_CONST              71 ('&timezone_name=Africa%2FNairobi&carrier_region_v2=310&residence=')
            2334 LOAD_NAME               74 (region2)
            2336 FORMAT_VALUE             0
            2338 LOAD_CONST              72 ('&app_language=en&carrier_region=')
            2340 LOAD_NAME               74 (region2)
            2342 FORMAT_VALUE             0
            2344 LOAD_CONST              73 ('&ac2=wifi5g&uoo=0&op_region=')
            2346 LOAD_NAME               74 (region2)
            2348 FORMAT_VALUE             0
            2350 LOAD_CONST              74 ('&timezone_offset=10800&build_number=33.6.3&host_abi=arm64-v8a&locale=en&region=')
            2352 LOAD_NAME               73 (region)
            2354 FORMAT_VALUE             0
            2356 LOAD_CONST              75 ('&ts=')
            2358 LOAD_NAME               72 (ts)
            2360 FORMAT_VALUE             0
            2362 LOAD_CONST              76 ('&cdid=')
            2364 LOAD_NAME               63 (uid)
            2366 FORMAT_VALUE             0
            2368 LOAD_CONST             115 ('&support_webview=1&okhttp_version=4.2.137.49-tiktok&use_store_region_cookie=1')
            2370 BUILD_STRING            29
            2372 STORE_NAME              98 (u1)

255         2374 LOAD_CONST              49 ('')
            2376 LOAD_METHOD             60 (join)
            2398 LOAD_CONST             116 (<code object <listcomp> at 0x7cb6204ff0, file "", line 255>)
            2400 MAKE_FUNCTION            0
            2402 PUSH_NULL
            2404 LOAD_NAME               46 (input)
            2406 LOAD_CONST             117 ('يرجا ادخال الكود : ')
            2408 PRECALL                  1
            2412 CALL                     1
            2422 GET_ITER
            2424 PRECALL                  0
            2428 CALL                     0
            2438 PRECALL                  1
            2442 CALL                     1

256         2452 LOAD_CONST              87 ('app')

258         2454 LOAD_CONST              29 ('1')

259         2456 LOAD_CONST              88 ('3436')

260         2458 LOAD_NAME               83 (email)

261         2460 LOAD_CONST              29 ('1')

255         2462 LOAD_CONST             118 (('code', 'account_sdk_source', 'multi_login', 'type', 'email', 'mix_mode'))
            2464 BUILD_CONST_KEY_MAP      6
            2466 STORE_NAME              99 (dd)

262         2468 PUSH_NULL
            2470 LOAD_NAME                0 (requests)
            2472 LOAD_ATTR               95 (post)
            2482 LOAD_NAME               98 (u1)
            2484 LOAD_NAME               94 (h)
            2486 LOAD_NAME               99 (dd)
            2488 KW_NAMES               112
            2490 PRECALL                  3
            2494 CALL                     3
            2504 STORE_NAME              97 (r)

263         2506 LOAD_CONST             113 ('success')
            2508 LOAD_NAME               97 (r)
            2510 LOAD_ATTR               96 (text)
            2520 CONTAINS_OP              0
            2522 POP_JUMP_FORWARD_IF_FALSE    76 (to 2676)

264         2524 LOAD_NAME               97 (r)
            2526 LOAD_METHOD             10 (json)
            2548 PRECALL                  0
            2552 CALL                     0
            2562 LOAD_CONST             119 ('data')
            2564 BINARY_SUBSCR
            2574 LOAD_CONST             120 ('session_key')
            2576 BINARY_SUBSCR
            2586 STORE_NAME             100 (ses1)

265         2588 PUSH_NULL
            2590 LOAD_NAME               44 (clear)
            2592 PRECALL                  0
            2596 CALL                     0
            2606 POP_TOP

266         2608 PUSH_NULL
            2610 LOAD_NAME               45 (print)
            2612 LOAD_CONST             121 ('قم بنسخ السيزن الخاص بيك')
            2614 PRECALL                  1
            2618 CALL                     1
            2628 POP_TOP

267         2630 PUSH_NULL
            2632 LOAD_NAME               45 (print)
            2634 LOAD_CONST             122 (' ')
            2636 PRECALL                  1
            2640 CALL                     1
            2650 POP_TOP

268         2652 PUSH_NULL
            2654 LOAD_NAME               45 (print)
            2656 LOAD_NAME              100 (ses1)
            2658 PRECALL                  1
            2662 CALL                     1
            2672 POP_TOP
            2674 JUMP_FORWARD            76 (to 2828)

269     >>  2676 LOAD_CONST             123 ('Verification code is expired or incorrect. Try again.')
            2678 LOAD_NAME               97 (r)
            2680 LOAD_ATTR               96 (text)
            2690 CONTAINS_OP              0
            2692 POP_JUMP_FORWARD_IF_FALSE    12 (to 2718)

270         2694 PUSH_NULL
            2696 LOAD_NAME               45 (print)
            2698 LOAD_CONST             124 ('الكود خطاء اعد المحاوله من جديد')
            2700 PRECALL                  1
            2704 CALL                     1
            2714 POP_TOP
            2716 JUMP_FORWARD            55 (to 2828)

272     >>  2718 PUSH_NULL
            2720 LOAD_NAME               45 (print)
            2722 LOAD_NAME               97 (r)
            2724 LOAD_ATTR               96 (text)
            2734 PRECALL                  1
            2738 CALL                     1
            2748 POP_TOP
            2750 JUMP_FORWARD            38 (to 2828)

273     >>  2752 LOAD_CONST             125 ("Account doesn't exist")
            2754 LOAD_NAME               97 (r)
            2756 CONTAINS_OP              0
            2758 POP_JUMP_FORWARD_IF_FALSE    12 (to 2784)

274         2760 PUSH_NULL
            2762 LOAD_NAME               45 (print)
            2764 LOAD_CONST             126 ('هذا الاميل ليس به حساب ')
            2766 PRECALL                  1
            2770 CALL                     1
            2780 POP_TOP
            2782 JUMP_FORWARD            22 (to 2828)

276     >>  2784 PUSH_NULL
            2786 LOAD_NAME               45 (print)
            2788 LOAD_CONST             127 ('الكثي من المحاولات يرجه اعادة بعد بضع دقائق')
            2790 PRECALL                  1
            2794 CALL                     1
            2804 POP_TOP

277         2806 PUSH_NULL
            2808 LOAD_NAME               45 (print)
            2810 LOAD_NAME               97 (r)
            2812 PRECALL                  1
            2816 CALL                     1
            2826 POP_TOP

278     >>  2828 LOAD_NAME               47 (Get_aobsh)
            2830 LOAD_CONST              32 ('2')
            2832 CONTAINS_OP              0
            2834 EXTENDED_ARG             1
            2836 POP_JUMP_FORWARD_IF_FALSE   482 (to 3802)

279         2838 LOAD_CONST               0 (0)
            2840 STORE_GLOBAL           101 (e)

280         2842 LOAD_CONST               0 (0)
            2844 STORE_GLOBAL            24 (er)

281         2846 LOAD_CONST             128 ('https://raw.githubusercontent.com/TheSpeedX/PROXY-List/master/http.txt')
            2848 STORE_NAME             102 (PR1)

282         2850 LOAD_CONST             129 ('https://raw.githubusercontent.com/TheSpeedX/PROXY-List/master/socks5.txt')
            2852 STORE_NAME             103 (PR2)

283         2854 LOAD_CONST             130 ('https://raw.githubusercontent.com/TheSpeedX/PROXY-List/master/socks4.txt')
            2856 STORE_NAME             104 (PR3)

284         2858 PUSH_NULL
            2860 LOAD_NAME               44 (clear)
            2862 PRECALL                  0
            2866 CALL                     0
            2876 POP_TOP

285         2878 BUILD_LIST               0
            2880 STORE_NAME              20 (ls)

286         2882 NOP

287         2884 PUSH_NULL
            2886 LOAD_NAME                4 (os)
            2888 LOAD_ATTR              105 (remove)
            2898 LOAD_CONST             131 ('SAIPR_REPORT_AFRIT_SAIPR.txt')
            2900 PRECALL                  1
            2904 CALL                     1
            2914 POP_TOP
            2916 JUMP_FORWARD             7 (to 2932)
        >>  2918 PUSH_EXC_INFO

288         2920 POP_TOP

289         2922 POP_EXCEPT
            2924 JUMP_FORWARD             3 (to 2932)
        >>  2926 COPY                     3
            2928 POP_EXCEPT
            2930 RERAISE                  1

290     >>  2932 NOP

291         2934 PUSH_NULL
            2936 LOAD_NAME                4 (os)
            2938 LOAD_ATTR              105 (remove)
            2948 LOAD_CONST             132 ('PROXY_AFRIT_TIK.txt')
            2950 PRECALL                  1
            2954 CALL                     1
            2964 POP_TOP
            2966 JUMP_FORWARD             7 (to 2982)
        >>  2968 PUSH_EXC_INFO

292         2970 POP_TOP

293         2972 POP_EXCEPT
            2974 JUMP_FORWARD             3 (to 2982)
        >>  2976 COPY                     3
            2978 POP_EXCEPT
            2980 RERAISE                  1

294     >>  2982 PUSH_NULL
            2984 LOAD_NAME                0 (requests)
            2986 LOAD_ATTR               66 (get)
            2996 LOAD_CONST             133 ('%s')
            2998 LOAD_NAME              102 (PR1)
            3000 BINARY_OP                6 (%)
            3004 PRECALL                  1
            3008 CALL                     1
            3018 LOAD_ATTR               96 (text)
            3028 STORE_NAME             106 (DA3)

295         3030 PUSH_NULL
            3032 LOAD_NAME              107 (open)
            3034 LOAD_CONST             132 ('PROXY_AFRIT_TIK.txt')
            3036 LOAD_CONST             134 ('a')
            3038 PRECALL                  2
            3042 CALL                     2
            3052 BEFORE_WITH
            3054 STORE_NAME             108 (Prox1y)

296         3056 LOAD_NAME              108 (Prox1y)
            3058 LOAD_METHOD            109 (write)
            3080 LOAD_NAME              106 (DA3)
            3082 LOAD_CONST             135 ('\n')
            3084 BINARY_OP                0 (+)
            3088 PRECALL                  1
            3092 CALL                     1
            3102 POP_TOP

295         3104 LOAD_CONST               1 (None)
            3106 LOAD_CONST               1 (None)
            3108 LOAD_CONST               1 (None)
            3110 PRECALL                  2
            3114 CALL                     2
            3124 POP_TOP
            3126 JUMP_FORWARD            11 (to 3150)
        >>  3128 PUSH_EXC_INFO
            3130 WITH_EXCEPT_START
            3132 POP_JUMP_FORWARD_IF_TRUE     4 (to 3142)
            3134 RERAISE                  2
        >>  3136 COPY                     3
            3138 POP_EXCEPT
            3140 RERAISE                  1
        >>  3142 POP_TOP
            3144 POP_EXCEPT
            3146 POP_TOP
            3148 POP_TOP

297     >>  3150 PUSH_NULL
            3152 LOAD_NAME                0 (requests)
            3154 LOAD_ATTR               66 (get)
            3164 LOAD_CONST             133 ('%s')
            3166 LOAD_NAME              103 (PR2)
            3168 BINARY_OP                6 (%)
            3172 PRECALL                  1
            3176 CALL                     1
            3186 LOAD_ATTR               96 (text)
            3196 STORE_NAME             110 (DA1)

298         3198 PUSH_NULL
            3200 LOAD_NAME              107 (open)
            3202 LOAD_CONST             132 ('PROXY_AFRIT_TIK.txt')
            3204 LOAD_CONST             134 ('a')
            3206 PRECALL                  2
            3210 CALL                     2
            3220 BEFORE_WITH
            3222 STORE_NAME             108 (Prox1y)

299         3224 LOAD_NAME              108 (Prox1y)
            3226 LOAD_METHOD            109 (write)
            3248 LOAD_NAME              110 (DA1)
            3250 LOAD_CONST             135 ('\n')
            3252 BINARY_OP                0 (+)
            3256 PRECALL                  1
            3260 CALL                     1
            3270 POP_TOP

298         3272 LOAD_CONST               1 (None)
            3274 LOAD_CONST               1 (None)
            3276 LOAD_CONST               1 (None)
            3278 PRECALL                  2
            3282 CALL                     2
            3292 POP_TOP
            3294 JUMP_FORWARD            11 (to 3318)
        >>  3296 PUSH_EXC_INFO
            3298 WITH_EXCEPT_START
            3300 POP_JUMP_FORWARD_IF_TRUE     4 (to 3310)
            3302 RERAISE                  2
        >>  3304 COPY                     3
            3306 POP_EXCEPT
            3308 RERAISE                  1
        >>  3310 POP_TOP
            3312 POP_EXCEPT
            3314 POP_TOP
            3316 POP_TOP

300     >>  3318 PUSH_NULL
            3320 LOAD_NAME                0 (requests)
            3322 LOAD_ATTR               66 (get)
            3332 LOAD_CONST             133 ('%s')
            3334 LOAD_NAME              104 (PR3)
            3336 BINARY_OP                6 (%)
            3340 PRECALL                  1
            3344 CALL                     1
            3354 LOAD_ATTR               96 (text)
            3364 STORE_NAME             111 (DA2)

301         3366 PUSH_NULL
            3368 LOAD_NAME              107 (open)
            3370 LOAD_CONST             132 ('PROXY_AFRIT_TIK.txt')
            3372 LOAD_CONST             134 ('a')
            3374 PRECALL                  2
            3378 CALL                     2
            3388 BEFORE_WITH
            3390 STORE_NAME             108 (Prox1y)

302         3392 LOAD_NAME              108 (Prox1y)
            3394 LOAD_METHOD            109 (write)
            3416 LOAD_NAME              111 (DA2)
            3418 LOAD_CONST             135 ('\n')
            3420 BINARY_OP                0 (+)
            3424 PRECALL                  1
            3428 CALL                     1
            3438 POP_TOP

301         3440 LOAD_CONST               1 (None)
            3442 LOAD_CONST               1 (None)
            3444 LOAD_CONST               1 (None)
            3446 PRECALL                  2
            3450 CALL                     2
            3460 POP_TOP
            3462 JUMP_FORWARD            11 (to 3486)
        >>  3464 PUSH_EXC_INFO
            3466 WITH_EXCEPT_START
            3468 POP_JUMP_FORWARD_IF_TRUE     4 (to 3478)
            3470 RERAISE                  2
        >>  3472 COPY                     3
            3474 POP_EXCEPT
            3476 RERAISE                  1
        >>  3478 POP_TOP
            3480 POP_EXCEPT
            3482 POP_TOP
            3484 POP_TOP

303     >>  3486 NOP

304         3488 PUSH_NULL
            3490 LOAD_NAME              107 (open)
            3492 LOAD_CONST             132 ('PROXY_AFRIT_TIK.txt')
            3494 LOAD_CONST             136 ('r')
            3496 PRECALL                  2
            3500 CALL                     2
            3510 LOAD_METHOD            112 (read)
            3532 PRECALL                  0
            3536 CALL                     0
            3546 LOAD_METHOD            113 (splitlines)
            3568 PRECALL                  0
            3572 CALL                     0
            3582 STORE_NAME              28 (O)

305         3584 LOAD_NAME               28 (O)
            3586 GET_ITER
        >>  3588 FOR_ITER                23 (to 3636)
            3590 STORE_NAME             114 (prox)

306         3592 LOAD_NAME               20 (ls)
            3594 LOAD_METHOD            115 (append)
            3616 LOAD_NAME              114 (prox)
            3618 PRECALL                  1
            3622 CALL                     1
            3632 POP_TOP
            3634 JUMP_BACKWARD           24 (to 3588)

305     >>  3636 JUMP_FORWARD            28 (to 3694)
        >>  3638 PUSH_EXC_INFO

307         3640 POP_TOP
            3642 PUSH_NULL
            3644 LOAD_NAME               45 (print)
            3646 LOAD_CONST             137 ('STOP')
            3648 PRECALL                  1
            3652 CALL                     1
            3662 POP_TOP
            3664 PUSH_NULL
            3666 LOAD_NAME              116 (exit)
            3668 PRECALL                  0
            3672 CALL                     0
            3682 POP_TOP
            3684 POP_EXCEPT
            3686 JUMP_FORWARD             3 (to 3694)
        >>  3688 COPY                     3
            3690 POP_EXCEPT
            3692 RERAISE                  1

308     >>  3694 LOAD_CONST             138 (<code object af at 0x7f464a5570, file "", line 308>)
            3696 MAKE_FUNCTION            0
            3698 STORE_NAME             117 (af)

320         3700 PUSH_NULL
            3702 LOAD_NAME               61 (range)
            3704 LOAD_CONST             139 (300)
            3706 PRECALL                  1
            3710 CALL                     1
            3720 GET_ITER
        >>  3722 FOR_ITER                39 (to 3802)
            3724 STORE_NAME             118 (i)

321         3726 PUSH_NULL
            3728 LOAD_NAME                5 (threading)
            3730 LOAD_ATTR              119 (Thread)
            3740 LOAD_NAME              117 (af)
            3742 KW_NAMES               140
            3744 PRECALL                  1
            3748 CALL                     1
            3758 STORE_NAME             120 (t)

322         3760 LOAD_NAME              120 (t)
            3762 LOAD_METHOD            121 (start)
            3784 PRECALL                  0
            3788 CALL                     0
            3798 POP_TOP
            3800 JUMP_BACKWARD           40 (to 3722)

323     >>  3802 LOAD_NAME               47 (Get_aobsh)
            3804 LOAD_CONST              34 ('3')
            3806 CONTAINS_OP              0
            3808 POP_JUMP_FORWARD_IF_FALSE   203 (to 4216)

324         3810 PUSH_NULL
            3812 LOAD_NAME               45 (print)
            3814 LOAD_CONST             141 ('\nالسلام عليكم\nوياكم خادمك الصغير \nالمبرمج علــش\nالحساب الرسمي ع التلكرام\n@f8f11\nالقناة الرسمية ع التلكرام\n@gx1gx1\nالادات كل اتصالاتها مسحوبه\nمن البرنامج الرسمي\nلشركة تيكتوك اصدار\n33.3.4\nالادات تبلغ ب3 انواع اجهزه\nاوبو وسامسونك وريلمي فقط\nوكل جهاز وله مشتقاته\nوتبلغ باكثر من 10 لغات\nواكثر من 10 دول\nوباكثر من الاف  الايبيات\nويتوفر بها حسابات لهدم الحساب\nوتخلل به وللشك بشركه \nانه ينتهك\nتابع الخطوات \nلكي تعرف تزيل الحسابات\nالقويه وضعيفه\n@==========================@\n')
            3816 PRECALL                  1
            3820 CALL                     1
            3830 POP_TOP

350         3832 PUSH_NULL
            3834 LOAD_NAME               46 (input)
            3836 LOAD_CONST             142 ('أضغط انتر للتكمله')
            3838 PRECALL                  1
            3842 CALL                     1
            3852 POP_TOP

351         3854 PUSH_NULL
            3856 LOAD_NAME               44 (clear)
            3858 PRECALL                  0
            3862 CALL                     0
            3872 POP_TOP

352         3874 PUSH_NULL
            3876 LOAD_NAME               45 (print)
            3878 LOAD_CONST             143 ('\nلتطيير اي حساب مهم كانت قوته\nلازم تتبع الخطوات الي اذكرهن حرفين\nتتبعهن خطوه بخطوه تخطاء بخطوه\nراح يكون صعب اطير الحساب\n@==================================@\n')
            3880 PRECALL                  1
            3884 CALL                     1
            3894 POP_TOP

359         3896 PUSH_NULL
            3898 LOAD_NAME               46 (input)
            3900 LOAD_CONST             142 ('أضغط انتر للتكمله')
            3902 PRECALL                  1
            3906 CALL                     1
            3916 POP_TOP

360         3918 PUSH_NULL
            3920 LOAD_NAME               44 (clear)
            3922 PRECALL                  0
            3926 CALL                     0
            3936 POP_TOP

361         3938 PUSH_NULL
            3940 LOAD_NAME               45 (print)
            3942 LOAD_CONST             144 ('\nالخطوه الاوله\nلازم تسحب سيزن ايدي\n30 حساب اقل شي\nوكل 3 ايام او بلحد الادنا سبوع\nلازم تغير الحسابات\nوتكدر ترجعلهن السبوع الي بعده\nوكذالك تسحب سيزنات جديده\nرقم واحد لسحب السيزن داخل الادات\nولازم تسحب فقط من الادات\n@================================@\n')
            3944 PRECALL                  1
            3948 CALL                     1
            3958 POP_TOP

373         3960 PUSH_NULL
            3962 LOAD_NAME               46 (input)
            3964 LOAD_CONST             142 ('أضغط انتر للتكمله')
            3966 PRECALL                  1
            3970 CALL                     1
            3980 POP_TOP

374         3982 PUSH_NULL
            3984 LOAD_NAME               44 (clear)
            3986 PRECALL                  0
            3990 CALL                     0
            4000 POP_TOP

375         4002 PUSH_NULL
            4004 LOAD_NAME               45 (print)
            4006 LOAD_CONST             145 ('\nالخطوه الثانيه \nتسحب بروكسي مايقل\nعن 500 بروكسي\nوبعد استخدامك لسحب البروكسي\nفعلم ان البروكسيات انتهن \nوماراح يخدمن بشي \nغير الضرر الك\nفلازم تعيد السحب من جديد\n@=========================@\n')
            4008 PRECALL                  1
            4012 CALL                     1
            4022 POP_TOP

386         4024 PUSH_NULL
            4026 LOAD_NAME               46 (input)
            4028 LOAD_CONST             142 ('أضغط انتر للتكمله')
            4030 PRECALL                  1
            4034 CALL                     1
            4044 POP_TOP

387         4046 PUSH_NULL
            4048 LOAD_NAME               44 (clear)
            4050 PRECALL                  0
            4054 CALL                     0
            4064 POP_TOP

388         4066 PUSH_NULL
            4068 LOAD_NAME               45 (print)
            4070 LOAD_CONST             146 ('\nالخطوه الثالثه\nتقوم بابلاغ ع الحساب فقط من\nالسيزنات المتوفره داخل الادات\nولازم \nتشوف انو كل السيزنات بلغن ع الحساب\nوبهذي الحاله راح تكدر تعيد تشغيل الادات\nلان الحساب نهدم جذرين\n@========================================@\n')
            4072 PRECALL                  1
            4076 CALL                     1
            4086 POP_TOP

398         4088 PUSH_NULL
            4090 LOAD_NAME               46 (input)
            4092 LOAD_CONST             142 ('أضغط انتر للتكمله')
            4094 PRECALL                  1
            4098 CALL                     1
            4108 POP_TOP

399         4110 PUSH_NULL
            4112 LOAD_NAME               44 (clear)
            4114 PRECALL                  0
            4118 CALL                     0
            4128 POP_TOP

400         4130 PUSH_NULL
            4132 LOAD_NAME               45 (print)
            4134 LOAD_CONST             147 ('\nالخطوه الرابعه\nوهنا اول خطوه مهمه الك\nلازم تسويه ركز وياي\nانته سحبت سيزن ايدي\nمن 30 حساب\nتجي تاخذ من 30 سيزن\n20 تخصصهم فقط البدايت\nالبلاغ الاوليه\nهنا انته مجهز بروكسي 500 جديد\nوتختار البلاغ كون الي تشوف\nالحساب المنتهك بي\nوتخلي 20 سيزن\nوتخلهم يبلغن\nلحد متشوف كل الفيدوهات انضربن\n@===============================@\n')
            4136 PRECALL                  1
            4140 CALL                     1
            4150 POP_TOP

417         4152 PUSH_NULL
            4154 LOAD_NAME               46 (input)
            4156 LOAD_CONST             142 ('أضغط انتر للتكمله')
            4158 PRECALL                  1
            4162 CALL                     1
            4172 POP_TOP

418         4174 PUSH_NULL
            4176 LOAD_NAME               44 (clear)
            4178 PRECALL                  0
            4182 CALL                     0
            4192 POP_TOP

419         4194 PUSH_NULL
            4196 LOAD_NAME               45 (print)
            4198 LOAD_CONST             148 ('\nالخطوه الخامسه\nوهي ثاني خطوه مهمه\nيكون ساحب 500 بروكسي جديد\nوبقن 10 سيزنات\nمن 30 سيزن\nوهذا الشي راجعلك تكدر تكثرهن \nالمهم يكونن مختلفات مامتشابهات بلي بلغت بيهن\nوكذالك تعيد ضرب الحساب بيهن\nويفضل تبلغ بيهن بلاغ اخر\nوهذي نسبت 75%\nراح يطير عنك الحساب اذا\nطبقت الخطوات\nوشرح مثل مافهمتك بيهن\nوماراح يصعب عليك اي حساب \nانشالله\nواذا شفت حساب مابي انتهاكات\nوقوي ضاعف السيزنات اكثر راح اجيب ازالته \n100%\n')
            4200 PRECALL                  1
            4204 CALL                     1
            4214 POP_TOP

439     >>  4216 LOAD_NAME               47 (Get_aobsh)
            4218 LOAD_CONST              36 ('4')
            4220 CONTAINS_OP              0
            4222 EXTENDED_ARG            11
            4224 POP_JUMP_FORWARD_IF_FALSE  2989 (to 10204)

440         4226 PUSH_NULL
            4228 LOAD_NAME               44 (clear)
            4230 PRECALL                  0
            4234 CALL                     0
            4244 POP_TOP

441         4246 BUILD_LIST               0
            4248 LOAD_CONST             149 (('z1.h4', '94qr4', ' z1.h4', ' 94qr4', 'z1.h4 ', '94qr4 ', 'fwd1'))
            4250 LIST_EXTEND              1
            4252 STORE_NAME             122 (usr)

442         4254 PUSH_NULL
            4256 LOAD_NAME               46 (input)
            4258 LOAD_CONST             150 ('       ')
            4260 LOAD_NAME               30 (X)
            4262 FORMAT_VALUE             0
            4264 LOAD_CONST              28 ('[')
            4266 LOAD_NAME               31 (F)
            4268 FORMAT_VALUE             0
            4270 LOAD_CONST              38 ('×')
            4272 LOAD_NAME               30 (X)
            4274 FORMAT_VALUE             0
            4276 LOAD_CONST              39 (']')
            4278 LOAD_NAME               29 (Z)
            4280 FORMAT_VALUE             0
            4282 LOAD_CONST             151 (' Target username - يوزر الضحيه  :  ')
            4284 BUILD_STRING             9
            4286 LOAD_NAME               32 (L)
            4288 BINARY_OP                0 (+)
            4292 PRECALL                  1
            4296 CALL                     1
            4306 STORE_NAME             123 (g)

443         4308 PUSH_NULL
            4310 LOAD_NAME               44 (clear)
            4312 PRECALL                  0
            4316 CALL                     0
            4326 POP_TOP

444         4328 LOAD_NAME              123 (g)
            4330 LOAD_NAME              122 (usr)
            4332 CONTAINS_OP              0
            4334 POP_JUMP_FORWARD_IF_FALSE    22 (to 4380)

445         4336 PUSH_NULL
            4338 LOAD_NAME               45 (print)
            4340 LOAD_CONST             152 ('علــــش🔹')
            4342 PRECALL                  1
            4346 CALL                     1
            4356 POP_TOP
            4358 PUSH_NULL
            4360 LOAD_NAME              116 (exit)
            4362 PRECALL                  0
            4366 CALL                     0
            4376 POP_TOP
            4378 JUMP_FORWARD             1 (to 4382)

447     >>  4380 NOP

448     >>  4382 NOP

449         4384 LOAD_CONST             153 ('user-agent')
            4386 LOAD_CONST             154 ('Mozilla/5.0 (Linux; Android 6.0; Nexus 5 Build/MRA58N) AppleWebKit/537.36 (KHTML, like Gecko) Chrome/86.0.4240.198 Mobile Safari/537.36')
            4388 BUILD_MAP                1
            4390 STORE_NAME             124 (headers)

450         4392 PUSH_NULL
            4394 LOAD_NAME                0 (requests)
            4396 LOAD_ATTR               66 (get)
            4406 LOAD_CONST             155 ('https://www.tiktok.com/@')
            4408 LOAD_NAME              123 (g)
            4410 FORMAT_VALUE             0
            4412 BUILD_STRING             2
            4414 LOAD_NAME              124 (headers)
            4416 KW_NAMES                55
            4418 PRECALL                  2
            4422 CALL                     2
            4432 LOAD_ATTR               96 (text)
            4442 LOAD_METHOD             87 (split)
            4464 LOAD_CONST             156 ('"userInfo"')
            4466 PRECALL                  1
            4470 CALL                     1
            4480 LOAD_CONST              93 (1)
            4482 BINARY_SUBSCR
            4492 LOAD_METHOD             87 (split)
            4514 LOAD_CONST             157 ('"statusMsg":"')
            4516 PRECALL                  1
            4520 CALL                     1
            4530 LOAD_CONST               0 (0)
            4532 BINARY_SUBSCR
            4542 STORE_NAME              97 (r)

452         4544 LOAD_NAME               97 (r)
            4546 LOAD_METHOD             87 (split)
            4568 LOAD_CONST             158 ('"secUid":"')
            4570 PRECALL                  1
            4574 CALL                     1
            4584 LOAD_CONST              93 (1)
            4586 BINARY_SUBSCR
            4596 LOAD_METHOD             87 (split)
            4618 LOAD_CONST             159 ('",')
            4620 PRECALL                  1
            4624 CALL                     1
            4634 LOAD_CONST               0 (0)
            4636 BINARY_SUBSCR
            4646 STORE_NAME             125 (ur)

453         4648 LOAD_NAME               97 (r)
            4650 LOAD_METHOD             87 (split)
            4672 LOAD_CONST             160 ('"user":{"id":"')
            4674 PRECALL                  1
            4678 CALL                     1
            4688 LOAD_CONST              93 (1)
            4690 BINARY_SUBSCR
            4700 LOAD_METHOD             87 (split)
            4722 LOAD_CONST             159 ('",')
            4724 PRECALL                  1
            4728 CALL                     1
            4738 LOAD_CONST               0 (0)
            4740 BINARY_SUBSCR
            4750 STORE_NAME             126 (id)

454         4752 LOAD_NAME               97 (r)
            4754 LOAD_METHOD             87 (split)
            4776 LOAD_CONST             161 ('"nickname":"')
            4778 PRECALL                  1
            4782 CALL                     1
            4792 LOAD_CONST              93 (1)
            4794 BINARY_SUBSCR
            4804 LOAD_METHOD             87 (split)
            4826 LOAD_CONST             159 ('",')
            4828 PRECALL                  1
            4832 CALL                     1
            4842 LOAD_CONST               0 (0)
            4844 BINARY_SUBSCR
            4854 STORE_NAME             127 (nickname)
            4856 JUMP_FORWARD            28 (to 4914)
        >>  4858 PUSH_EXC_INFO

455         4860 POP_TOP
            4862 PUSH_NULL
            4864 LOAD_NAME               45 (print)
            4866 LOAD_CONST             162 ('◻️اكتب يوزر الضحية◻️')
            4868 PRECALL                  1
            4872 CALL                     1
            4882 POP_TOP
            4884 PUSH_NULL
            4886 LOAD_NAME              116 (exit)
            4888 PRECALL                  0
            4892 CALL                     0
            4902 POP_TOP
            4904 POP_EXCEPT
            4906 JUMP_FORWARD             3 (to 4914)
        >>  4908 COPY                     3
            4910 POP_EXCEPT
            4912 RERAISE                  1

456     >>  4914 PUSH_NULL
            4916 LOAD_NAME               44 (clear)
            4918 PRECALL                  0
            4922 CALL                     0
            4932 POP_TOP

457         4934 BUILD_LIST               0
            4936 STORE_NAME             128 (uid1)

459         4938 PUSH_NULL
            4940 LOAD_NAME               45 (print)
            4942 LOAD_NAME               29 (Z)
            4944 FORMAT_VALUE             0
            4946 LOAD_CONST              28 ('[')
            4948 LOAD_NAME               31 (F)
            4950 FORMAT_VALUE             0
            4952 LOAD_CONST              29 ('1')
            4954 LOAD_NAME               29 (Z)
            4956 FORMAT_VALUE             0
            4958 LOAD_CONST              30 ('] ')
            4960 LOAD_NAME               41 (C1)
            4962 FORMAT_VALUE             0
            4964 LOAD_CONST             163 ('سيزن من الادات😎')            4966 BUILD_STRING             8
            4968 PRECALL                  1
            4972 CALL                     1
            4982 POP_TOP

460         4984 PUSH_NULL
            4986 LOAD_NAME               45 (print)
            4988 LOAD_NAME               29 (Z)
            4990 FORMAT_VALUE             0
            4992 LOAD_CONST              28 ('[')
            4994 LOAD_NAME               31 (F)
            4996 FORMAT_VALUE             0
            4998 LOAD_CONST              32 ('2')
            5000 LOAD_NAME               29 (Z)
            5002 FORMAT_VALUE             0
            5004 LOAD_CONST              30 ('] ')
            5006 LOAD_NAME               41 (C1)
            5008 FORMAT_VALUE             0
            5010 LOAD_CONST             164 ('سيزن خاص بيك🔥')
            5012 BUILD_STRING             8
            5014 PRECALL                  1
            5018 CALL                     1
            5028 POP_TOP

461         5030 PUSH_NULL
            5032 LOAD_NAME               46 (input)
            5034 LOAD_NAME               30 (X)
            5036 FORMAT_VALUE             0
            5038 LOAD_CONST              28 ('[')
            5040 LOAD_NAME               31 (F)
            5042 FORMAT_VALUE             0
            5044 LOAD_CONST              38 ('×')
            5046 LOAD_NAME               30 (X)
            5048 FORMAT_VALUE             0
            5050 LOAD_CONST              39 (']')
            5052 LOAD_NAME               29 (Z)
            5054 FORMAT_VALUE             0
            5056 LOAD_CONST              40 (' اختار : ')
            5058 BUILD_STRING             8
            5060 LOAD_NAME               32 (L)
            5062 BINARY_OP                0 (+)
            5066 PRECALL                  1
            5070 CALL                     1
            5080 STORE_NAME             129 (aobsh)

462         5082 PUSH_NULL
            5084 LOAD_NAME               44 (clear)
            5086 PRECALL                  0
            5090 CALL                     0
            5100 POP_TOP

463         5102 LOAD_NAME              129 (aobsh)
            5104 LOAD_CONST              29 ('1')
            5106 COMPARE_OP               2 (==)
            5112 POP_JUMP_FORWARD_IF_FALSE   118 (to 5350)

464         5114 NOP

466         5116 LOAD_CONST             153 ('user-agent')
            5118 LOAD_CONST             165 ('Mozilla/5.0 (Windows NT 10.0; Win64; x64) AppleWebKit/537.36 (KHTML, like Gecko) Chrome/109.0.0.0 Safari/537.36')
            5120 BUILD_MAP                1
            5122 STORE_NAME             130 (h3)

468         5124 PUSH_NULL
            5126 LOAD_NAME                0 (requests)
            5128 LOAD_ATTR              131 (head)
            5138 LOAD_CONST             166 ('https://www.tiktok.com/')
            5140 LOAD_NAME              130 (h3)
            5142 KW_NAMES                55
            5144 PRECALL                  2
            5148 CALL                     2
            5158 LOAD_ATTR               67 (cookies)
            5168 LOAD_METHOD             68 (get_dict)
            5190 PRECALL                  0
            5194 CALL                     0
            5204 LOAD_CONST             167 ('ttwid')
            5206 BINARY_SUBSCR
            5216 STORE_NAME             132 (ttwid)
            5218 JUMP_FORWARD            65 (to 5350)
        >>  5220 PUSH_EXC_INFO

469         5222 LOAD_NAME                0 (requests)
            5224 LOAD_ATTR              133 (exceptions)
            5234 LOAD_ATTR              134 (ConnectionError)
            5244 CHECK_EXC_MATCH
            5246 POP_JUMP_FORWARD_IF_FALSE    24 (to 5296)
            5248 POP_TOP

470         5250 PUSH_NULL
            5252 LOAD_NAME               45 (print)
            5254 LOAD_CONST             168 ('يرجا التاكد من النت واعد المحاوله مره اخره')
            5256 PRECALL                  1
            5260 CALL                     1
            5270 POP_TOP
            5272 PUSH_NULL
            5274 LOAD_NAME              116 (exit)
            5276 PRECALL                  0
            5280 CALL                     0
            5290 POP_TOP
            5292 POP_EXCEPT
            5294 JUMP_FORWARD            27 (to 5350)

471     >>  5296 POP_TOP
            5298 PUSH_NULL
            5300 LOAD_NAME               45 (print)
            5302 LOAD_CONST             169 ('يرجا المحاوله مره اخره')
            5304 PRECALL                  1
            5308 CALL                     1
            5318 POP_TOP
            5320 PUSH_NULL
            5322 LOAD_NAME              116 (exit)
            5324 PRECALL                  0
            5328 CALL                     0
            5338 POP_TOP
            5340 POP_EXCEPT
            5342 JUMP_FORWARD             3 (to 5350)
        >>  5344 COPY                     3
            5346 POP_EXCEPT
            5348 RERAISE                  1

473     >>  5350 LOAD_NAME              129 (aobsh)
            5352 LOAD_CONST              32 ('2')
            5354 COMPARE_OP               2 (==)
            5360 EXTENDED_ARG             1
            5362 POP_JUMP_FORWARD_IF_FALSE   358 (to 6080)

474         5364 NOP

475         5366 PUSH_NULL
            5368 LOAD_NAME               44 (clear)
            5370 PRECALL                  0
            5374 CALL                     0
            5384 POP_TOP

476         5386 PUSH_NULL
            5388 LOAD_NAME               70 (int)
            5390 PUSH_NULL
            5392 LOAD_NAME               46 (input)
            5394 LOAD_CONST             170 (' عدد  سيزنات : ')            5396 LOAD_NAME               30 (X)
            5398 BINARY_OP                0 (+)
            5402 PRECALL                  1
            5406 CALL                     1
            5416 PRECALL                  1
            5420 CALL                     1
            5430 STORE_NAME             135 (jum)
            5432 JUMP_FORWARD            35 (to 5504)
        >>  5434 PUSH_EXC_INFO

477         5436 LOAD_NAME              136 (ValueError)
            5438 CHECK_EXC_MATCH
            5440 POP_JUMP_FORWARD_IF_FALSE    27 (to 5496)
            5442 POP_TOP

478         5444 PUSH_NULL
            5446 LOAD_NAME               45 (print)
            5448 LOAD_NAME               29 (Z)
            5450 LOAD_CONST             171 ('الرجاء كتابت كم  سيزنات بلارقام')
            5452 BINARY_OP                0 (+)
            5456 PRECALL                  1
            5460 CALL                     1
            5470 POP_TOP

479         5472 PUSH_NULL
            5474 LOAD_NAME              116 (exit)
            5476 PRECALL                  0
            5480 CALL                     0
            5490 POP_TOP
            5492 POP_EXCEPT
            5494 JUMP_FORWARD             4 (to 5504)

477     >>  5496 RERAISE                  0
        >>  5498 COPY                     3
            5500 POP_EXCEPT
            5502 RERAISE                  1

480     >>  5504 LOAD_NAME              135 (jum)
            5506 LOAD_CONST              93 (1)
            5508 COMPARE_OP               0 (<)
            5514 POP_JUMP_FORWARD_IF_TRUE     6 (to 5528)
            5516 LOAD_NAME              135 (jum)
            5518 LOAD_CONST              57 (1000)
            5520 COMPARE_OP               4 (>)
            5526 POP_JUMP_FORWARD_IF_FALSE    24 (to 5576)

481     >>  5528 PUSH_NULL
            5530 LOAD_NAME               45 (print)
            5532 LOAD_NAME               29 (Z)
            5534 LOAD_CONST             172 ('فشل تفريغ  ')
            5536 BINARY_OP                0 (+)
            5540 PRECALL                  1
            5544 CALL                     1
            5554 POP_TOP

482         5556 PUSH_NULL
            5558 LOAD_NAME              116 (exit)
            5560 PRECALL                  0
            5564 CALL                     0
            5574 POP_TOP

483     >>  5576 LOAD_CONST               0 (0)
            5578 STORE_NAME             137 (yz)

484         5580 PUSH_NULL
            5582 LOAD_NAME               61 (range)
            5584 LOAD_NAME              135 (jum)
            5586 PRECALL                  1
            5590 CALL                     1
            5600 GET_ITER
        >>  5602 FOR_ITER                73 (to 5750)
            5604 STORE_NAME             138 (met)

485         5606 LOAD_NAME              137 (yz)
            5608 LOAD_CONST              93 (1)
            5610 BINARY_OP               13 (+=)
            5614 STORE_NAME             137 (yz)

486         5616 PUSH_NULL
            5618 LOAD_NAME               44 (clear)
            5620 PRECALL                  0
            5624 CALL                     0
            5634 POP_TOP

487         5636 PUSH_NULL
            5638 LOAD_NAME               46 (input)
            5640 LOAD_CONST             173 ('السيزن  ')
            5642 LOAD_NAME               30 (X)
            5644 BINARY_OP                0 (+)
            5648 PUSH_NULL
            5650 LOAD_NAME               50 (str)
            5652 LOAD_NAME              137 (yz)
            5654 PRECALL                  1
            5658 CALL                     1
            5668 BINARY_OP                0 (+)
            5672 LOAD_NAME               31 (F)
            5674 BINARY_OP                0 (+)
            5678 LOAD_CONST             174 (' : ')
            5680 BINARY_OP                0 (+)
            5684 LOAD_NAME               32 (L)
            5686 BINARY_OP                0 (+)
            5690 PRECALL                  1
            5694 CALL                     1
            5704 STORE_NAME             139 (kl)

488         5706 LOAD_NAME              128 (uid1)
            5708 LOAD_METHOD            115 (append)
            5730 LOAD_NAME              139 (kl)
            5732 PRECALL                  1
            5736 CALL                     1
            5746 POP_TOP
            5748 JUMP_BACKWARD           74 (to 5602)

489     >>  5750 LOAD_NAME              128 (uid1)
            5752 GET_ITER
        >>  5754 FOR_ITER               162 (to 6080)
            5756 STORE_NAME             140 (userr)

491         5758 NOP

492         5760 PUSH_NULL
            5762 LOAD_NAME                0 (requests)
            5764 LOAD_ATTR               66 (get)
            5774 LOAD_CONST             175 ('https://api16-normal-c-useast1a.tiktokv.com/passport/account/info/v2/?')
            5776 LOAD_CONST             176 ('cookie')
            5778 LOAD_CONST             177 ('sessionid=')
            5780 LOAD_NAME              140 (userr)
            5782 FORMAT_VALUE             0
            5784 LOAD_CONST             178 (';')
            5786 BUILD_STRING             3
            5788 BUILD_MAP                1
            5790 KW_NAMES                55
            5792 PRECALL                  2
            5796 CALL                     2
            5806 STORE_NAME             141 (rh)

493         5808 LOAD_CONST             113 ('success')
            5810 PUSH_NULL
            5812 LOAD_NAME               50 (str)
            5814 LOAD_NAME              141 (rh)
            5816 LOAD_ATTR               96 (text)
            5826 PRECALL                  1
            5830 CALL                     1
            5840 CONTAINS_OP              0
            5842 POP_JUMP_FORWARD_IF_FALSE    26 (to 5896)

494         5844 LOAD_NAME              140 (userr)
            5846 LOAD_NAME               21 (sisn)
            5848 CONTAINS_OP              0
            5850 POP_JUMP_FORWARD_IF_FALSE     1 (to 5854)

495         5852 JUMP_FORWARD            21 (to 5896)

497     >>  5854 LOAD_NAME               21 (sisn)
            5856 LOAD_METHOD            115 (append)
            5878 LOAD_NAME              140 (userr)
            5880 PRECALL                  1
            5884 CALL                     1
            5894 POP_TOP

498     >>  5896 LOAD_CONST             179 ('error')
            5898 PUSH_NULL
            5900 LOAD_NAME               50 (str)
            5902 LOAD_NAME              141 (rh)
            5904 LOAD_ATTR               96 (text)
            5914 PRECALL                  1
            5918 CALL                     1
            5928 CONTAINS_OP              0
            5930 POP_JUMP_FORWARD_IF_FALSE    38 (to 6008)

499         5932 PUSH_NULL
            5934 LOAD_NAME               45 (print)
            5936 LOAD_CONST             180 ('ان هذا السيزن ايدي متوقف')
            5938 PRECALL                  1
            5942 CALL                     1
            5952 POP_TOP

500         5954 PUSH_NULL
            5956 LOAD_NAME               45 (print)
            5958 LOAD_NAME              140 (userr)
            5960 PRECALL                  1
            5964 CALL                     1
            5974 POP_TOP

501         5976 PUSH_NULL
            5978 LOAD_NAME               11 (time)
            5980 LOAD_ATTR              142 (sleep)
            5990 LOAD_CONST             181 (5)
            5992 PRECALL                  1
            5996 CALL                     1
            6006 POP_TOP
        >>  6008 JUMP_BACKWARD          128 (to 5754)
        >>  6010 PUSH_EXC_INFO

502         6012 LOAD_NAME                0 (requests)
            6014 LOAD_ATTR              133 (exceptions)
            6024 LOAD_ATTR              134 (ConnectionError)
            6034 CHECK_EXC_MATCH
            6036 POP_JUMP_FORWARD_IF_FALSE    17 (to 6072)
            6038 POP_TOP

503         6040 PUSH_NULL
            6042 LOAD_NAME               45 (print)
            6044 LOAD_NAME               29 (Z)
            6046 LOAD_CONST             182 ('       الاتصال في النت ظعيف')
            6048 BINARY_OP                0 (+)
            6052 PRECALL                  1
            6056 CALL                     1
            6066 POP_TOP
            6068 POP_EXCEPT
            6070 JUMP_BACKWARD          159 (to 5754)

502     >>  6072 RERAISE                  0
        >>  6074 COPY                     3
            6076 POP_EXCEPT
            6078 RERAISE                  1

504     >>  6080 PUSH_NULL
            6082 LOAD_NAME               44 (clear)
            6084 PRECALL                  0
            6088 CALL                     0
            6098 POP_TOP

506         6100 PUSH_NULL
            6102 LOAD_NAME              143 (len)
            6104 LOAD_NAME               21 (sisn)
            6106 PRECALL                  1
            6110 CALL                     1
            6120 LOAD_CONST              93 (1)
            6122 COMPARE_OP               0 (<)
            6128 POP_JUMP_FORWARD_IF_FALSE    26 (to 6182)

507         6130 PUSH_NULL
            6132 LOAD_NAME               45 (print)
            6134 LOAD_NAME               29 (Z)
            6136 LOAD_CONST             183 ('السيزنات اقل من 10 ')
            6138 BINARY_OP                0 (+)
            6142 PRECALL                  1
            6146 CALL                     1
            6156 POP_TOP

508         6158 PUSH_NULL
            6160 LOAD_NAME              116 (exit)
            6162 PRECALL                  0
            6166 CALL                     0
            6176 POP_TOP
            6178 LOAD_CONST               1 (None)
            6180 RETURN_VALUE

510     >>  6182 LOAD_NAME              129 (aobsh)
            6184 LOAD_CONST              32 ('2')
            6186 COMPARE_OP               2 (==)
            6192 EXTENDED_ARG             5
            6194 POP_JUMP_FORWARD_IF_FALSE  1413 (to 9022)

511         6196 BUILD_LIST               0
            6198 STORE_NAME             144 (reason1)

512         6200 PUSH_NULL
            6202 LOAD_NAME               45 (print)
            6204 LOAD_CONST             184 ('    ')
            6206 LOAD_NAME               30 (X)
            6208 FORMAT_VALUE             0
            6210 LOAD_CONST              28 ('[')
            6212 LOAD_NAME               31 (F)
            6214 FORMAT_VALUE             0
            6216 LOAD_CONST              29 ('1')
            6218 LOAD_NAME               30 (X)
            6220 FORMAT_VALUE             0
            6222 LOAD_CONST              39 (']')
            6224 LOAD_NAME               41 (C1)
            6226 FORMAT_VALUE             0
            6228 LOAD_CONST             185 (' العنف والايذاء والاستغلال الاجرامي')
            6230 BUILD_STRING             9
            6232 PRECALL                  1
            6236 CALL                     1
            6246 POP_TOP

513         6248 PUSH_NULL
            6250 LOAD_NAME               45 (print)
            6252 LOAD_CONST             184 ('    ')
            6254 LOAD_NAME               30 (X)
            6256 FORMAT_VALUE             0
            6258 LOAD_CONST              28 ('[')
            6260 LOAD_NAME               31 (F)
            6262 FORMAT_VALUE             0
            6264 LOAD_CONST              32 ('2')
            6266 LOAD_NAME               30 (X)
            6268 FORMAT_VALUE             0
            6270 LOAD_CONST              39 (']')
            6272 LOAD_NAME               41 (C1)
            6274 FORMAT_VALUE             0
            6276 LOAD_CONST             186 (' الكراهيه والتحرش')
            6278 BUILD_STRING             9
            6280 PRECALL                  1
            6284 CALL                     1
            6294 POP_TOP

514         6296 PUSH_NULL
            6298 LOAD_NAME               45 (print)
            6300 LOAD_CONST             184 ('    ')
            6302 LOAD_NAME               30 (X)
            6304 FORMAT_VALUE             0
            6306 LOAD_CONST              28 ('[')
            6308 LOAD_NAME               31 (F)
            6310 FORMAT_VALUE             0
            6312 LOAD_CONST              34 ('3')
            6314 LOAD_NAME               30 (X)
            6316 FORMAT_VALUE             0
            6318 LOAD_CONST              39 (']')
            6320 LOAD_NAME               41 (C1)
            6322 FORMAT_VALUE             0
            6324 LOAD_CONST             187 (' الانتحار وإيذاء النفس')
            6326 BUILD_STRING             9
            6328 PRECALL                  1
            6332 CALL                     1
            6342 POP_TOP

515         6344 PUSH_NULL
            6346 LOAD_NAME               45 (print)
            6348 LOAD_CONST             184 ('    ')
            6350 LOAD_NAME               30 (X)
            6352 FORMAT_VALUE             0
            6354 LOAD_CONST              28 ('[')
            6356 LOAD_NAME               31 (F)
            6358 FORMAT_VALUE             0
            6360 LOAD_CONST              36 ('4')
            6362 LOAD_NAME               30 (X)
            6364 FORMAT_VALUE             0
            6366 LOAD_CONST              39 (']')
            6368 LOAD_NAME               41 (C1)
            6370 FORMAT_VALUE             0
            6372 LOAD_CONST             188 (' اضطرابات الأكل وصورة الجسم غير الصحية')
            6374 BUILD_STRING             9
            6376 PRECALL                  1
            6380 CALL                     1
            6390 POP_TOP

516         6392 PUSH_NULL
            6394 LOAD_NAME               45 (print)
            6396 LOAD_CONST             184 ('    ')
            6398 LOAD_NAME               30 (X)
            6400 FORMAT_VALUE             0
            6402 LOAD_CONST              28 ('[')
            6404 LOAD_NAME               31 (F)
            6406 FORMAT_VALUE             0
            6408 LOAD_CONST             189 ('5')
            6410 LOAD_NAME               30 (X)
            6412 FORMAT_VALUE             0
            6414 LOAD_CONST              39 (']')
            6416 LOAD_NAME               41 (C1)
            6418 FORMAT_VALUE             0
            6420 LOAD_CONST             190 (' الأنشطة والتحديات الخطرة')
            6422 BUILD_STRING             9
            6424 PRECALL                  1
            6428 CALL                     1
            6438 POP_TOP

517         6440 PUSH_NULL
            6442 LOAD_NAME               45 (print)
            6444 LOAD_CONST             184 ('    ')
            6446 LOAD_NAME               30 (X)
            6448 FORMAT_VALUE             0
            6450 LOAD_CONST              28 ('[')
            6452 LOAD_NAME               31 (F)
            6454 FORMAT_VALUE             0
            6456 LOAD_CONST             191 ('6')
            6458 LOAD_NAME               30 (X)
            6460 FORMAT_VALUE             0
            6462 LOAD_CONST              39 (']')
            6464 LOAD_NAME               41 (C1)
            6466 FORMAT_VALUE             0
            6468 LOAD_CONST             192 (' العري والمحتوى الجنسي')
            6470 BUILD_STRING             9
            6472 PRECALL                  1
            6476 CALL                     1
            6486 POP_TOP

518         6488 PUSH_NULL
            6490 LOAD_NAME               45 (print)
            6492 LOAD_CONST             184 ('    ')
            6494 LOAD_NAME               30 (X)
            6496 FORMAT_VALUE             0
            6498 LOAD_CONST              28 ('[')
            6500 LOAD_NAME               31 (F)
            6502 FORMAT_VALUE             0
            6504 LOAD_CONST             193 ('7')
            6506 LOAD_NAME               30 (X)
            6508 FORMAT_VALUE             0
            6510 LOAD_CONST              39 (']')
            6512 LOAD_NAME               41 (C1)
            6514 FORMAT_VALUE             0
            6516 LOAD_CONST             194 (' المحتوى صادم وبشع المنظر')
            6518 BUILD_STRING             9
            6520 PRECALL                  1
            6524 CALL                     1
            6534 POP_TOP

519         6536 PUSH_NULL
            6538 LOAD_NAME               45 (print)
            6540 LOAD_CONST             184 ('    ')
            6542 LOAD_NAME               30 (X)
            6544 FORMAT_VALUE             0
            6546 LOAD_CONST              28 ('[')
            6548 LOAD_NAME               31 (F)
            6550 FORMAT_VALUE             0
            6552 LOAD_CONST             195 ('8')
            6554 LOAD_NAME               30 (X)
            6556 FORMAT_VALUE             0
            6558 LOAD_CONST              39 (']')
            6560 LOAD_NAME               41 (C1)
            6562 FORMAT_VALUE             0
            6564 LOAD_CONST             196 (' معلومات خاطئه')
            6566 BUILD_STRING             9
            6568 PRECALL                  1
            6572 CALL                     1
            6582 POP_TOP

520         6584 PUSH_NULL
            6586 LOAD_NAME               45 (print)
            6588 LOAD_CONST             184 ('    ')
            6590 LOAD_NAME               30 (X)
            6592 FORMAT_VALUE             0
            6594 LOAD_CONST              28 ('[')
            6596 LOAD_NAME               31 (F)
            6598 FORMAT_VALUE             0
            6600 LOAD_CONST             197 ('9')
            6602 LOAD_NAME               30 (X)
            6604 FORMAT_VALUE             0
            6606 LOAD_CONST              39 (']')
            6608 LOAD_NAME               41 (C1)
            6610 FORMAT_VALUE             0
            6612 LOAD_CONST             198 (' السلوك المخادع والغش')
            6614 BUILD_STRING             9
            6616 PRECALL                  1
            6620 CALL                     1
            6630 POP_TOP

521         6632 PUSH_NULL
            6634 LOAD_NAME               45 (print)
            6636 LOAD_CONST             184 ('    ')
            6638 LOAD_NAME               30 (X)
            6640 FORMAT_VALUE             0
            6642 LOAD_CONST              28 ('[')
            6644 LOAD_NAME               31 (F)
            6646 FORMAT_VALUE             0
            6648 LOAD_CONST             199 ('10')
            6650 LOAD_NAME               30 (X)
            6652 FORMAT_VALUE             0
            6654 LOAD_CONST              39 (']')
            6656 LOAD_NAME               41 (C1)
            6658 FORMAT_VALUE             0
            6660 LOAD_CONST             200 (' السلع والانشطة الخاضعه للتنظيم')
            6662 BUILD_STRING             9
            6664 PRECALL                  1
            6668 CALL                     1
            6678 POP_TOP

522         6680 PUSH_NULL
            6682 LOAD_NAME               45 (print)
            6684 LOAD_CONST             184 ('    ')
            6686 LOAD_NAME               30 (X)
            6688 FORMAT_VALUE             0
            6690 LOAD_CONST              28 ('[')
            6692 LOAD_NAME               31 (F)
            6694 FORMAT_VALUE             0
            6696 LOAD_CONST             201 ('11')
            6698 LOAD_NAME               30 (X)
            6700 FORMAT_VALUE             0
            6702 LOAD_CONST              39 (']')
            6704 LOAD_NAME               41 (C1)
            6706 FORMAT_VALUE             0
            6708 LOAD_CONST             202 (' الغش والاحتيال')            6710 BUILD_STRING             9
            6712 PRECALL                  1
            6716 CALL                     1
            6726 POP_TOP

523         6728 PUSH_NULL
            6730 LOAD_NAME               45 (print)
            6732 LOAD_CONST             184 ('    ')
            6734 LOAD_NAME               30 (X)
            6736 FORMAT_VALUE             0
            6738 LOAD_CONST              28 ('[')
            6740 LOAD_NAME               31 (F)
            6742 FORMAT_VALUE             0
            6744 LOAD_CONST             203 ('12')
            6746 LOAD_NAME               30 (X)
            6748 FORMAT_VALUE             0
            6750 LOAD_CONST              39 (']')
            6752 LOAD_NAME               41 (C1)
            6754 FORMAT_VALUE             0
            6756 LOAD_CONST             204 (' مشاركة المعلومات الشخصية')
            6758 BUILD_STRING             9
            6760 PRECALL                  1
            6764 CALL                     1
            6774 POP_TOP

524         6776 PUSH_NULL
            6778 LOAD_NAME               45 (print)
            6780 LOAD_CONST             184 ('    ')
            6782 LOAD_NAME               30 (X)
            6784 FORMAT_VALUE             0
            6786 LOAD_CONST              28 ('[')
            6788 LOAD_NAME               31 (F)
            6790 FORMAT_VALUE             0
            6792 LOAD_CONST             205 ('13')
            6794 LOAD_NAME               30 (X)
            6796 FORMAT_VALUE             0
            6798 LOAD_CONST              39 (']')
            6800 LOAD_NAME               41 (C1)
            6802 FORMAT_VALUE             0
            6804 LOAD_CONST             206 (' تقليد والملكية الفكرية')
            6806 BUILD_STRING             9
            6808 PRECALL                  1
            6812 CALL                     1
            6822 POP_TOP

525         6824 PUSH_NULL
            6826 LOAD_NAME               45 (print)
            6828 LOAD_CONST             184 ('    ')
            6830 LOAD_NAME               30 (X)
            6832 FORMAT_VALUE             0
            6834 LOAD_CONST              28 ('[')
            6836 LOAD_NAME               31 (F)
            6838 FORMAT_VALUE             0
            6840 LOAD_CONST             207 ('14')
            6842 LOAD_NAME               30 (X)
            6844 FORMAT_VALUE             0
            6846 LOAD_CONST              39 (']')
            6848 LOAD_NAME               41 (C1)
            6850 FORMAT_VALUE             0
            6852 LOAD_CONST             208 (' اخرى')
            6854 BUILD_STRING             9
            6856 PRECALL                  1
            6860 CALL                     1
            6870 POP_TOP

526         6872 PUSH_NULL
            6874 LOAD_NAME               46 (input)
            6876 LOAD_NAME               30 (X)
            6878 FORMAT_VALUE             0
            6880 LOAD_CONST              28 ('[')
            6882 LOAD_NAME               31 (F)
            6884 FORMAT_VALUE             0
            6886 LOAD_CONST              38 ('×')
            6888 LOAD_NAME               30 (X)
            6890 FORMAT_VALUE             0
            6892 LOAD_CONST              39 (']')
            6894 LOAD_NAME               29 (Z)
            6896 FORMAT_VALUE             0
            6898 LOAD_CONST             209 ('   اختار المناسب لك : ')
            6900 BUILD_STRING             8
            6902 LOAD_NAME               32 (L)
            6904 BINARY_OP                0 (+)
            6908 PRECALL                  1
            6912 CALL                     1
            6922 STORE_NAME             145 (xxx)

527         6924 PUSH_NULL
            6926 LOAD_NAME               44 (clear)
            6928 PRECALL                  0
            6932 CALL                     0
            6942 POP_TOP

528         6944 LOAD_NAME              145 (xxx)
            6946 LOAD_CONST              29 ('1')
            6948 COMPARE_OP               2 (==)
            6954 POP_JUMP_FORWARD_IF_FALSE   224 (to 7404)

529         6956 PUSH_NULL
            6958 LOAD_NAME               45 (print)
            6960 LOAD_NAME               30 (X)
            6962 FORMAT_VALUE             0
            6964 LOAD_CONST              28 ('[')
            6966 LOAD_NAME               31 (F)
            6968 FORMAT_VALUE             0
            6970 LOAD_CONST              29 ('1')
            6972 LOAD_NAME               30 (X)
            6974 FORMAT_VALUE             0
            6976 LOAD_CONST              39 (']')
            6978 LOAD_NAME               39 (J22)
            6980 FORMAT_VALUE             0
            6982 LOAD_CONST             210 (' استغلال الأشخاص الذين تقل أعمارهم عن 18 عامًا أو إساءة معاملتهم')
            6984 BUILD_STRING             8
            6986 PRECALL                  1
            6990 CALL                     1
            7000 POP_TOP

530         7002 PUSH_NULL
            7004 LOAD_NAME               45 (print)
            7006 LOAD_NAME               30 (X)
            7008 FORMAT_VALUE             0
            7010 LOAD_CONST              28 ('[')
            7012 LOAD_NAME               31 (F)
            7014 FORMAT_VALUE             0
            7016 LOAD_CONST              32 ('2')
            7018 LOAD_NAME               30 (X)
            7020 FORMAT_VALUE             0
            7022 LOAD_CONST              39 (']')
            7024 LOAD_NAME               39 (J22)
            7026 FORMAT_VALUE             0
            7028 LOAD_CONST             211 (' العنف الجسدي والتهديدات العنيفة')
            7030 BUILD_STRING             8
            7032 PRECALL                  1
            7036 CALL                     1
            7046 POP_TOP

531         7048 PUSH_NULL
            7050 LOAD_NAME               45 (print)
            7052 LOAD_NAME               30 (X)
            7054 FORMAT_VALUE             0
            7056 LOAD_CONST              28 ('[')
            7058 LOAD_NAME               31 (F)
            7060 FORMAT_VALUE             0
            7062 LOAD_CONST              34 ('3')
            7064 LOAD_NAME               30 (X)
            7066 FORMAT_VALUE             0
            7068 LOAD_CONST              39 (']')
            7070 LOAD_NAME               39 (J22)
            7072 FORMAT_VALUE             0
            7074 LOAD_CONST             212 (' الاستغلال والاعتداء الجنسي')
            7076 BUILD_STRING             8
            7078 PRECALL                  1
            7082 CALL                     1
            7092 POP_TOP

532         7094 PUSH_NULL
            7096 LOAD_NAME               45 (print)
            7098 LOAD_NAME               30 (X)
            7100 FORMAT_VALUE             0
            7102 LOAD_CONST              28 ('[')
            7104 LOAD_NAME               31 (F)
            7106 FORMAT_VALUE             0
            7108 LOAD_CONST              36 ('4')
            7110 LOAD_NAME               30 (X)
            7112 FORMAT_VALUE             0
            7114 LOAD_CONST              39 (']')
            7116 LOAD_NAME               39 (J22)
            7118 FORMAT_VALUE             0
            7120 LOAD_CONST             213 (' الاستغلال البشري')
            7122 BUILD_STRING             8
            7124 PRECALL                  1
            7128 CALL                     1
            7138 POP_TOP

533         7140 PUSH_NULL
            7142 LOAD_NAME               45 (print)
            7144 LOAD_NAME               30 (X)
            7146 FORMAT_VALUE             0
            7148 LOAD_CONST              28 ('[')
            7150 LOAD_NAME               31 (F)
            7152 FORMAT_VALUE             0
            7154 LOAD_CONST             189 ('5')
            7156 LOAD_NAME               30 (X)
            7158 FORMAT_VALUE             0
            7160 LOAD_CONST              39 (']')
            7162 LOAD_NAME               39 (J22)
            7164 FORMAT_VALUE             0
            7166 LOAD_CONST             214 (' الإساءة للحيوان')
            7168 BUILD_STRING             8
            7170 PRECALL                  1
            7174 CALL                     1
            7184 POP_TOP

534         7186 PUSH_NULL
            7188 LOAD_NAME               45 (print)
            7190 LOAD_NAME               30 (X)
            7192 FORMAT_VALUE             0
            7194 LOAD_CONST              28 ('[')
            7196 LOAD_NAME               31 (F)
            7198 FORMAT_VALUE             0
            7200 LOAD_CONST             191 ('6')
            7202 LOAD_NAME               30 (X)
            7204 FORMAT_VALUE             0
            7206 LOAD_CONST              39 (']')
            7208 LOAD_NAME               39 (J22)
            7210 FORMAT_VALUE             0
            7212 LOAD_CONST             215 (' الأنشطة الإجرامية الأخرى')
            7214 BUILD_STRING             8
            7216 PRECALL                  1
            7220 CALL                     1
            7230 POP_TOP

535         7232 PUSH_NULL
            7234 LOAD_NAME               46 (input)
            7236 LOAD_NAME               30 (X)
            7238 FORMAT_VALUE             0
            7240 LOAD_CONST              28 ('[')
            7242 LOAD_NAME               31 (F)
            7244 FORMAT_VALUE             0
            7246 LOAD_CONST              38 ('×')
            7248 LOAD_NAME               30 (X)
            7250 FORMAT_VALUE             0
            7252 LOAD_CONST              39 (']')
            7254 LOAD_NAME               29 (Z)
            7256 FORMAT_VALUE             0
            7258 LOAD_CONST             216 ('اختار المناسب لك : ')
            7260 BUILD_STRING             8
            7262 LOAD_NAME               32 (L)
            7264 BINARY_OP                0 (+)
            7268 PRECALL                  1
            7272 CALL                     1
            7282 STORE_NAME             145 (xxx)

536         7284 LOAD_NAME              145 (xxx)
            7286 LOAD_CONST              29 ('1')
            7288 COMPARE_OP               2 (==)
            7294 POP_JUMP_FORWARD_IF_FALSE     4 (to 7304)
            7296 LOAD_CONST             217 ('902112')
            7298 STORE_NAME             144 (reason1)
            7300 EXTENDED_ARG             3
            7302 JUMP_FORWARD           859 (to 9022)

537     >>  7304 LOAD_NAME              145 (xxx)
            7306 LOAD_CONST              32 ('2')
            7308 COMPARE_OP               2 (==)
            7314 POP_JUMP_FORWARD_IF_FALSE     4 (to 7324)
            7316 LOAD_CONST             217 ('902112')
            7318 STORE_NAME             144 (reason1)
            7320 EXTENDED_ARG             3
            7322 JUMP_FORWARD           849 (to 9022)

538     >>  7324 LOAD_NAME              145 (xxx)
            7326 LOAD_CONST              34 ('3')
            7328 COMPARE_OP               2 (==)
            7334 POP_JUMP_FORWARD_IF_FALSE     4 (to 7344)
            7336 LOAD_CONST             217 ('902112')
            7338 STORE_NAME             144 (reason1)
            7340 EXTENDED_ARG             3
            7342 JUMP_FORWARD           839 (to 9022)

539     >>  7344 LOAD_NAME              145 (xxx)
            7346 LOAD_CONST              36 ('4')
            7348 COMPARE_OP               2 (==)
            7354 POP_JUMP_FORWARD_IF_FALSE     4 (to 7364)
            7356 LOAD_CONST             217 ('902112')
            7358 STORE_NAME             144 (reason1)
            7360 EXTENDED_ARG             3
            7362 JUMP_FORWARD           829 (to 9022)

540     >>  7364 LOAD_NAME              145 (xxx)
            7366 LOAD_CONST             189 ('5')
            7368 COMPARE_OP               2 (==)
            7374 POP_JUMP_FORWARD_IF_FALSE     4 (to 7384)
            7376 LOAD_CONST             217 ('902112')
            7378 STORE_NAME             144 (reason1)
            7380 EXTENDED_ARG             3
            7382 JUMP_FORWARD           819 (to 9022)

541     >>  7384 LOAD_NAME              145 (xxx)
            7386 LOAD_CONST             191 ('6')
            7388 COMPARE_OP               2 (==)
            7394 POP_JUMP_FORWARD_IF_FALSE     2 (to 7400)
            7396 LOAD_CONST             217 ('902112')
            7398 STORE_NAME             144 (reason1)
        >>  7400 EXTENDED_ARG             3
            7402 JUMP_FORWARD           809 (to 9022)

542     >>  7404 LOAD_NAME              145 (xxx)
            7406 LOAD_CONST              32 ('2')
            7408 COMPARE_OP               2 (==)
            7414 POP_JUMP_FORWARD_IF_FALSE    92 (to 7600)

543         7416 PUSH_NULL
            7418 LOAD_NAME               45 (print)
            7420 LOAD_NAME               30 (X)
            7422 FORMAT_VALUE             0
            7424 LOAD_CONST              28 ('[')
            7426 LOAD_NAME               31 (F)
            7428 FORMAT_VALUE             0
            7430 LOAD_CONST              29 ('1')
            7432 LOAD_NAME               30 (X)
            7434 FORMAT_VALUE             0
            7436 LOAD_CONST              39 (']')
            7438 LOAD_NAME               39 (J22)
            7440 FORMAT_VALUE             0
            7442 LOAD_CONST             218 (' الكلام الذي يحض على الكراهية والسلوكيات البغيضة')
            7444 BUILD_STRING             8
            7446 PRECALL                  1
            7450 CALL                     1
            7460 POP_TOP

544         7462 PUSH_NULL
            7464 LOAD_NAME               45 (print)
            7466 LOAD_NAME               30 (X)
            7468 FORMAT_VALUE             0
            7470 LOAD_CONST              28 ('[')
            7472 LOAD_NAME               31 (F)
            7474 FORMAT_VALUE             0
            7476 LOAD_CONST              32 ('2')
            7478 LOAD_NAME               30 (X)
            7480 FORMAT_VALUE             0
            7482 LOAD_CONST              39 (']')
            7484 LOAD_NAME               39 (J22)
            7486 FORMAT_VALUE             0
            7488 LOAD_CONST             219 (' التحرش والتنمر')            7490 BUILD_STRING             8
            7492 PRECALL                  1
            7496 CALL                     1
            7506 POP_TOP

545         7508 PUSH_NULL
            7510 LOAD_NAME               46 (input)
            7512 LOAD_NAME               30 (X)
            7514 FORMAT_VALUE             0
            7516 LOAD_CONST              28 ('[')
            7518 LOAD_NAME               31 (F)
            7520 FORMAT_VALUE             0
            7522 LOAD_CONST              38 ('×')
            7524 LOAD_NAME               30 (X)
            7526 FORMAT_VALUE             0
            7528 LOAD_CONST              39 (']')
            7530 LOAD_NAME               29 (Z)
            7532 FORMAT_VALUE             0
            7534 LOAD_CONST             216 ('اختار المناسب لك : ')
            7536 BUILD_STRING             8
            7538 LOAD_NAME               32 (L)
            7540 BINARY_OP                0 (+)
            7544 PRECALL                  1
            7548 CALL                     1
            7558 STORE_NAME             145 (xxx)

546         7560 LOAD_NAME              145 (xxx)
            7562 LOAD_CONST              29 ('1')
            7564 COMPARE_OP               2 (==)
            7570 POP_JUMP_FORWARD_IF_FALSE     4 (to 7580)
            7572 LOAD_CONST             217 ('902112')
            7574 STORE_NAME             144 (reason1)
            7576 EXTENDED_ARG             2
            7578 JUMP_FORWARD           721 (to 9022)

547     >>  7580 LOAD_NAME              145 (xxx)
            7582 LOAD_CONST              32 ('2')
            7584 COMPARE_OP               2 (==)
            7590 POP_JUMP_FORWARD_IF_FALSE     2 (to 7596)
            7592 LOAD_CONST             217 ('902112')
            7594 STORE_NAME             144 (reason1)
        >>  7596 EXTENDED_ARG             2
            7598 JUMP_FORWARD           711 (to 9022)

548     >>  7600 LOAD_NAME              145 (xxx)
            7602 LOAD_CONST              34 ('3')
            7604 COMPARE_OP               2 (==)
            7610 POP_JUMP_FORWARD_IF_FALSE     4 (to 7620)
            7612 LOAD_CONST             217 ('902112')
            7614 STORE_NAME             144 (reason1)
            7616 EXTENDED_ARG             2
            7618 JUMP_FORWARD           701 (to 9022)

549     >>  7620 LOAD_NAME              145 (xxx)
            7622 LOAD_CONST              36 ('4')
            7624 COMPARE_OP               2 (==)
            7630 POP_JUMP_FORWARD_IF_FALSE     4 (to 7640)
            7632 LOAD_CONST             217 ('902112')
            7634 STORE_NAME             144 (reason1)
            7636 EXTENDED_ARG             2
            7638 JUMP_FORWARD           691 (to 9022)

550     >>  7640 LOAD_NAME              145 (xxx)
            7642 LOAD_CONST             189 ('5')
            7644 COMPARE_OP               2 (==)
            7650 POP_JUMP_FORWARD_IF_FALSE     4 (to 7660)
            7652 LOAD_CONST             217 ('902112')
            7654 STORE_NAME             144 (reason1)
            7656 EXTENDED_ARG             2
            7658 JUMP_FORWARD           681 (to 9022)

551     >>  7660 LOAD_NAME              145 (xxx)
            7662 LOAD_CONST             191 ('6')
            7664 COMPARE_OP               2 (==)
            7670 POP_JUMP_FORWARD_IF_FALSE   191 (to 8054)

552         7672 PUSH_NULL
            7674 LOAD_NAME               45 (print)
            7676 LOAD_NAME               30 (X)
            7678 FORMAT_VALUE             0
            7680 LOAD_CONST              28 ('[')
            7682 LOAD_NAME               31 (F)
            7684 FORMAT_VALUE             0
            7686 LOAD_CONST              29 ('1')
            7688 LOAD_NAME               30 (X)
            7690 FORMAT_VALUE             0
            7692 LOAD_CONST              39 (']')
            7694 LOAD_NAME               39 (J22)
            7696 FORMAT_VALUE             0
            7698 LOAD_CONST             220 (' النشاط الجنسي للشباب والاستدراج الجنسي والاستغلال الجنسي')
            7700 BUILD_STRING             8
            7702 PRECALL                  1
            7706 CALL                     1
            7716 POP_TOP

553         7718 PUSH_NULL
            7720 LOAD_NAME               45 (print)
            7722 LOAD_NAME               30 (X)
            7724 FORMAT_VALUE             0
            7726 LOAD_CONST              28 ('[')
            7728 LOAD_NAME               31 (F)
            7730 FORMAT_VALUE             0
            7732 LOAD_CONST              32 ('2')
            7734 LOAD_NAME               30 (X)
            7736 FORMAT_VALUE             0
            7738 LOAD_CONST              39 (']')
            7740 LOAD_NAME               39 (J22)
            7742 FORMAT_VALUE             0
            7744 LOAD_CONST             221 (' السلوك الموحي جنسيًا بواسطة الشباب')
            7746 BUILD_STRING             8
            7748 PRECALL                  1
            7752 CALL                     1
            7762 POP_TOP

554         7764 PUSH_NULL
            7766 LOAD_NAME               45 (print)
            7768 LOAD_NAME               30 (X)
            7770 FORMAT_VALUE             0
            7772 LOAD_CONST              28 ('[')
            7774 LOAD_NAME               31 (F)
            7776 FORMAT_VALUE             0
            7778 LOAD_CONST              34 ('3')
            7780 LOAD_NAME               30 (X)
            7782 FORMAT_VALUE             0
            7784 LOAD_CONST              39 (']')
            7786 LOAD_NAME               39 (J22)
            7788 FORMAT_VALUE             0
            7790 LOAD_CONST             222 (' النشاط الجنسي للبالغين والخدمات الجنسية والاستدراج الجنسي')
            7792 BUILD_STRING             8
            7794 PRECALL                  1
            7798 CALL                     1
            7808 POP_TOP

555         7810 PUSH_NULL
            7812 LOAD_NAME               45 (print)
            7814 LOAD_NAME               30 (X)
            7816 FORMAT_VALUE             0
            7818 LOAD_CONST              28 ('[')
            7820 LOAD_NAME               31 (F)
            7822 FORMAT_VALUE             0
            7824 LOAD_CONST              36 ('4')
            7826 LOAD_NAME               30 (X)
            7828 FORMAT_VALUE             0
            7830 LOAD_CONST              39 (']')
            7832 LOAD_NAME               39 (J22)
            7834 FORMAT_VALUE             0
            7836 LOAD_CONST             223 (' عُري البالغين')
            7838 BUILD_STRING             8
            7840 PRECALL                  1
            7844 CALL                     1
            7854 POP_TOP

556         7856 PUSH_NULL
            7858 LOAD_NAME               45 (print)
            7860 LOAD_NAME               30 (X)
            7862 FORMAT_VALUE             0
            7864 LOAD_CONST              28 ('[')
            7866 LOAD_NAME               31 (F)
            7868 FORMAT_VALUE             0
            7870 LOAD_CONST             189 ('5')
            7872 LOAD_NAME               30 (X)
            7874 FORMAT_VALUE             0
            7876 LOAD_CONST              39 (']')
            7878 LOAD_NAME               39 (J22)
            7880 FORMAT_VALUE             0
            7882 LOAD_CONST             224 (' اللغة الجنسية الفاحشة')
            7884 BUILD_STRING             8
            7886 PRECALL                  1
            7890 CALL                     1
            7900 POP_TOP

557         7902 PUSH_NULL
            7904 LOAD_NAME               46 (input)
            7906 LOAD_NAME               30 (X)
            7908 FORMAT_VALUE             0
            7910 LOAD_CONST              28 ('[')
            7912 LOAD_NAME               31 (F)
            7914 FORMAT_VALUE             0
            7916 LOAD_CONST              38 ('×')
            7918 LOAD_NAME               30 (X)
            7920 FORMAT_VALUE             0
            7922 LOAD_CONST              39 (']')
            7924 LOAD_NAME               29 (Z)
            7926 FORMAT_VALUE             0
            7928 LOAD_CONST             216 ('اختار المناسب لك : ')
            7930 BUILD_STRING             8
            7932 LOAD_NAME               32 (L)
            7934 BINARY_OP                0 (+)
            7938 PRECALL                  1
            7942 CALL                     1
            7952 STORE_NAME             145 (xxx)

558         7954 LOAD_NAME              145 (xxx)
            7956 LOAD_CONST              29 ('1')
            7958 COMPARE_OP               2 (==)
            7964 POP_JUMP_FORWARD_IF_FALSE     4 (to 7974)
            7966 LOAD_CONST             217 ('902112')
            7968 STORE_NAME             144 (reason1)
            7970 EXTENDED_ARG             2
            7972 JUMP_FORWARD           524 (to 9022)

559     >>  7974 LOAD_NAME              145 (xxx)
            7976 LOAD_CONST              32 ('2')
            7978 COMPARE_OP               2 (==)
            7984 POP_JUMP_FORWARD_IF_FALSE     4 (to 7994)
            7986 LOAD_CONST             217 ('902112')
            7988 STORE_NAME             144 (reason1)
            7990 EXTENDED_ARG             2
            7992 JUMP_FORWARD           514 (to 9022)

560     >>  7994 LOAD_NAME              145 (xxx)
            7996 LOAD_CONST              34 ('3')
            7998 COMPARE_OP               2 (==)
            8004 POP_JUMP_FORWARD_IF_FALSE     4 (to 8014)
            8006 LOAD_CONST             217 ('902112')
            8008 STORE_NAME             144 (reason1)
            8010 EXTENDED_ARG             1
            8012 JUMP_FORWARD           504 (to 9022)

561     >>  8014 LOAD_NAME              145 (xxx)
            8016 LOAD_CONST              36 ('4')
            8018 COMPARE_OP               2 (==)
            8024 POP_JUMP_FORWARD_IF_FALSE     4 (to 8034)
            8026 LOAD_CONST             217 ('902112')
            8028 STORE_NAME             144 (reason1)
            8030 EXTENDED_ARG             1
            8032 JUMP_FORWARD           494 (to 9022)

562     >>  8034 LOAD_NAME              145 (xxx)
            8036 LOAD_CONST             189 ('5')
            8038 COMPARE_OP               2 (==)
            8044 POP_JUMP_FORWARD_IF_FALSE     2 (to 8050)
            8046 LOAD_CONST             217 ('902112')
            8048 STORE_NAME             144 (reason1)
        >>  8050 EXTENDED_ARG             1
            8052 JUMP_FORWARD           484 (to 9022)

563     >>  8054 LOAD_NAME              145 (xxx)
            8056 LOAD_CONST             193 ('7')
            8058 COMPARE_OP               2 (==)
            8064 POP_JUMP_FORWARD_IF_FALSE     4 (to 8074)
            8066 LOAD_CONST             217 ('902112')
            8068 STORE_NAME             144 (reason1)
            8070 EXTENDED_ARG             1
            8072 JUMP_FORWARD           474 (to 9022)

564     >>  8074 LOAD_NAME              145 (xxx)
            8076 LOAD_CONST             195 ('8')
            8078 COMPARE_OP               2 (==)
            8084 POP_JUMP_FORWARD_IF_FALSE   125 (to 8336)

565         8086 PUSH_NULL
            8088 LOAD_NAME               45 (print)
            8090 LOAD_NAME               30 (X)
            8092 FORMAT_VALUE             0
            8094 LOAD_CONST              28 ('[')
            8096 LOAD_NAME               31 (F)
            8098 FORMAT_VALUE             0
            8100 LOAD_CONST              29 ('1')
            8102 LOAD_NAME               30 (X)
            8104 FORMAT_VALUE             0
            8106 LOAD_CONST              39 (']')
            8108 LOAD_NAME               39 (J22)
            8110 FORMAT_VALUE             0
            8112 LOAD_CONST             225 (' معلومات خاطئة عن الانتخابات')
            8114 BUILD_STRING             8
            8116 PRECALL                  1
            8120 CALL                     1
            8130 POP_TOP

566         8132 PUSH_NULL
            8134 LOAD_NAME               45 (print)
            8136 LOAD_NAME               30 (X)
            8138 FORMAT_VALUE             0
            8140 LOAD_CONST              28 ('[')
            8142 LOAD_NAME               31 (F)
            8144 FORMAT_VALUE             0
            8146 LOAD_CONST              32 ('2')
            8148 LOAD_NAME               30 (X)
            8150 FORMAT_VALUE             0
            8152 LOAD_CONST              39 (']')
            8154 LOAD_NAME               39 (J22)
            8156 FORMAT_VALUE             0
            8158 LOAD_CONST             226 (' المعلومات الضارة المضللة')
            8160 BUILD_STRING             8
            8162 PRECALL                  1
            8166 CALL                     1
            8176 POP_TOP

567         8178 PUSH_NULL
            8180 LOAD_NAME               45 (print)
            8182 LOAD_NAME               30 (X)
            8184 FORMAT_VALUE             0
            8186 LOAD_CONST              28 ('[')
            8188 LOAD_NAME               31 (F)
            8190 FORMAT_VALUE             0
            8192 LOAD_CONST              34 ('3')
            8194 LOAD_NAME               30 (X)
            8196 FORMAT_VALUE             0
            8198 LOAD_CONST              39 (']')
            8200 LOAD_NAME               39 (J22)
            8202 FORMAT_VALUE             0
            8204 LOAD_CONST             227 (' التزييف العميق (Deepfakes) الوسائط التي تم التلاعب بها')
            8206 BUILD_STRING             8
            8208 PRECALL                  1
            8212 CALL                     1
            8222 POP_TOP

568         8224 PUSH_NULL
            8226 LOAD_NAME               46 (input)
            8228 LOAD_NAME               30 (X)
            8230 FORMAT_VALUE             0
            8232 LOAD_CONST              28 ('[')
            8234 LOAD_NAME               31 (F)
            8236 FORMAT_VALUE             0
            8238 LOAD_CONST              38 ('×')
            8240 LOAD_NAME               30 (X)
            8242 FORMAT_VALUE             0
            8244 LOAD_CONST              39 (']')
            8246 LOAD_NAME               29 (Z)
            8248 FORMAT_VALUE             0
            8250 LOAD_CONST             216 ('اختار المناسب لك : ')
            8252 BUILD_STRING             8
            8254 LOAD_NAME               32 (L)
            8256 BINARY_OP                0 (+)
            8260 PRECALL                  1
            8264 CALL                     1
            8274 STORE_NAME             145 (xxx)

569         8276 LOAD_NAME              145 (xxx)
            8278 LOAD_CONST              29 ('1')
            8280 COMPARE_OP               2 (==)
            8286 POP_JUMP_FORWARD_IF_FALSE     4 (to 8296)
            8288 LOAD_CONST             217 ('902112')
            8290 STORE_NAME             144 (reason1)
            8292 EXTENDED_ARG             1
            8294 JUMP_FORWARD           363 (to 9022)

570     >>  8296 LOAD_NAME              145 (xxx)
            8298 LOAD_CONST              32 ('2')
            8300 COMPARE_OP               2 (==)
            8306 POP_JUMP_FORWARD_IF_FALSE     4 (to 8316)
            8308 LOAD_CONST             217 ('902112')
            8310 STORE_NAME             144 (reason1)
            8312 EXTENDED_ARG             1
            8314 JUMP_FORWARD           353 (to 9022)

571     >>  8316 LOAD_NAME              145 (xxx)
            8318 LOAD_CONST              34 ('3')
            8320 COMPARE_OP               2 (==)
            8326 POP_JUMP_FORWARD_IF_FALSE     2 (to 8332)
            8328 LOAD_CONST             217 ('902112')
            8330 STORE_NAME             144 (reason1)
        >>  8332 EXTENDED_ARG             1
            8334 JUMP_FORWARD           343 (to 9022)

572     >>  8336 LOAD_NAME              145 (xxx)
            8338 LOAD_CONST             197 ('9')
            8340 COMPARE_OP               2 (==)
            8346 POP_JUMP_FORWARD_IF_FALSE   122 (to 8592)

573         8348 PUSH_NULL
            8350 LOAD_NAME               45 (print)
            8352 LOAD_NAME               30 (X)
            8354 FORMAT_VALUE             0
            8356 LOAD_CONST              28 ('[')
            8358 LOAD_NAME               31 (F)
            8360 FORMAT_VALUE             0
            8362 LOAD_CONST              29 ('1')
            8364 LOAD_NAME               30 (X)
            8366 FORMAT_VALUE             0
            8368 LOAD_CONST              39 (']')
            8370 LOAD_NAME               39 (J22)
            8372 FORMAT_VALUE             0
            8374 LOAD_CONST             228 (' التفاعل الزائف')            8376 BUILD_STRING             8
            8378 PRECALL                  1
            8382 CALL                     1
            8392 POP_TOP

574         8394 PUSH_NULL
            8396 LOAD_NAME               45 (print)
            8398 LOAD_NAME               30 (X)
            8400 FORMAT_VALUE             0
            8402 LOAD_CONST              28 ('[')
            8404 LOAD_NAME               31 (F)
            8406 FORMAT_VALUE             0
            8408 LOAD_CONST              32 ('2')
            8410 LOAD_NAME               30 (X)
            8412 FORMAT_VALUE             0
            8414 LOAD_CONST              39 (']')
            8416 LOAD_NAME               39 (J22)
            8418 FORMAT_VALUE             0
            8420 LOAD_CONST             229 (' مزعج')
            8422 BUILD_STRING             8
            8424 PRECALL                  1
            8428 CALL                     1
            8438 POP_TOP

575         8440 PUSH_NULL
            8442 LOAD_NAME               45 (print)
            8444 LOAD_NAME               30 (X)
            8446 FORMAT_VALUE             0
            8448 LOAD_CONST              28 ('[')
            8450 LOAD_NAME               31 (F)
            8452 FORMAT_VALUE             0
            8454 LOAD_CONST              34 ('3')
            8456 LOAD_NAME               30 (X)
            8458 FORMAT_VALUE             0
            8460 LOAD_CONST              39 (']')
            8462 LOAD_NAME               39 (J22)
            8464 FORMAT_VALUE             0
            8466 LOAD_CONST             230 (' محتوى مرتبط بعلامة تجارية غير معلن عنه')
            8468 BUILD_STRING             8
            8470 PRECALL                  1
            8474 CALL                     1
            8484 POP_TOP

576         8486 PUSH_NULL
            8488 LOAD_NAME               46 (input)
            8490 LOAD_NAME               30 (X)
            8492 FORMAT_VALUE             0
            8494 LOAD_CONST              28 ('[')
            8496 LOAD_NAME               31 (F)
            8498 FORMAT_VALUE             0
            8500 LOAD_CONST              38 ('×')
            8502 LOAD_NAME               30 (X)
            8504 FORMAT_VALUE             0
            8506 LOAD_CONST              39 (']')
            8508 LOAD_NAME               29 (Z)
            8510 FORMAT_VALUE             0
            8512 LOAD_CONST             216 ('اختار المناسب لك : ')
            8514 BUILD_STRING             8
            8516 LOAD_NAME               32 (L)
            8518 BINARY_OP                0 (+)
            8522 PRECALL                  1
            8526 CALL                     1
            8536 STORE_NAME             145 (xxx)

577         8538 LOAD_NAME              145 (xxx)
            8540 LOAD_CONST              29 ('1')
            8542 COMPARE_OP               2 (==)
            8548 POP_JUMP_FORWARD_IF_FALSE     3 (to 8556)
            8550 LOAD_CONST             217 ('902112')
            8552 STORE_NAME             144 (reason1)
            8554 JUMP_FORWARD           233 (to 9022)

578     >>  8556 LOAD_NAME              145 (xxx)
            8558 LOAD_CONST              32 ('2')
            8560 COMPARE_OP               2 (==)
            8566 POP_JUMP_FORWARD_IF_FALSE     3 (to 8574)
            8568 LOAD_CONST             217 ('902112')
            8570 STORE_NAME             144 (reason1)
            8572 JUMP_FORWARD           224 (to 9022)

579     >>  8574 LOAD_NAME              145 (xxx)
            8576 LOAD_CONST              34 ('3')
            8578 COMPARE_OP               2 (==)
            8584 POP_JUMP_FORWARD_IF_FALSE     2 (to 8590)
            8586 LOAD_CONST             217 ('902112')
            8588 STORE_NAME             144 (reason1)
        >>  8590 JUMP_FORWARD           215 (to 9022)

580     >>  8592 LOAD_NAME              145 (xxx)
            8594 LOAD_CONST             199 ('10')
            8596 COMPARE_OP               2 (==)
            8602 POP_JUMP_FORWARD_IF_FALSE   154 (to 8912)

581         8604 PUSH_NULL
            8606 LOAD_NAME               45 (print)
            8608 LOAD_NAME               30 (X)
            8610 FORMAT_VALUE             0
            8612 LOAD_CONST              28 ('[')
            8614 LOAD_NAME               31 (F)
            8616 FORMAT_VALUE             0
            8618 LOAD_CONST              29 ('1')
            8620 LOAD_NAME               30 (X)
            8622 FORMAT_VALUE             0
            8624 LOAD_CONST              39 (']')
            8626 LOAD_NAME               39 (J22)
            8628 FORMAT_VALUE             0
            8630 LOAD_CONST             231 (' المقامرة')
            8632 BUILD_STRING             8
            8634 PRECALL                  1
            8638 CALL                     1
            8648 POP_TOP

582         8650 PUSH_NULL
            8652 LOAD_NAME               45 (print)
            8654 LOAD_NAME               30 (X)
            8656 FORMAT_VALUE             0
            8658 LOAD_CONST              28 ('[')
            8660 LOAD_NAME               31 (F)
            8662 FORMAT_VALUE             0
            8664 LOAD_CONST              32 ('2')
            8666 LOAD_NAME               30 (X)
            8668 FORMAT_VALUE             0
            8670 LOAD_CONST              39 (']')
            8672 LOAD_NAME               39 (J22)
            8674 FORMAT_VALUE             0
            8676 LOAD_CONST             232 (' الكحول والتبغ والمخدرات')
            8678 BUILD_STRING             8
            8680 PRECALL                  1
            8684 CALL                     1
            8694 POP_TOP

583         8696 PUSH_NULL
            8698 LOAD_NAME               45 (print)
            8700 LOAD_NAME               30 (X)
            8702 FORMAT_VALUE             0
            8704 LOAD_CONST              28 ('[')
            8706 LOAD_NAME               31 (F)
            8708 FORMAT_VALUE             0
            8710 LOAD_CONST              34 ('3')
            8712 LOAD_NAME               30 (X)
            8714 FORMAT_VALUE             0
            8716 LOAD_CONST              39 (']')
            8718 LOAD_NAME               39 (J22)
            8720 FORMAT_VALUE             0
            8722 LOAD_CONST             233 (' الأسلحة النارية والأسلحة الخطرة')
            8724 BUILD_STRING             8
            8726 PRECALL                  1
            8730 CALL                     1
            8740 POP_TOP

584         8742 PUSH_NULL
            8744 LOAD_NAME               45 (print)
            8746 LOAD_NAME               30 (X)
            8748 FORMAT_VALUE             0
            8750 LOAD_CONST              28 ('[')
            8752 LOAD_NAME               31 (F)
            8754 FORMAT_VALUE             0
            8756 LOAD_CONST              36 ('4')
            8758 LOAD_NAME               30 (X)
            8760 FORMAT_VALUE             0
            8762 LOAD_CONST              39 (']')
            8764 LOAD_NAME               39 (J22)
            8766 FORMAT_VALUE             0
            8768 LOAD_CONST             234 (' تجارة السلع والخدمات الأخرى الخاضعة للرقابة')
            8770 BUILD_STRING             8
            8772 PRECALL                  1
            8776 CALL                     1
            8786 POP_TOP

585         8788 PUSH_NULL
            8790 LOAD_NAME               46 (input)
            8792 LOAD_NAME               30 (X)
            8794 FORMAT_VALUE             0
            8796 LOAD_CONST              28 ('[')
            8798 LOAD_NAME               31 (F)
            8800 FORMAT_VALUE             0
            8802 LOAD_CONST              38 ('×')
            8804 LOAD_NAME               30 (X)
            8806 FORMAT_VALUE             0
            8808 LOAD_CONST              39 (']')
            8810 LOAD_NAME               29 (Z)
            8812 FORMAT_VALUE             0
            8814 LOAD_CONST             216 ('اختار المناسب لك : ')
            8816 BUILD_STRING             8
            8818 LOAD_NAME               32 (L)
            8820 BINARY_OP                0 (+)
            8824 PRECALL                  1
            8828 CALL                     1
            8838 STORE_NAME             145 (xxx)

586         8840 LOAD_NAME              145 (xxx)
            8842 LOAD_CONST              29 ('1')
            8844 COMPARE_OP               2 (==)
            8850 POP_JUMP_FORWARD_IF_FALSE     3 (to 8858)
            8852 LOAD_CONST             217 ('902112')
            8854 STORE_NAME             144 (reason1)
            8856 JUMP_FORWARD            82 (to 9022)

587     >>  8858 LOAD_NAME              145 (xxx)
            8860 LOAD_CONST              32 ('2')
            8862 COMPARE_OP               2 (==)
            8868 POP_JUMP_FORWARD_IF_FALSE     3 (to 8876)
            8870 LOAD_CONST             217 ('902112')
            8872 STORE_NAME             144 (reason1)
            8874 JUMP_FORWARD            73 (to 9022)

588     >>  8876 LOAD_NAME              145 (xxx)
            8878 LOAD_CONST              34 ('3')
            8880 COMPARE_OP               2 (==)
            8886 POP_JUMP_FORWARD_IF_FALSE     3 (to 8894)
            8888 LOAD_CONST             217 ('902112')
            8890 STORE_NAME             144 (reason1)
            8892 JUMP_FORWARD            64 (to 9022)

589     >>  8894 LOAD_NAME              145 (xxx)
            8896 LOAD_CONST              36 ('4')
            8898 COMPARE_OP               2 (==)
            8904 POP_JUMP_FORWARD_IF_FALSE     2 (to 8910)
            8906 LOAD_CONST             217 ('902112')
            8908 STORE_NAME             144 (reason1)
        >>  8910 JUMP_FORWARD            55 (to 9022)

590     >>  8912 LOAD_NAME              145 (xxx)
            8914 LOAD_CONST             201 ('11')
            8916 COMPARE_OP               2 (==)
            8922 POP_JUMP_FORWARD_IF_FALSE     3 (to 8930)
            8924 LOAD_CONST             217 ('902112')
            8926 STORE_NAME             144 (reason1)
            8928 JUMP_FORWARD            46 (to 9022)

591     >>  8930 LOAD_NAME              145 (xxx)
            8932 LOAD_CONST             203 ('12')
            8934 COMPARE_OP               2 (==)
            8940 POP_JUMP_FORWARD_IF_FALSE     3 (to 8948)
            8942 LOAD_CONST             217 ('902112')
            8944 STORE_NAME             144 (reason1)
            8946 JUMP_FORWARD            37 (to 9022)

592     >>  8948 LOAD_NAME              145 (xxx)
            8950 LOAD_CONST             205 ('13')
            8952 COMPARE_OP               2 (==)
            8958 POP_JUMP_FORWARD_IF_FALSE     3 (to 8966)
            8960 LOAD_CONST             217 ('902112')
            8962 STORE_NAME             144 (reason1)
            8964 JUMP_FORWARD            28 (to 9022)

593     >>  8966 LOAD_NAME              145 (xxx)
            8968 LOAD_CONST             207 ('14')
            8970 COMPARE_OP               2 (==)
            8976 POP_JUMP_FORWARD_IF_FALSE    22 (to 9022)

594         8978 PUSH_NULL
            8980 LOAD_NAME               45 (print)
            8982 LOAD_CONST             235 ('لازم تكتبه حسب الانتهاك الي بلحساب')
            8984 PRECALL                  1
            8988 CALL                     1
            8998 POP_TOP

595         9000 PUSH_NULL
            9002 LOAD_NAME               46 (input)
            9004 LOAD_CONST             236 ('يرجا كتابة النص بلغه الانكليزي : ')
            9006 PRECALL                  1
            9010 CALL                     1
            9020 STORE_NAME             146 (ktab)

597     >>  9022 PUSH_NULL
            9024 LOAD_NAME              107 (open)
            9026 LOAD_CONST             131 ('SAIPR_REPORT_AFRIT_SAIPR.txt')
            9028 LOAD_CONST             136 ('r')
            9030 PRECALL                  2
            9034 CALL                     2
            9044 LOAD_METHOD            112 (read)
            9066 PRECALL                  0
            9070 CALL                     0
            9080 LOAD_METHOD            113 (splitlines)
            9102 PRECALL                  0
            9106 CALL                     0
            9116 STORE_NAME              28 (O)

598         9118 LOAD_NAME               28 (O)
            9120 GET_ITER
        >>  9122 FOR_ITER                23 (to 9170)
            9124 STORE_NAME             114 (prox)

600         9126 LOAD_NAME               20 (ls)
            9128 LOAD_METHOD            115 (append)
            9150 LOAD_NAME              114 (prox)
            9152 PRECALL                  1
            9156 CALL                     1
            9166 POP_TOP
            9168 JUMP_BACKWARD           24 (to 9122)

601     >>  9170 PUSH_NULL
            9172 LOAD_NAME               44 (clear)
            9174 PRECALL                  0
            9178 CALL                     0
            9188 POP_TOP

602         9190 LOAD_CONST             237 (<code object afr at 0x7d9649bb20, file "", line 602>)
            9192 MAKE_FUNCTION            0
            9194 STORE_NAME             147 (afr)

895         9196 LOAD_CONST               0 (0)
            9198 STORE_NAME             148 (hussain)

896         9200 LOAD_NAME              148 (hussain)
            9202 PUSH_NULL
            9204 LOAD_NAME              143 (len)
            9206 LOAD_NAME               21 (sisn)
            9208 PRECALL                  1
            9212 CALL                     1
            9222 COMPARE_OP               0 (<)
            9228 EXTENDED_ARG             1
            9230 POP_JUMP_FORWARD_IF_FALSE   488 (to 10208)

897     >>  9232 LOAD_NAME               21 (sisn)
            9234 GET_ITER
        >>  9236 EXTENDED_ARG             1
            9238 FOR_ITER               464 (to 10168)
            9240 STORE_NAME             118 (i)

898         9242 PUSH_NULL
            9244 LOAD_NAME               50 (str)
            9246 LOAD_NAME              118 (i)
            9248 LOAD_METHOD            149 (strip)
            9270 PRECALL                  0
            9274 CALL                     0
            9284 PRECALL                  1
            9288 CALL                     1
            9298 STORE_NAME              79 (sessionid)

899         9300 BUILD_LIST               0
            9302 STORE_NAME             150 (video_list)

900         9304 LOAD_CONST               0 (0)
            9306 STORE_NAME             151 (max_cursor)

901         9308 NOP

902     >>  9310 PUSH_NULL
            9312 LOAD_NAME               50 (str)
            9314 PUSH_NULL
            9316 LOAD_NAME                3 (binascii)
            9318 LOAD_ATTR               51 (hexlify)
            9328 PUSH_NULL
            9330 LOAD_NAME                4 (os)
            9332 LOAD_ATTR               52 (urandom)
            9342 LOAD_CONST              42 (8)
            9344 PRECALL                  1
            9348 CALL                     1
            9358 PRECALL                  1
            9362 CALL                     1
            9372 LOAD_METHOD             53 (decode)
            9394 PRECALL                  0
            9398 CALL                     0
            9408 PRECALL                  1
            9412 CALL                     1
            9422 STORE_NAME              54 (openudid)

903         9424 PUSH_NULL
            9426 LOAD_NAME               70 (int)
            9428 PUSH_NULL
            9430 LOAD_NAME               11 (time)
            9432 LOAD_ATTR               11 (time)
            9442 PRECALL                  0
            9446 CALL                     0
            9456 LOAD_CONST              57 (1000)
            9458 BINARY_OP                5 (*)
            9462 PRECALL                  1
            9466 CALL                     1
            9476 STORE_NAME              71 (_rticket)

904         9478 PUSH_NULL
            9480 LOAD_NAME               50 (str)
            9482 PUSH_NULL
            9484 LOAD_NAME               70 (int)
            9486 PUSH_NULL
            9488 LOAD_NAME               11 (time)
            9490 LOAD_ATTR               11 (time)
            9500 PRECALL                  0
            9504 CALL                     0
            9514 LOAD_CONST              57 (1000)
            9516 BINARY_OP                5 (*)
            9520 PRECALL                  1
            9524 CALL                     1
            9534 PRECALL                  1
            9538 CALL                     1
            9548 LOAD_CONST               1 (None)
            9550 LOAD_CONST              58 (10)
            9552 BUILD_SLICE              2
            9554 BINARY_SUBSCR
            9564 STORE_NAME              72 (ts)

905         9566 LOAD_CONST             238 ('https://api2-19-h2.musical.ly/aweme/v1/aweme/post/?source=0&max_cursor=')
            9568 LOAD_NAME              151 (max_cursor)
            9570 FORMAT_VALUE             0
            9572 LOAD_CONST             239 ('&sec_user_id=')
            9574 LOAD_NAME              125 (ur)
            9576 FORMAT_VALUE             0
            9578 LOAD_CONST             240 ('&count=20&app_skin=white&manifest_version_code=2021600040&_rticket=')
            9580 LOAD_NAME               71 (_rticket)
            9582 FORMAT_VALUE             0
            9584 LOAD_CONST             241 ('&app_language=en&app_type=normal&iid=7368148584393508613&channel=googleplay&device_type=SM-G973N&language=en&cpu_support64=true&host_abi=armeabi-v7a&locale=en&uuid=354730022862944&resolution=720*1280&openudid=')
            9586 LOAD_NAME               54 (openudid)
            9588 FORMAT_VALUE             0
            9590 LOAD_CONST             242 ('&update_version_code=2021600040&ac2=wifi5g&sys_region=US&os_api=32&uoo=0&timezone_name=Africa%2FNairobi&dpi=240&carrier_region=IQ&ac=wifi&device_id=6980700221262235138&pass-route=1&mcc_mnc=31002&os_version=12&timezone_offset=10800&version_code=160004&carrier_region_v2=310&app_name=musical_ly&ab_version=16.0.4&version_name=16.0.4&device_brand=samsung&op_region=IQ&ssmix=a&pass-region=1&device_platform=android&build_number=16.0.4&region=US&aid=1233&ts=')
            9592 LOAD_NAME               72 (ts)
            9594 FORMAT_VALUE             0
            9596 BUILD_STRING            10
            9598 STORE_NAME              76 (u)

906         9600 PUSH_NULL
            9602 LOAD_NAME               25 (ttsign)
            9604 LOAD_NAME               76 (u)
            9606 LOAD_METHOD             87 (split)
            9628 LOAD_CONST              92 ('?')
            9630 PRECALL                  1
            9634 CALL                     1
            9644 LOAD_CONST              93 (1)
            9646 BINARY_SUBSCR
            9656 LOAD_CONST              49 ('')
            9658 LOAD_CONST               1 (None)
            9660 PRECALL                  3
            9664 CALL                     3
            9674 LOAD_METHOD             88 (get_value)
            9696 PRECALL                  0
            9700 CALL                     0
            9710 STORE_NAME              89 (signed)

907         9712 LOAD_NAME               89 (signed)
            9714 LOAD_CONST              94 ('x-gorgon')
            9716 BINARY_SUBSCR
            9726 STORE_NAME              90 (x_gorgon)

908         9728 LOAD_NAME               89 (signed)
            9730 LOAD_CONST              96 ('x-khronos')
            9732 BINARY_SUBSCR
            9742 STORE_NAME              92 (x_khronos)

909         9744 LOAD_CONST             243 ('gzip')

910         9746 LOAD_CONST             244 ('Keep-Alive')

911         9748 LOAD_CONST             177 ('sessionid=')
            9750 PUSH_NULL
            9752 LOAD_NAME                1 (random)
            9754 LOAD_ATTR               55 (choice)
            9764 BUILD_LIST               0
            9766 LOAD_CONST             245 (('58722b392919a8cb490e9150a0214e9d', '7102eb970e667d3e870a53eaa9b72dcd', '4c1b5e5553effcceab87f5def506bd39', 'f448b52989da0e9186516af7d6618018', 'fdd47427291edd263755a5e1f8f57561', '94ec15f73dd664ff5f27195bb3c4f2e4', '1eb64c7737a9ff4bd73ba79f865fa216', '3d0a85f5ab8c4bb7811753c9b662195f', 'e839032d49dcad97dfabb33729f43ac0'))
            9768 LIST_EXTEND              1
            9770 PRECALL                  1
            9774 CALL                     1
            9784 FORMAT_VALUE             0
            9786 BUILD_STRING             2

912         9788 LOAD_CONST             246 ('api2-19-h2.musical.ly')

913         9790 LOAD_CONST              29 ('1')
            9792 LOAD_CONST             247 ('okhttp/3.10.0.1')
914         9794 LOAD_NAME               90 (x_gorgon)

915         9796 LOAD_NAME               92 (x_khronos)

909         9798 LOAD_CONST             248 (('Accept-Encoding', 'Connection', 'Cookie', 'Host', 'sdk-version', 'User-Agent', 'X-Gorgon', 'X-Khronos'))
            9800 BUILD_CONST_KEY_MAP      8
            9802 STORE_NAME              94 (h)

916         9804 NOP

917         9806 PUSH_NULL
            9808 LOAD_NAME                0 (requests)
            9810 LOAD_ATTR               66 (get)
            9820 LOAD_NAME               76 (u)
            9822 LOAD_NAME               94 (h)
            9824 KW_NAMES                55
            9826 PRECALL                  2
            9830 CALL                     2
            9840 LOAD_METHOD             10 (json)
            9862 PRECALL                  0
            9866 CALL                     0
            9876 STORE_NAME              97 (r)

919         9878 NOP

920         9880 LOAD_NAME               97 (r)
            9882 LOAD_CONST             249 ('max_cursor')
            9884 BINARY_SUBSCR
            9894 STORE_NAME             151 (max_cursor)
            9896 JUMP_FORWARD            38 (to 9974)
        >>  9898 PUSH_EXC_INFO

921         9900 LOAD_NAME              152 (Exception)
            9902 CHECK_EXC_MATCH
            9904 POP_JUMP_FORWARD_IF_FALSE    30 (to 9966)
            9906 POP_TOP

922         9908 LOAD_CONST             250 ('No more videos')
            9910 PUSH_NULL
            9912 LOAD_NAME                0 (requests)
            9914 LOAD_ATTR               66 (get)
            9924 LOAD_NAME               76 (u)
            9926 LOAD_NAME               94 (h)
            9928 KW_NAMES                55
            9930 PRECALL                  2
            9934 CALL                     2
            9944 LOAD_ATTR               96 (text)
            9954 CONTAINS_OP              0
            9956 POP_JUMP_FORWARD_IF_FALSE     2 (to 9962)

923         9958 POP_EXCEPT
            9960 JUMP_FORWARD           101 (to 10164)

922     >>  9962 POP_EXCEPT
            9964 JUMP_FORWARD             4 (to 9974)

921     >>  9966 RERAISE                  0
        >>  9968 COPY                     3
            9970 POP_EXCEPT
            9972 RERAISE                  1

924     >>  9974 LOAD_NAME               97 (r)
            9976 LOAD_CONST             251 ('aweme_list')
            9978 BINARY_SUBSCR
            9988 STORE_NAME             153 (aweme_list)

925         9990 LOAD_NAME              153 (aweme_list)
            9992 GET_ITER
        >>  9994 FOR_ITER                74 (to 10144)
            9996 STORE_NAME             154 (aweme)

926         9998 LOAD_NAME              154 (aweme)
           10000 LOAD_CONST             252 ('aweme_id')
           10002 BINARY_SUBSCR
           10012 STORE_NAME             155 (aweme_id)

927        10014 LOAD_NAME              155 (aweme_id)
           10016 LOAD_NAME               18 (tar)
           10018 CONTAINS_OP              0
           10020 POP_JUMP_FORWARD_IF_FALSE     1 (to 10024)

928        10022 JUMP_FORWARD            21 (to 10066)

930     >> 10024 LOAD_NAME               18 (tar)
           10026 LOAD_METHOD            115 (append)
           10048 LOAD_NAME              155 (aweme_id)
           10050 PRECALL                  1
           10054 CALL                     1
           10064 POP_TOP

931     >> 10066 PUSH_NULL
           10068 LOAD_NAME                5 (threading)
           10070 LOAD_ATTR              119 (Thread)

932        10080 LOAD_NAME              147 (afr)

934        10082 LOAD_NAME              155 (aweme_id)

935        10084 LOAD_NAME               79 (sessionid)

933        10086 BUILD_TUPLE              2

931        10088 KW_NAMES               253
           10090 PRECALL                  2
           10094 CALL                     2

937        10104 LOAD_METHOD            121 (start)
           10126 PRECALL                  0
           10130 CALL                     0
           10140 POP_TOP
           10142 JUMP_BACKWARD           75 (to 9994)

925     >> 10144 JUMP_FORWARD             7 (to 10160)
        >> 10146 PUSH_EXC_INFO

939        10148 POP_TOP
           10150 POP_EXCEPT
           10152 JUMP_FORWARD             3 (to 10160)
        >> 10154 COPY                     3
           10156 POP_EXCEPT
           10158 RERAISE                  1

901     >> 10160 EXTENDED_ARG             1
           10162 JUMP_BACKWARD          427 (to 9310)

923     >> 10164 EXTENDED_ARG             1
           10166 JUMP_BACKWARD          466 (to 9236)

896     >> 10168 LOAD_NAME              148 (hussain)
           10170 PUSH_NULL
           10172 LOAD_NAME              143 (len)
           10174 LOAD_NAME               21 (sisn)
           10176 PRECALL                  1
           10180 CALL                     1
           10190 COMPARE_OP               0 (<)
           10196 EXTENDED_ARG             1
           10198 POP_JUMP_BACKWARD_IF_TRUE   484 (to 9232)
           10200 LOAD_CONST               1 (None)
           10202 RETURN_VALUE

439     >> 10204 LOAD_CONST               1 (None)
           10206 RETURN_VALUE

896     >> 10208 LOAD_CONST               1 (None)
           10210 RETURN_VALUE
ExceptionTable:
  2884 to 2914 -> 2918 [0]
  2918 to 2920 -> 2926 [1] lasti
  2934 to 2964 -> 2968 [0]
  2968 to 2970 -> 2976 [1] lasti
  3054 to 3102 -> 3128 [1] lasti
  3128 to 3134 -> 3136 [3] lasti
  3142 to 3142 -> 3136 [3] lasti
  3222 to 3270 -> 3296 [1] lasti
  3296 to 3302 -> 3304 [3] lasti
  3310 to 3310 -> 3304 [3] lasti
  3390 to 3438 -> 3464 [1] lasti
  3464 to 3470 -> 3472 [3] lasti
  3478 to 3478 -> 3472 [3] lasti
  3488 to 3634 -> 3638 [0]
  3638 to 3682 -> 3688 [1] lasti
  4384 to 4854 -> 4858 [0]
  4858 to 4902 -> 4908 [1] lasti
  5116 to 5216 -> 5220 [0]
  5220 to 5290 -> 5344 [1] lasti
  5296 to 5338 -> 5344 [1] lasti
  5366 to 5430 -> 5434 [0]
  5434 to 5490 -> 5498 [1] lasti
  5496 to 5496 -> 5498 [1] lasti
  5760 to 6006 -> 6010 [1]
  6010 to 6066 -> 6074 [2] lasti
  6072 to 6072 -> 6074 [2] lasti
  9806 to 9876 -> 10146 [1]
  9880 to 9894 -> 9898 [1]
  9896 to 9896 -> 10146 [1]
  9898 to 9956 -> 9968 [2] lasti
  9958 to 9958 -> 10146 [1]
  9962 to 9964 -> 10146 [1]
  9966 to 9966 -> 9968 [2] lasti
  9968 to 10142 -> 10146 [1]
  10146 to 10148 -> 10154 [2] lasti

Disassembly of <code object ttsign at 0x7cb6352af0, file "", line 19>:
 19           0 RESUME                   0
              2 LOAD_NAME                0 (__name__)
              4 STORE_NAME               1 (__module__)
              6 LOAD_CONST               0 ('ttsign')
              8 STORE_NAME               2 (__qualname__)

 20          10 LOAD_CONST               1 ('params')
             12 LOAD_NAME                3 (str)
             14 LOAD_CONST               2 ('data')
             16 LOAD_NAME                3 (str)
             18 LOAD_CONST               3 ('cookies')
             20 LOAD_NAME                3 (str)
             22 LOAD_CONST               4 ('return')
             24 LOAD_CONST               5 (None)
             26 BUILD_TUPLE              8
             28 LOAD_CONST               6 (<code object __init__ at 0x7cb61e9b60, file "", line 20>)
             30 MAKE_FUNCTION            4 (annotations)
             32 STORE_NAME               4 (__init__)

 25          34 LOAD_CONST               2 ('data')
             36 LOAD_NAME                3 (str)
             38 LOAD_CONST               4 ('return')
             40 LOAD_NAME                3 (str)
             42 BUILD_TUPLE              4
             44 LOAD_CONST               7 (<code object hash at 0x7cb634cc00, file "", line 25>)
             46 MAKE_FUNCTION            4 (annotations)
             48 STORE_NAME               5 (hash)

 28          50 LOAD_CONST               4 ('return')
             52 LOAD_NAME                3 (str)
             54 BUILD_TUPLE              2
             56 LOAD_CONST               8 (<code object get_base_string at 0x7cb61c0eb0, file "", line 28>)
             58 MAKE_FUNCTION            4 (annotations)
             60 STORE_NAME               6 (get_base_string)

 40          62 LOAD_CONST               4 ('return')
             64 LOAD_NAME                7 (json)
             66 BUILD_TUPLE              2
             68 LOAD_CONST               9 (<code object get_value at 0x7cb62fbaa0, file "", line 40>)
             70 MAKE_FUNCTION            4 (annotations)
             72 STORE_NAME               8 (get_value)

 43          74 LOAD_CONST               2 ('data')
             76 LOAD_NAME                3 (str)
             78 LOAD_CONST               4 ('return')
             80 LOAD_NAME                7 (json)
             82 BUILD_TUPLE              4
             84 LOAD_CONST              10 (<code object encrypt at 0x7f5649cea0, file "", line 43>)
             86 MAKE_FUNCTION            4 (annotations)
             88 STORE_NAME               9 (encrypt)

 99          90 LOAD_CONST              11 (<code object rbit_algorithm at 0x7cb62c9470, file "", line 99>)
             92 MAKE_FUNCTION            0
             94 STORE_NAME              10 (rbit_algorithm)

108          96 LOAD_CONST              12 (<code object hex_string at 0x7cb6204c90, file "", line 108>)
             98 MAKE_FUNCTION            0
            100 STORE_NAME              11 (hex_string)

114         102 LOAD_CONST              13 (<code object reverse at 0x7cb63510d0, file "", line 114>)
            104 MAKE_FUNCTION            0
            106 STORE_NAME              12 (reverse)
            108 LOAD_CONST               5 (None)
            110 RETURN_VALUE

Disassembly of <code object __init__ at 0x7cb61e9b60, file "", line 20>:
 20           0 RESUME                   0

 21           2 LOAD_FAST                1 (params)
              4 LOAD_FAST                0 (self)
              6 STORE_ATTR               0 (params)

 22          16 LOAD_FAST                2 (data)
             18 LOAD_FAST                0 (self)
             20 STORE_ATTR               1 (data)

 23          30 LOAD_FAST                3 (cookies)
             32 LOAD_FAST                0 (self)
             34 STORE_ATTR               2 (cookies)
             44 LOAD_CONST               0 (None)
             46 RETURN_VALUE

Disassembly of <code object hash at 0x7cb634cc00, file "", line 25>:
 25           0 RESUME                   0

 26           2 LOAD_GLOBAL              1 (NULL + str)
             14 LOAD_GLOBAL              3 (NULL + hashlib)
             26 LOAD_ATTR                2 (md5)
             36 LOAD_FAST                1 (data)
             38 LOAD_METHOD              3 (encode)
             60 PRECALL                  0
             64 CALL                     0
             74 PRECALL                  1
             78 CALL                     1
             88 LOAD_METHOD              4 (hexdigest)
            110 PRECALL                  0
            114 CALL                     0
            124 PRECALL                  1
            128 CALL                     1
            138 RETURN_VALUE

Disassembly of <code object get_base_string at 0x7cb61c0eb0, file "", line 28>:
 28           0 RESUME                   0

 29           2 LOAD_FAST                0 (self)
              4 LOAD_METHOD              0 (hash)
             26 LOAD_FAST                0 (self)
             28 LOAD_ATTR                1 (params)
             38 PRECALL                  1
             42 CALL                     1
             52 STORE_FAST               1 (base_str)

 31          54 LOAD_FAST                0 (self)
             56 LOAD_ATTR                2 (data)
             66 POP_JUMP_FORWARD_IF_FALSE    29 (to 126)
             68 LOAD_FAST                1 (base_str)
             70 LOAD_FAST                0 (self)
             72 LOAD_METHOD              0 (hash)
             94 LOAD_FAST                0 (self)
             96 LOAD_ATTR                2 (data)
            106 PRECALL                  1
            110 CALL                     1
            120 BINARY_OP                0 (+)
            124 JUMP_FORWARD            17 (to 160)
        >>  126 LOAD_FAST                1 (base_str)
            128 LOAD_GLOBAL              7 (NULL + str)
            140 LOAD_CONST               1 ('00000000000000000000000000000000')
            142 PRECALL                  1
            146 CALL                     1
            156 BINARY_OP                0 (+)

 30     >>  160 STORE_FAST               1 (base_str)

 35         162 LOAD_FAST                0 (self)
            164 LOAD_ATTR                4 (cookies)

 34         174 POP_JUMP_FORWARD_IF_FALSE    29 (to 234)
            176 LOAD_FAST                1 (base_str)
            178 LOAD_FAST                0 (self)
            180 LOAD_METHOD              0 (hash)
            202 LOAD_FAST                0 (self)
            204 LOAD_ATTR                4 (cookies)
            214 PRECALL                  1
            218 CALL                     1
            228 BINARY_OP                0 (+)
            232 JUMP_FORWARD            17 (to 268)

 36     >>  234 LOAD_FAST                1 (base_str)
            236 LOAD_GLOBAL              7 (NULL + str)
            248 LOAD_CONST               1 ('00000000000000000000000000000000')
            250 PRECALL                  1
            254 CALL                     1
            264 BINARY_OP                0 (+)

 33     >>  268 STORE_FAST               1 (base_str)

 38         270 LOAD_FAST                1 (base_str)
            272 RETURN_VALUE

Disassembly of <code object get_value at 0x7cb62fbaa0, file "", line 40>:
 40           0 RESUME                   0

 41           2 LOAD_FAST                0 (self)
              4 LOAD_METHOD              0 (encrypt)
             26 LOAD_FAST                0 (self)
             28 LOAD_METHOD              1 (get_base_string)
             50 PRECALL                  0
             54 CALL                     0
             64 PRECALL                  1
             68 CALL                     1
             78 RETURN_VALUE

Disassembly of <code object encrypt at 0x7f5649cea0, file "", line 43>:
 43           0 RESUME                   0

 44           2 LOAD_GLOBAL              1 (NULL + time)
             14 LOAD_ATTR                0 (time)
             24 PRECALL                  0
             28 CALL                     0
             38 STORE_FAST               2 (unix)

 45          40 LOAD_CONST               1 (20)
             42 STORE_FAST               3 (len)

 46          44 BUILD_LIST               0
             46 LOAD_CONST               2 ((223, 119, 185, 64, 185, 155, 132, 131, 209, 185, 203, 209, 247, 194, 185, 133, 195, 208, 251, 195))
             48 LIST_EXTEND              1
             50 STORE_FAST               4 (key)

 68          52 BUILD_LIST               0
             54 STORE_FAST               5 (param_list)

 69          56 LOAD_GLOBAL              3 (NULL + range)
             68 LOAD_CONST               3 (0)
             70 LOAD_CONST               4 (12)
             72 LOAD_CONST               5 (4)
             74 PRECALL                  3
             78 CALL                     3
             88 GET_ITER
        >>   90 FOR_ITER                93 (to 278)
             92 STORE_FAST               6 (i)

 70          94 LOAD_FAST                1 (data)
             96 LOAD_CONST               6 (8)
             98 LOAD_FAST                6 (i)
            100 BINARY_OP                5 (*)
            104 LOAD_CONST               6 (8)
            106 LOAD_FAST                6 (i)
            108 LOAD_CONST               7 (1)
            110 BINARY_OP                0 (+)
            114 BINARY_OP                5 (*)
            118 BUILD_SLICE              2
            120 BINARY_SUBSCR
            130 STORE_FAST               7 (temp)

 71         132 LOAD_GLOBAL              3 (NULL + range)
            144 LOAD_CONST               5 (4)
            146 PRECALL                  1
            150 CALL                     1
            160 GET_ITER
        >>  162 FOR_ITER                56 (to 276)
            164 STORE_FAST               8 (j)

 72         166 LOAD_GLOBAL              5 (NULL + int)
            178 LOAD_FAST                7 (temp)
            180 LOAD_FAST                8 (j)
            182 LOAD_CONST               8 (2)
            184 BINARY_OP                5 (*)
            188 LOAD_FAST                8 (j)
            190 LOAD_CONST               7 (1)
            192 BINARY_OP                0 (+)
            196 LOAD_CONST               8 (2)
            198 BINARY_OP                5 (*)
            202 BUILD_SLICE              2
            204 BINARY_SUBSCR
            214 LOAD_CONST               9 (16)
            216 PRECALL                  2
            220 CALL                     2
            230 STORE_FAST               9 (H)

 73         232 LOAD_FAST                5 (param_list)
            234 LOAD_METHOD              3 (append)
            256 LOAD_FAST                9 (H)
            258 PRECALL                  1
            262 CALL                     1
            272 POP_TOP
            274 JUMP_BACKWARD           57 (to 162)

 71     >>  276 JUMP_BACKWARD           94 (to 90)

 74     >>  278 LOAD_FAST                5 (param_list)
            280 LOAD_METHOD              4 (extend)
            302 BUILD_LIST               0
            304 LOAD_CONST              10 ((0, 6, 11, 28))
            306 LIST_EXTEND              1
            308 PRECALL                  1
            312 CALL                     1
            322 POP_TOP

 75         324 LOAD_GLOBAL              5 (NULL + int)
            336 LOAD_GLOBAL             11 (NULL + hex)
            348 LOAD_GLOBAL              5 (NULL + int)
            360 LOAD_FAST                2 (unix)
            362 PRECALL                  1
            366 CALL                     1
            376 PRECALL                  1
            380 CALL                     1
            390 LOAD_CONST               9 (16)
            392 PRECALL                  2
            396 CALL                     2
            406 STORE_FAST               9 (H)

 76         408 LOAD_FAST                5 (param_list)
            410 LOAD_METHOD              3 (append)
            432 LOAD_FAST                9 (H)
            434 LOAD_CONST              11 (4278190080)
            436 BINARY_OP                1 (&)
            440 LOAD_CONST              12 (24)
            442 BINARY_OP                9 (>>)
            446 PRECALL                  1
            450 CALL                     1
            460 POP_TOP

 77         462 LOAD_FAST                5 (param_list)
            464 LOAD_METHOD              3 (append)
            486 LOAD_FAST                9 (H)
            488 LOAD_CONST              13 (16711680)
            490 BINARY_OP                1 (&)
            494 LOAD_CONST               9 (16)
            496 BINARY_OP                9 (>>)
            500 PRECALL                  1
            504 CALL                     1
            514 POP_TOP

 78         516 LOAD_FAST                5 (param_list)
            518 LOAD_METHOD              3 (append)
            540 LOAD_FAST                9 (H)
            542 LOAD_CONST              14 (65280)
            544 BINARY_OP                1 (&)
            548 LOAD_CONST               6 (8)
            550 BINARY_OP                9 (>>)
            554 PRECALL                  1
            558 CALL                     1
            568 POP_TOP

 79         570 LOAD_FAST                5 (param_list)
            572 LOAD_METHOD              3 (append)
            594 LOAD_FAST                9 (H)
            596 LOAD_CONST              15 (255)
            598 BINARY_OP                1 (&)
            602 LOAD_CONST               3 (0)
            604 BINARY_OP                9 (>>)
            608 PRECALL                  1
            612 CALL                     1
            622 POP_TOP

 80         624 BUILD_LIST               0
            626 STORE_FAST              10 (eor_result_list)

 81         628 LOAD_GLOBAL             13 (NULL + zip)
            640 LOAD_FAST                5 (param_list)
            642 LOAD_FAST                4 (key)
            644 PRECALL                  2
            648 CALL                     2
            658 GET_ITER
        >>  660 FOR_ITER                29 (to 720)
            662 UNPACK_SEQUENCE          2
            666 STORE_FAST              11 (A)
            668 STORE_FAST              12 (B)

 82         670 LOAD_FAST               10 (eor_result_list)
            672 LOAD_METHOD              3 (append)
            694 LOAD_FAST               11 (A)
            696 LOAD_FAST               12 (B)
            698 BINARY_OP               12 (^)
            702 PRECALL                  1
            706 CALL                     1
            716 POP_TOP
            718 JUMP_BACKWARD           30 (to 660)

 83     >>  720 LOAD_GLOBAL              3 (NULL + range)
            732 LOAD_FAST                3 (len)
            734 PRECALL                  1
            738 CALL                     1
            748 GET_ITER
        >>  750 FOR_ITER                85 (to 922)
            752 STORE_FAST               6 (i)

 84         754 LOAD_FAST                0 (self)
            756 LOAD_METHOD              7 (reverse)
            778 LOAD_FAST               10 (eor_result_list)
            780 LOAD_FAST                6 (i)
            782 BINARY_SUBSCR
            792 PRECALL                  1
            796 CALL                     1
            806 STORE_FAST              13 (C)

 85         808 LOAD_FAST               10 (eor_result_list)
            810 LOAD_FAST                6 (i)
            812 LOAD_CONST               7 (1)
            814 BINARY_OP                0 (+)
            818 LOAD_FAST                3 (len)
            820 BINARY_OP                6 (%)
            824 BINARY_SUBSCR
            834 STORE_FAST              14 (D)

 86         836 LOAD_FAST               13 (C)
            838 LOAD_FAST               14 (D)
            840 BINARY_OP               12 (^)
            844 STORE_FAST              15 (E)

 87         846 LOAD_FAST                0 (self)
            848 LOAD_METHOD              8 (rbit_algorithm)
            870 LOAD_FAST               15 (E)
            872 PRECALL                  1
            876 CALL                     1
            886 STORE_FAST              16 (F)

 88         888 LOAD_FAST               16 (F)
            890 LOAD_CONST              16 (4294967295)
            892 BINARY_OP               12 (^)
            896 LOAD_FAST                3 (len)
            898 BINARY_OP               12 (^)
            902 LOAD_CONST              15 (255)
            904 BINARY_OP                1 (&)
            908 STORE_FAST               9 (H)

 89         910 LOAD_FAST                9 (H)
            912 LOAD_FAST               10 (eor_result_list)
            914 LOAD_FAST                6 (i)
            916 STORE_SUBSCR
            920 JUMP_BACKWARD           86 (to 750)

 90     >>  922 LOAD_CONST              17 ('')
            924 STORE_FAST              17 (result)

 91         926 LOAD_FAST               10 (eor_result_list)
            928 GET_ITER
        >>  930 FOR_ITER                26 (to 984)
            932 STORE_FAST              18 (param)

 92         934 LOAD_FAST               17 (result)
            936 LOAD_FAST                0 (self)
            938 LOAD_METHOD              9 (hex_string)
            960 LOAD_FAST               18 (param)
            962 PRECALL                  1
            966 CALL                     1
            976 BINARY_OP               13 (+=)
            980 STORE_FAST              17 (result)
            982 JUMP_BACKWARD           27 (to 930)

 94     >>  984 LOAD_GLOBAL             21 (NULL + str)
            996 LOAD_GLOBAL              5 (NULL + int)
           1008 LOAD_FAST                2 (unix)
           1010 LOAD_CONST              18 (1000)
           1012 BINARY_OP                5 (*)
           1016 PRECALL                  1
           1020 CALL                     1
           1030 PRECALL                  1
           1034 CALL                     1

 95        1044 LOAD_GLOBAL             21 (NULL + str)
           1056 LOAD_GLOBAL              5 (NULL + int)
           1068 LOAD_FAST                2 (unix)
           1070 PRECALL                  1
           1074 CALL                     1
           1084 PRECALL                  1
           1088 CALL                     1

 96        1098 LOAD_CONST              19 ('0404b0d30000')
           1100 LOAD_FAST               17 (result)
           1102 BINARY_OP                0 (+)

 93        1106 LOAD_CONST              20 (('x-ss-req-ticket', 'x-khronos', 'x-gorgon'))
           1108 BUILD_CONST_KEY_MAP      3
           1110 RETURN_VALUE

Disassembly of <code object rbit_algorithm at 0x7cb62c9470, file "", line 99>:
 99           0 RESUME                   0

100           2 LOAD_CONST               1 ('')
              4 STORE_FAST               2 (result)

101           6 LOAD_GLOBAL              1 (NULL + bin)
             18 LOAD_FAST                1 (num)
             20 PRECALL                  1
             24 CALL                     1
             34 LOAD_CONST               2 (2)
             36 LOAD_CONST               0 (None)
             38 BUILD_SLICE              2
             40 BINARY_SUBSCR
             50 STORE_FAST               3 (tmp_string)

102          52 LOAD_GLOBAL              3 (NULL + len)
             64 LOAD_FAST                3 (tmp_string)
             66 PRECALL                  1
             70 CALL                     1
             80 LOAD_CONST               3 (8)
             82 COMPARE_OP               0 (<)
             88 POP_JUMP_FORWARD_IF_FALSE    24 (to 138)

103     >>   90 LOAD_CONST               4 ('0')
             92 LOAD_FAST                3 (tmp_string)
             94 BINARY_OP                0 (+)
             98 STORE_FAST               3 (tmp_string)

102         100 LOAD_GLOBAL              3 (NULL + len)
            112 LOAD_FAST                3 (tmp_string)
            114 PRECALL                  1
            118 CALL                     1
            128 LOAD_CONST               3 (8)
            130 COMPARE_OP               0 (<)
            136 POP_JUMP_BACKWARD_IF_TRUE    24 (to 90)

104     >>  138 LOAD_GLOBAL              5 (NULL + range)
            150 LOAD_CONST               5 (0)
            152 LOAD_CONST               3 (8)
            154 PRECALL                  2
            158 CALL                     2
            168 GET_ITER
        >>  170 FOR_ITER                16 (to 204)
            172 STORE_FAST               4 (i)

105         174 LOAD_FAST                2 (result)
            176 LOAD_FAST                3 (tmp_string)
            178 LOAD_CONST               6 (7)
            180 LOAD_FAST                4 (i)
            182 BINARY_OP               10 (-)
            186 BINARY_SUBSCR
            196 BINARY_OP                0 (+)
            200 STORE_FAST               2 (result)
            202 JUMP_BACKWARD           17 (to 170)

106     >>  204 LOAD_GLOBAL              7 (NULL + int)
            216 LOAD_FAST                2 (result)
            218 LOAD_CONST               2 (2)
            220 PRECALL                  2
            224 CALL                     2
            234 RETURN_VALUE

Disassembly of <code object hex_string at 0x7cb6204c90, file "", line 108>:
108           0 RESUME                   0

109           2 LOAD_GLOBAL              1 (NULL + hex)
             14 LOAD_FAST                1 (num)
             16 PRECALL                  1
             20 CALL                     1
             30 LOAD_CONST               1 (2)
             32 LOAD_CONST               0 (None)
             34 BUILD_SLICE              2
             36 BINARY_SUBSCR
             46 STORE_FAST               2 (tmp_string)

110          48 LOAD_GLOBAL              3 (NULL + len)
             60 LOAD_FAST                2 (tmp_string)
             62 PRECALL                  1
             66 CALL                     1
             76 LOAD_CONST               1 (2)
             78 COMPARE_OP               0 (<)
             84 POP_JUMP_FORWARD_IF_FALSE     5 (to 96)

111          86 LOAD_CONST               2 ('0')
             88 LOAD_FAST                2 (tmp_string)
             90 BINARY_OP                0 (+)
             94 STORE_FAST               2 (tmp_string)

112     >>   96 LOAD_FAST                2 (tmp_string)
             98 RETURN_VALUE

Disassembly of <code object reverse at 0x7cb63510d0, file "", line 114>:
114           0 RESUME                   0

115           2 LOAD_FAST                0 (self)
              4 LOAD_METHOD              0 (hex_string)
             26 LOAD_FAST                1 (num)
             28 PRECALL                  1
             32 CALL                     1
             42 STORE_FAST               2 (tmp_string)

116          44 LOAD_GLOBAL              3 (NULL + int)
             56 LOAD_FAST                2 (tmp_string)
             58 LOAD_CONST               1 (1)
             60 LOAD_CONST               0 (None)
             62 BUILD_SLICE              2
             64 BINARY_SUBSCR
             74 LOAD_FAST                2 (tmp_string)
             76 LOAD_CONST               0 (None)
             78 LOAD_CONST               1 (1)
             80 BUILD_SLICE              2
             82 BINARY_SUBSCR
             92 BINARY_OP                0 (+)
             96 LOAD_CONST               2 (16)
             98 PRECALL                  2
            102 CALL                     2
            112 RETURN_VALUE

Disassembly of <code object clear at 0x7e4648a2f0, file "", line 138>:
138           0 RESUME                   0

139           2 LOAD_GLOBAL              1 (NULL + random)
             14 LOAD_ATTR                1 (choice)
             24 LOAD_GLOBAL              4 (J1)
             36 LOAD_GLOBAL              6 (J2)
             48 LOAD_GLOBAL              8 (J21)
             60 LOAD_GLOBAL             10 (J22)
             72 LOAD_GLOBAL             12 (F1)
             84 LOAD_GLOBAL             14 (C1)
             96 LOAD_GLOBAL             16 (P1)
            108 LOAD_GLOBAL             18 (P2)
            120 BUILD_LIST               8
            122 PRECALL                  1
            126 CALL                     1
            136 STORE_FAST               0 (sd)

140         138 LOAD_GLOBAL             21 (NULL + os)
            150 LOAD_ATTR               11 (system)
            160 LOAD_CONST               1 ('clear||cls')
            162 PRECALL                  1
            166 CALL                     1
            176 POP_TOP

141         178 LOAD_GLOBAL             25 (NULL + print)
            190 LOAD_GLOBAL             26 (P)
            202 FORMAT_VALUE             0
            204 LOAD_CONST               2 (' ▬▬▬▬▬▬▬▬▬▬▬▬▬▬▬▬▬▬▬▬▬▬')
            206 LOAD_GLOBAL             10 (J22)
            218 FORMAT_VALUE             0
            220 LOAD_CONST               3 ('علـــش')
            222 LOAD_GLOBAL             26 (P)
            234 FORMAT_VALUE             0
            236 LOAD_CONST               4 ('▬▬▬▬▬▬▬▬▬▬▬▬▬▬▬▬▬▬▬▬▬▬')
            238 BUILD_STRING             6
            240 PRECALL                  1
            244 CALL                     1
            254 POP_TOP

142         256 LOAD_GLOBAL             25 (NULL + print)
            268 LOAD_FAST                0 (sd)
            270 LOAD_CONST               5 ('⣿⣿⣿⣿⢿⠛⢛⠿⠉⠉⠉⡉⢙⣻⠻⠻⣿⣿⣿⣿⣿⣿\n⣿⣿⣿⠟⢁⡠⠀⠄⠀⠀⠀⠉⠙⠒⠃⠾⠹⣲⡘⠿⣿⣿⣿\n⣿⡿⠁⠀⠀⠀⠈⠛⠚⠉⠉⠛⠉⠙⠳⠖⣤⢌⡑⠂⠞⢿⣿\n⡟⠐⠂⠅⡠⠂⠁⠀⠀⢀⣴⣦⣶⣶⣶⣦⣌⠘⢮⡔⡈⠙⣿\n⠁⢀⠄⡈⠄⢀⠀⢠⣶⣿⣿⣿⣿⣿⣿⣿⣿⡆⠈⢣⠈⠜⣿\n⠄⠑⡨⠈⠀⢠⣴⠿⡿⣿⣿⣿⣿⣿⣿⡿⠟⠻⡄⠈⢸⡀⠚\n⡤⠪⠀⠀⢠⣿⣥⡴⠦⠤⠉⣙⣿⣿⠡⡔⠾⠟⣾⠀⠨⢀⠘\n⠃⠀⠀⠀⢸⣿⣤⡠⠧⢤⡻⢼⣿⣿⣼⣿⣤⣧⣿⠀⡄⢸⠀\n⠀⣀⠀⠀⠀⣿⣿⣿⣷⣿⣷⣿⣿⣿⣿⣿⣿⣿⣿⡄⢀⢸⠀\n⠠⡇⠀⠀⠀⢹⣿⡿⣿⣿⣏⡖⢿⣿⢓⣽⣿⣿⣿⠁⢨⢸⠀\n⠠⠇⠀⠀⠀⠀⠫⣿⣿⠟⠉⠀⠀⠄⠀⠉⠙⢿⡟⠀⠈⠸⠀\n⡐⡆⠀⠀⠀⠀⠀⠘⠁⠀⢀⡐⠒⠒⠢⠂⠀⠀⠂⠀⢀⠀⠀\n⣹⠆⠀⠀⠀⠀⠀⠀⠀⠀⠀⠀⠀⠀⠀⠀⠀⠀⠀⠀⠈⠀⢰\n⢺⠀⠀⠀⠈⢸⡀⠀⠀⠀⠀⠀⠀⠀⠀⠀⠀⠀⠀⠀⠀⠂⡘\n⡎⠀⠀⠀⠀⠄⣇⠠⢄⠀⠀⠀⠀⠀⠀⣀⡀⡄⠀⠀⠀⠀⡇\n⠄⠀⠀⠀⠀⡇⣷⡀⠩⡇⣠⣮⣶⣿⠿⣫⡾⠀⠀⠀⠀⠀⠁\n⠀⠀⠀⠀⠀⣷⠑⠳⠋⣾⡿⠟⣫⢵⡿⠟⠀⠀⠀⠀⠀⠀⠀\n⠀⠀⠀⠀⠐⠁⢀⣴⠀⣩⡖⡽⠝⢈⠀⠀⠀⠀⠀⠀⠀⠀⠀\n⠀⠀⠀⠀⢠⣴⡏⣫⣾⠟⠉⢀⡴⠁⠀⠀⠀⠀⠀⠀⠀⠀⠀\n⠀⠀⠀⠀⣿⢟⠕⠋⢀⣠⣲⡟⠁⠀⠀⠀⠀⠀⠀⠀⠀⠀⠀\n⠀⠀⠀⠠⣷⠋⣠⠞⣰⣿⡝⠀⠀⠀⠀⠀⠀⠀⠀⠀⠀⠀⠀\n⠀⠀⠀⣾⠁⣼⡟⣼⡏⡟⠀⠀⠀⠀⠀⠀⠀⠀⠀⠀⠀⠀⠀\n⠀⠀⠀⢁⣾⣯⢃⣿⡟⠀⠀⠀⠀⠀⠀⠀⠀⠀⠀⠀⠀⠀⠀\n⠀⠀⠀⣿⣿⢤⣾⡏⠀⠀⠀⠀⠀⠀⠀⠀⠀⠀⠀⠀⠀⠀⠀\n⠀⠀⢸⣿⣲⣿⡟⠀⠀⠀⠀⠀⠀⠀⠀⠀⠀⠀⠀⠀⠀⠀⠀\n⠀⠀⡿⣜⣿⡿⠁⠀⠀⠀⠀⠀⠀⠀⠀⠀⠀⠀⠀⠀⠀⠀⠀\n⠀⢠⡟⣼⣿⠁⠀⠀⠀@Gx1Gx1⠀⠀⠀⠀⠀⠀⠀⠀⠀⠀⠀⠀⠀⠀\n⠀⠸⣼⣿⠃⠀⠀⠀@Gx1Gx1⠀⠀⠀⠀⠀⠀⠀⠀⠀⠀⠀⠀⠀⠀⠀\n⠀⣽⣿⠏⠀⠀⠀⠀⠀⠀⠀⠀⠀⠀⠀⠀⠀⠀⠀⠀⠀⠀⠀\n\n⠀⠀⠀⠀⠀⠀⠀⠀⠀⢸⡇⠀⠀⠀⠀⠀⢰⡆⠀⠀⠀⠀⠀⠀\n⠀⠀⠀⠀⠀⠀⠀⠀⠀⣽⡇⠀⠀⠀⠀⠀⣼⡇⠀⠀⠀⠀⠀⠀\n⠀⠀⠀⠀⠀⠀⠀⠀⠀⢿⡇⠀⠀⠀⠀⠀⣿⠇⠀⢀⠀⠀⠀⠀\n⠀⠀⠀⠀⠀⢀⣴⣶⡆⢹⡇⢠⣴⣶⣶⠀⣿⡇⠀⣸⣷⠀⠀⠀\n⠀⠀⢸⡇⠀⢸⡯⣿⣷⣾⣷⣾⣿⣶⣶⠀⣿⣶⣶⣿⣿⠀⠀⠀\n⠀⠀⠙⢿⣶⠿⠃⠀⠀⠀⠀⠀⠀⠀⠀⠀⠀⠀⣶⠀⡶⠀⠀⠀\n⠀⠀⠀⠾⠐⠷  ')
            272 BINARY_OP                0 (+)
            276 PRECALL                  1
            280 CALL                     1
            290 POP_TOP

179         292 LOAD_GLOBAL             25 (NULL + print)
            304 LOAD_GLOBAL             26 (P)
            316 FORMAT_VALUE             0
            318 LOAD_CONST               2 (' ▬▬▬▬▬▬▬▬▬▬▬▬▬▬▬▬▬▬▬▬▬▬')
            320 LOAD_GLOBAL             10 (J22)
            332 FORMAT_VALUE             0
            334 LOAD_CONST               6 ('GX1GX1')
            336 LOAD_GLOBAL             26 (P)
            348 FORMAT_VALUE             0
            350 LOAD_CONST               4 ('▬▬▬▬▬▬▬▬▬▬▬▬▬▬▬▬▬▬▬▬▬▬')
            352 BUILD_STRING             6
            354 PRECALL                  1
            358 CALL                     1
            368 POP_TOP
            370 LOAD_CONST               0 (None)
            372 RETURN_VALUE

Disassembly of <code object <genexpr> at 0x7cb61e1430, file "", line 195>:
195           0 RETURN_GENERATOR
              2 POP_TOP
              4 RESUME                   0
              6 LOAD_FAST                0 (.0)
        >>    8 FOR_ITER                24 (to 58)
             10 STORE_FAST               1 (_)
             12 LOAD_GLOBAL              1 (NULL + random)
             24 LOAD_ATTR                1 (choice)
             34 LOAD_CONST               0 ('01234qwertyuiopasdfghjkzxcvbnm56789')
             36 PRECALL                  1
             40 CALL                     1
             50 YIELD_VALUE
             52 RESUME                   1
             54 POP_TOP
             56 JUMP_BACKWARD           25 (to 8)
        >>   58 LOAD_CONST               1 (None)
             60 RETURN_VALUE

Disassembly of <code object <listcomp> at 0x7cb6204ff0, file "", line 255>:
255           0 RESUME                   0
              2 BUILD_LIST               0
              4 LOAD_FAST                0 (.0)
        >>    6 FOR_ITER                41 (to 90)
              8 STORE_FAST               1 (c)
             10 LOAD_GLOBAL              1 (NULL + hex)
             22 LOAD_GLOBAL              3 (NULL + ord)
             34 LOAD_FAST                1 (c)
             36 PRECALL                  1
             40 CALL                     1
             50 LOAD_CONST               0 (5)
             52 BINARY_OP               12 (^)
             56 PRECALL                  1
             60 CALL                     1
             70 LOAD_CONST               1 (2)
             72 LOAD_CONST               2 (None)
             74 BUILD_SLICE              2
             76 BINARY_SUBSCR
             86 LIST_APPEND              2
             88 JUMP_BACKWARD           42 (to 6)
        >>   90 RETURN_VALUE

Disassembly of <code object af at 0x7f464a5570, file "", line 308>:
308           0 RESUME                   0

310           2 NOP

311     >>    4 LOAD_GLOBAL              1 (NULL + str)
             16 LOAD_GLOBAL              3 (NULL + random)
             28 LOAD_ATTR                2 (choice)
             38 LOAD_GLOBAL              6 (ls)
             50 PRECALL                  1
             54 CALL                     1
             64 PRECALL                  1
             68 CALL                     1
             78 STORE_FAST               0 (proxies1)

312          80 NOP

313          82 LOAD_CONST               2 ('user-agent')
             84 LOAD_CONST               3 ('com.zhiliaoapp.musically/2023100040 (Linux; U; Android 9; en; G011A; Build/PI;tt-ok/3.12.13.1)')
             86 BUILD_MAP                1
             88 STORE_FAST               1 (headers)

314          90 LOAD_GLOBAL              9 (NULL + requests)
            102 LOAD_ATTR                5 (get)
            112 LOAD_CONST               4 ('https://api16-normal-c-useast1a.tiktokv.com/aweme/v2/aweme/feedback/?')
            114 LOAD_FAST                1 (headers)
            116 LOAD_CONST               5 ('socks5://')
            118 LOAD_FAST                0 (proxies1)
            120 FORMAT_VALUE             0
            122 BUILD_STRING             2
            124 LOAD_CONST               6 ('socks4://')
            126 LOAD_FAST                0 (proxies1)
            128 FORMAT_VALUE             0
            130 BUILD_STRING             2
            132 LOAD_CONST               7 ('http://')
            134 LOAD_FAST                0 (proxies1)
            136 FORMAT_VALUE             0
            138 BUILD_STRING             2
            140 LOAD_CONST               8 (('https', 'https', 'https'))
            142 BUILD_CONST_KEY_MAP      3
            144 KW_NAMES                 9
            146 PRECALL                  3
            150 CALL                     3
            160 LOAD_ATTR                6 (text)
            170 POP_TOP

315         172 LOAD_GLOBAL             15 (NULL + open)
            184 LOAD_CONST              10 ('SAIPR_REPORT_AFRIT_SAIPR.txt')
            186 LOAD_CONST              11 ('a')
            188 PRECALL                  2
            192 CALL                     2
            202 BEFORE_WITH
            204 STORE_FAST               2 (Prox1y)

316         206 LOAD_FAST                2 (Prox1y)
            208 LOAD_METHOD              8 (write)
            230 LOAD_FAST                0 (proxies1)
            232 LOAD_CONST              12 ('\n')
            234 BINARY_OP                0 (+)
            238 PRECALL                  1
            242 CALL                     1
            252 POP_TOP

315         254 LOAD_CONST               0 (None)
            256 LOAD_CONST               0 (None)
            258 LOAD_CONST               0 (None)
            260 PRECALL                  2
            264 CALL                     2
            274 POP_TOP
            276 JUMP_FORWARD            11 (to 300)
        >>  278 PUSH_EXC_INFO
            280 WITH_EXCEPT_START
            282 POP_JUMP_FORWARD_IF_TRUE     4 (to 292)
            284 RERAISE                  2
        >>  286 COPY                     3
            288 POP_EXCEPT
            290 RERAISE                  1
        >>  292 POP_TOP
            294 POP_EXCEPT
            296 POP_TOP
            298 POP_TOP

317     >>  300 LOAD_GLOBAL             18 (e)
            312 LOAD_CONST               1 (1)
            314 BINARY_OP               13 (+=)
            318 STORE_GLOBAL             9 (e)

318         320 LOAD_GLOBAL             21 (NULL + print)
            332 LOAD_CONST              13 ('\r')
            334 LOAD_GLOBAL             22 (X)
            346 FORMAT_VALUE             0
            348 LOAD_CONST              14 ('[')
            350 LOAD_GLOBAL             24 (F)
            362 FORMAT_VALUE             0
            364 LOAD_GLOBAL             18 (e)
            376 FORMAT_VALUE             0
            378 LOAD_GLOBAL             22 (X)
            390 FORMAT_VALUE             0
            392 LOAD_CONST              15 (']')
            394 LOAD_GLOBAL             26 (A)
            406 FORMAT_VALUE             0
            408 LOAD_CONST              16 (' -')
            410 LOAD_GLOBAL             28 (C1)
            422 FORMAT_VALUE             0
            424 LOAD_CONST              17 (' ')
            426 LOAD_FAST                0 (proxies1)
            428 FORMAT_VALUE             0
            430 LOAD_GLOBAL             26 (A)
            442 FORMAT_VALUE             0
            444 LOAD_CONST              18 (' - ')
            446 LOAD_GLOBAL             22 (X)
            458 FORMAT_VALUE             0
            460 LOAD_CONST              14 ('[')
            462 LOAD_GLOBAL             30 (Z)
            474 FORMAT_VALUE             0
            476 LOAD_GLOBAL             32 (er)
            488 FORMAT_VALUE             0
            490 LOAD_GLOBAL             22 (X)
            502 FORMAT_VALUE             0
            504 LOAD_CONST              19 (']       ')
            506 BUILD_STRING            20
            508 LOAD_CONST              20 ('')
            510 KW_NAMES                21
            512 PRECALL                  2
            516 CALL                     2
            526 POP_TOP
            528 JUMP_FORWARD           121 (to 772)
        >>  530 PUSH_EXC_INFO

319         532 POP_TOP
            534 LOAD_GLOBAL             32 (er)
            546 LOAD_CONST               1 (1)
            548 BINARY_OP               13 (+=)
            552 STORE_GLOBAL            16 (er)
            554 LOAD_GLOBAL             21 (NULL + print)
            566 LOAD_CONST              13 ('\r')
            568 LOAD_GLOBAL             22 (X)
            580 FORMAT_VALUE             0
            582 LOAD_CONST              14 ('[')
            584 LOAD_GLOBAL             24 (F)
            596 FORMAT_VALUE             0
            598 LOAD_GLOBAL             18 (e)
            610 FORMAT_VALUE             0
            612 LOAD_GLOBAL             22 (X)
            624 FORMAT_VALUE             0
            626 LOAD_CONST              15 (']')
            628 LOAD_GLOBAL             26 (A)
            640 FORMAT_VALUE             0
            642 LOAD_CONST              16 (' -')
            644 LOAD_GLOBAL             28 (C1)
            656 FORMAT_VALUE             0
            658 LOAD_CONST              17 (' ')
            660 LOAD_FAST                0 (proxies1)
            662 FORMAT_VALUE             0
            664 LOAD_GLOBAL             26 (A)
            676 FORMAT_VALUE             0
            678 LOAD_CONST              18 (' - ')
            680 LOAD_GLOBAL             22 (X)
            692 FORMAT_VALUE             0
            694 LOAD_CONST              14 ('[')
            696 LOAD_GLOBAL             30 (Z)
            708 FORMAT_VALUE             0
            710 LOAD_GLOBAL             32 (er)
            722 FORMAT_VALUE             0
            724 LOAD_GLOBAL             22 (X)
            736 FORMAT_VALUE             0
            738 LOAD_CONST              19 (']       ')
            740 BUILD_STRING            20
            742 LOAD_CONST              20 ('')
            744 KW_NAMES                21
            746 PRECALL                  2
            750 CALL                     2
            760 POP_TOP
            762 POP_EXCEPT
            764 JUMP_FORWARD             3 (to 772)
        >>  766 COPY                     3
            768 POP_EXCEPT
            770 RERAISE                  1

310     >>  772 EXTENDED_ARG             1
            774 JUMP_BACKWARD          386 (to 4)
ExceptionTable:
  82 to 202 -> 530 [0]
  204 to 252 -> 278 [1] lasti
  254 to 276 -> 530 [0]
  278 to 284 -> 286 [3] lasti
  286 to 290 -> 530 [0]
  292 to 292 -> 286 [3] lasti
  294 to 526 -> 530 [0]
  530 to 760 -> 766 [1] lasti

Disassembly of <code object afr at 0x7d9649bb20, file "", line 602>:
602           0 RESUME                   0

604           2 LOAD_GLOBAL              1 (NULL + str)
             14 LOAD_GLOBAL              3 (NULL + random)
             26 LOAD_ATTR                2 (choice)
             36 LOAD_GLOBAL              6 (ls)
             48 PRECALL                  1
             52 CALL                     1
             62 PRECALL                  1
             66 CALL                     1
             76 STORE_FAST               2 (proxies1)

605          78 LOAD_GLOBAL              9 (NULL + int)
             90 LOAD_GLOBAL             11 (NULL + time)
            102 LOAD_ATTR                5 (time)
            112 PRECALL                  0
            116 CALL                     0
            126 LOAD_CONST               1 (1000)
            128 BINARY_OP                5 (*)
            132 PRECALL                  1
            136 CALL                     1
            146 STORE_FAST               3 (_rticket)

606         148 LOAD_GLOBAL              1 (NULL + str)
            160 LOAD_GLOBAL              9 (NULL + int)
            172 LOAD_GLOBAL             11 (NULL + time)
            184 LOAD_ATTR                5 (time)
            194 PRECALL                  0
            198 CALL                     0
            208 LOAD_CONST               1 (1000)
            210 BINARY_OP                5 (*)
            214 PRECALL                  1
            218 CALL                     1
            228 PRECALL                  1
            232 CALL                     1
            242 LOAD_CONST               0 (None)
            244 LOAD_CONST               2 (10)
            246 BUILD_SLICE              2
            248 BINARY_SUBSCR
            258 STORE_FAST               4 (ts)

607         260 LOAD_CONST               3 (0)
            262 LOAD_CONST               4 (('uuid4',))
            264 IMPORT_NAME              6 (uuid)
            266 IMPORT_FROM              7 (uuid4)
            268 STORE_FAST               5 (uuid4)
            270 POP_TOP

608         272 LOAD_GLOBAL              1 (NULL + str)
            284 PUSH_NULL
            286 LOAD_FAST                5 (uuid4)
            288 PRECALL                  0
            292 CALL                     0
            302 PRECALL                  1
            306 CALL                     1
            316 STORE_FAST               6 (uid)

609         318 LOAD_GLOBAL              3 (NULL + random)
            330 LOAD_ATTR                8 (randrange)
            340 LOAD_CONST               5 (7334285683765348101)
            342 LOAD_CONST               6 (7334285999999999999)
            344 PRECALL                  2
            348 CALL                     2
            358 STORE_FAST               7 (install_id)

610         360 LOAD_GLOBAL              3 (NULL + random)
            372 LOAD_ATTR                8 (randrange)
            382 LOAD_CONST               7 (7283928371561793029)
            384 LOAD_CONST               8 (7283929999999999999)
            386 PRECALL                  2
            390 CALL                     2
            400 STORE_FAST               8 (device_id)

611         402 LOAD_GLOBAL              1 (NULL + str)
            414 LOAD_GLOBAL             19 (NULL + binascii)
            426 LOAD_ATTR               10 (hexlify)
            436 LOAD_GLOBAL             23 (NULL + os)
            448 LOAD_ATTR               12 (urandom)
            458 LOAD_CONST               9 (8)
            460 PRECALL                  1
            464 CALL                     1
            474 PRECALL                  1
            478 CALL                     1
            488 LOAD_METHOD             13 (decode)
            510 PRECALL                  0
            514 CALL                     0
            524 PRECALL                  1
            528 CALL                     1
            538 STORE_FAST               9 (openudid)

612         540 LOAD_GLOBAL              3 (NULL + random)
            552 LOAD_ATTR                2 (choice)
            562 BUILD_LIST               0
            564 LOAD_CONST              10 (('America/New_York', 'Europe/London', 'Asia/Tokyo', 'Australia/Sydney', 'Asia/Kolkata', 'America/Los_Angeles', 'Europe/Paris', 'Asia/Dubai', 'America/Sao_Paulo', 'Asia/Shanghai'))
            566 LIST_EXTEND              1
            568 PRECALL                  1
            572 CALL                     1
            582 STORE_FAST              10 (tz_name)

613         584 LOAD_GLOBAL              3 (NULL + random)
            596 LOAD_ATTR                2 (choice)
            606 BUILD_LIST               0
            608 LOAD_CONST              11 (('en', 'es', 'fr', 'de', 'ja', 'pt', 'it', 'ru', 'ar', 'hi'))
            610 LIST_EXTEND              1
            612 PRECALL                  1
            616 CALL                     1
            626 STORE_FAST              11 (webcast_language)

614         628 LOAD_GLOBAL              3 (NULL + random)
            640 LOAD_ATTR                2 (choice)
            650 BUILD_LIST               0
            652 LOAD_CONST              12 (('US', 'UK', 'CA', 'AU', 'IN', 'BR', 'FR', 'DE', 'IT', 'ES', 'AB'))
            654 LIST_EXTEND              1
            656 PRECALL                  1
            660 CALL                     1
            670 STORE_FAST              12 (current_region)

615         672 LOAD_GLOBAL              3 (NULL + random)
            684 LOAD_ATTR                2 (choice)
            694 BUILD_LIST               0
            696 LOAD_CONST              13 (('US', 'UK', 'CA', 'AU', 'IN', 'BR', 'FR', 'DE', 'IT', 'ES'))
            698 LIST_EXTEND              1
            700 PRECALL                  1
            704 CALL                     1
            714 STORE_FAST              13 (region)

616         716 LOAD_GLOBAL              3 (NULL + random)
            728 LOAD_ATTR               14 (randint)
            738 LOAD_CONST              14 (600)
            740 LOAD_CONST              15 (1080)
            742 PRECALL                  2
            746 CALL                     2
            756 STORE_FAST              14 (screen_height)

617         758 LOAD_GLOBAL              3 (NULL + random)
            770 LOAD_ATTR               14 (randint)
            780 LOAD_CONST              16 (800)
            782 LOAD_CONST              17 (1920)
            784 PRECALL                  2
            788 CALL                     2
            798 STORE_FAST              15 (screen_width)

618         800 BUILD_LIST               0
            802 LOAD_CONST              18 (('SM-G975F', 'SM-G532G', 'SM-N975F', 'SM-G988U', 'SM-G977U', 'SM-A705FN', 'SM-A515U1', 'SM-G955F', 'SM-A750G', 'SM-N960F', 'SM-G960U', 'SM-J600F', 'SM-A908B', 'SM-A705GM', 'SM-G970U', 'SM-A307FN', 'SM-G965U1', 'SM-A217F', 'SM-G986B', 'SM-A207M', 'SM-A515W', 'SM-A505G', 'SM-A315G', 'SM-A507FN', 'SM-A505U1', 'SM-G977T', 'SM-A025G', 'SM-J320F', 'SM-A715W', 'SM-A908N', 'SM-A205F', 'SM-G988B', 'SM-N986B', 'SM-A715F', 'SM-A515F', 'SM-G965F', 'SM-G960F', 'SM-A505F', 'SM-A207F', 'SM-A307G', 'SM-G970F', 'SM-A107F', 'SM-G935F', 'SM-G935A', 'SM-A310F', 'SM-J320FN'))
            804 LIST_EXTEND              1
            806 STORE_FAST              16 (samsung)

619         808 BUILD_LIST               0
            810 LOAD_CONST              19 (('CPH2359', 'CPH2457', 'CPH2349', 'CPH2145', 'CPH2293', 'CPH2343', 'CPH2127', 'CPH2197', 'CPH2173', 'CPH2371', 'CPH2269', 'CPH2005', 'CPH2185'))
            812 LIST_EXTEND              1
            814 STORE_FAST              17 (oppo)

620         816 BUILD_LIST               0
            818 LOAD_CONST              20 (('RMX3501', 'RMX3085', 'RMX1921', 'RMX3771', 'RMX3461', 'RMX3092', 'RMX3393', 'RMX3392', 'RMX1821', 'RMX1825', 'RMX3310'))
            820 LIST_EXTEND              1
            822 STORE_FAST              18 (realme)

621         824 LOAD_GLOBAL              3 (NULL + random)
            836 LOAD_ATTR                2 (choice)
            846 LOAD_FAST               16 (samsung)
            848 LOAD_FAST               17 (oppo)
            850 LOAD_FAST               18 (realme)
            852 BUILD_LIST               3
            854 PRECALL                  1
            858 CALL                     1
            868 STORE_FAST              19 (phone)

622         870 LOAD_GLOBAL              3 (NULL + random)
            882 LOAD_ATTR                2 (choice)
            892 LOAD_FAST               19 (phone)
            894 PRECALL                  1
            898 CALL                     1
            908 STORE_FAST              20 (type1)

623         910 LOAD_CONST              21 ('SM')
            912 LOAD_FAST               20 (type1)
            914 CONTAINS_OP              0
            916 POP_JUMP_FORWARD_IF_FALSE    29 (to 976)

624         918 LOAD_CONST              22 ('samsung')
            920 STORE_FAST              21 (brand)

625         922 LOAD_FAST               20 (type1)
            924 LOAD_METHOD             15 (split)
            946 LOAD_CONST              23 ('-')
            948 PRECALL                  1
            952 CALL                     1
            962 LOAD_CONST              24 (1)
            964 BINARY_SUBSCR
            974 STORE_FAST              22 (dev)

626     >>  976 LOAD_CONST              25 ('RMX')
            978 LOAD_FAST               20 (type1)
            980 CONTAINS_OP              0
            982 POP_JUMP_FORWARD_IF_FALSE    29 (to 1042)

627         984 LOAD_CONST              26 ('realme')
            986 STORE_FAST              21 (brand)

628         988 LOAD_FAST               20 (type1)
            990 LOAD_METHOD             15 (split)
           1012 LOAD_CONST              27 ('X')
           1014 PRECALL                  1
           1018 CALL                     1
           1028 LOAD_CONST              24 (1)
           1030 BINARY_SUBSCR
           1040 STORE_FAST              22 (dev)

629     >> 1042 LOAD_CONST              28 ('CPH')
           1044 LOAD_FAST               20 (type1)
           1046 CONTAINS_OP              0
           1048 POP_JUMP_FORWARD_IF_FALSE    29 (to 1108)

630        1050 LOAD_CONST              29 ('OPPO')
           1052 STORE_FAST              21 (brand)

631        1054 LOAD_FAST               20 (type1)
           1056 LOAD_METHOD             15 (split)
           1078 LOAD_CONST              30 ('H')
           1080 PRECALL                  1
           1084 CALL                     1
           1094 LOAD_CONST              24 (1)
           1096 BINARY_SUBSCR
           1106 STORE_FAST              22 (dev)

633     >> 1108 LOAD_GLOBAL              9 (NULL + int)
           1120 LOAD_GLOBAL             33 (NULL + round)
           1132 LOAD_GLOBAL             34 (datetime)
           1144 LOAD_ATTR               17 (datetime)
           1154 LOAD_METHOD             18 (now)
           1176 PRECALL                  0
           1180 CALL                     0
           1190 LOAD_GLOBAL             34 (datetime)
           1202 LOAD_ATTR               17 (datetime)
           1212 LOAD_METHOD             19 (utcnow)
           1234 PRECALL                  0
           1238 CALL                     0
           1248 BINARY_OP               10 (-)
           1252 LOAD_METHOD             20 (total_seconds)
           1274 PRECALL                  0
           1278 CALL                     0
           1288 PRECALL                  1
           1292 CALL                     1
           1302 PRECALL                  1
           1306 CALL                     1
           1316 STORE_FAST              23 (off)

634        1318 LOAD_GLOBAL             42 (aobsh)
           1330 LOAD_CONST              31 ('1')
           1332 COMPARE_OP               2 (==)
           1338 EXTENDED_ARG             1
           1340 POP_JUMP_FORWARD_IF_FALSE   302 (to 1946)

635        1342 LOAD_GLOBAL              9 (NULL + int)
           1354 LOAD_GLOBAL             34 (datetime)
           1366 LOAD_ATTR               17 (datetime)
           1376 LOAD_METHOD             18 (now)
           1398 PRECALL                  0
           1402 CALL                     0
           1412 LOAD_METHOD             22 (timestamp)
           1434 PRECALL                  0
           1438 CALL                     0
           1448 PRECALL                  1
           1452 CALL                     1
           1462 STORE_FAST              24 (time1)

636        1464 LOAD_CONST              32 ('902112')
           1466 BUILD_LIST               1
           1468 STORE_FAST              25 (sdsd)

637        1470 LOAD_GLOBAL              1 (NULL + str)
           1482 LOAD_GLOBAL              3 (NULL + random)
           1494 LOAD_ATTR                2 (choice)
           1504 LOAD_FAST               25 (sdsd)
           1506 PRECALL                  1
           1510 CALL                     1
           1520 PRECALL                  1
           1524 CALL                     1
           1534 STORE_FAST              26 (reason)

638        1536 LOAD_GLOBAL             47 (NULL + urlencode)
           1548 BUILD_MAP                0
           1550 LOAD_CONST              33 ('WebIdLastTime')
           1552 LOAD_FAST               24 (time1)
           1554 MAP_ADD                  1

640        1556 LOAD_CONST              34 ('aid')
           1558 LOAD_CONST              35 ('1988')

638        1560 MAP_ADD                  1

642        1562 LOAD_CONST              36 ('app_language')
           1564 LOAD_FAST               11 (webcast_language)

638        1566 MAP_ADD                  1

644        1568 LOAD_CONST              37 ('app_name')
           1570 LOAD_CONST              38 ('tiktok_web')

638        1572 MAP_ADD                  1

646        1574 LOAD_CONST              39 ('aweme_type')
           1576 LOAD_CONST              40 ('0')

638        1578 MAP_ADD                  1

648        1580 LOAD_CONST              41 ('browser_language')           1582 LOAD_FAST               11 (webcast_language)

638        1584 MAP_ADD                  1

650        1586 LOAD_CONST              42 ('browser_name')
           1588 LOAD_CONST              43 ('Mozilla')

638        1590 MAP_ADD                  1

652        1592 LOAD_CONST              44 ('browser_online')
           1594 LOAD_CONST              45 ('true')

638        1596 MAP_ADD                  1

654        1598 LOAD_CONST              46 ('browser_platform')           1600 LOAD_CONST              47 ('Win32')

638        1602 MAP_ADD                  1

656        1604 LOAD_CONST              48 ('browser_version')
           1606 LOAD_CONST              49 ('5.0 (Windows NT 10.0; Win64; x64) AppleWebKit/537.36 (KHTML, like Gecko) Chrome/120.0.0.0 Safari/537.36')

638        1608 MAP_ADD                  1

658        1610 LOAD_CONST              50 ('channel')
           1612 LOAD_CONST              38 ('tiktok_web')

638        1614 MAP_ADD                  1

660        1616 LOAD_CONST              51 ('cookie_enabled')
           1618 LOAD_CONST              45 ('true')

638        1620 MAP_ADD                  1

661        1622 LOAD_CONST              52 ('device_id')
           1624 LOAD_FAST                8 (device_id)

638        1626 MAP_ADD                  1

663        1628 LOAD_CONST              53 ('device_platform')
           1630 LOAD_CONST              54 ('web_pc')

638        1632 MAP_ADD                  1

665        1634 LOAD_CONST              55 ('focus_state')
           1636 LOAD_CONST              45 ('true')

638        1638 MAP_ADD                  1

667        1640 LOAD_CONST              56 ('from_page')
           1642 LOAD_CONST              57 ('video')

638        1644 MAP_ADD                  1

669        1646 LOAD_CONST              58 ('history_len')
           1648 LOAD_CONST              59 ('8')

638        1650 MAP_ADD                  1
           1652 BUILD_MAP                0

671        1654 LOAD_CONST              60 ('is_fullscreen')
           1656 LOAD_CONST              61 ('false')

638        1658 MAP_ADD                  1

673        1660 LOAD_CONST              62 ('is_page_visible')
           1662 LOAD_CONST              45 ('true')

638        1664 MAP_ADD                  1

675        1666 LOAD_CONST              63 ('is_sub_only_video')
           1668 LOAD_CONST              40 ('0')

638        1670 MAP_ADD                  1

677        1672 LOAD_CONST              64 ('lang')
           1674 LOAD_FAST               11 (webcast_language)

638        1676 MAP_ADD                  1

679        1678 LOAD_CONST              65 ('nickname')
           1680 LOAD_GLOBAL             48 (nickname)

638        1692 MAP_ADD                  1

681        1694 LOAD_CONST              66 ('object_id')
           1696 LOAD_FAST                0 (aweme_id)

638        1698 MAP_ADD                  1

683        1700 LOAD_CONST              67 ('object_owner_id')
           1702 LOAD_GLOBAL             50 (id)

638        1714 MAP_ADD                  1

685        1716 LOAD_CONST              68 ('os')
           1718 LOAD_CONST              69 ('windows')

638        1720 MAP_ADD                  1

687        1722 LOAD_CONST              70 ('owner_id')
           1724 LOAD_GLOBAL             50 (id)

638        1736 MAP_ADD                  1

689        1738 LOAD_CONST              71 ('play_mode')
           1740 LOAD_CONST              72 ('browser_mode')

638        1742 MAP_ADD                  1

691        1744 LOAD_CONST              73 ('reason')
           1746 LOAD_FAST               26 (reason)

638        1748 MAP_ADD                  1

693        1750 LOAD_CONST              74 ('referer')
           1752 LOAD_CONST              74 ('referer')

638        1754 MAP_ADD                  1

694        1756 LOAD_CONST              75 ('report_type')
           1758 LOAD_CONST              57 ('video')

638        1760 MAP_ADD                  1

696        1762 LOAD_CONST              76 ('reporter_id')
           1764 LOAD_CONST              77 ('6856361445673272326')

638        1766 MAP_ADD                  1

698        1768 LOAD_CONST              78 ('screen_height')
           1770 LOAD_FAST               14 (screen_height)

638        1772 MAP_ADD                  1

700        1774 LOAD_CONST              79 ('screen_width')
           1776 LOAD_FAST               15 (screen_width)

638        1778 MAP_ADD                  1

702        1780 LOAD_CONST              80 ('target')
           1782 LOAD_FAST                0 (aweme_id)

638        1784 MAP_ADD                  1
           1786 DICT_UPDATE              1

704        1788 LOAD_CONST              24 (1)

705        1790 LOAD_CONST              81 (2)

706        1792 LOAD_CONST              82 (3)

707        1794 LOAD_CONST              83 ('https://www.google.com/')

709        1796 LOAD_CONST              84 ('be')

710        1798 LOAD_CONST              85 ('Farouk Wanle')

711        1800 LOAD_CONST              86 ('_flagger_email')

713        1802 LOAD_FAST                0 (aweme_id)

715        1804 LOAD_CONST              87 ('[object Object]')

717        1806 LOAD_FAST               11 (webcast_language)

719        1808 LOAD_CONST              88 ('IV--mbNJVFdJzW3ezHWueGOYzCbGzWsDOhS5NTUcIhaUlI-PaYeT0XEu1G8dbDVs2Sht-5LXELzOfW6634YUJ6iPNP1JnmQPdnuaGBZ-s6BR2wxIzC9QAvsHIQ6PFliZzFjJ9zsarQBdjw==')

721        1810 LOAD_CONST              89 ('w7Dwu7yXuV_QZ2Gln8An6PeXwM6aWAL3ss-a3epdRBhi8Gwz80qUryo9Cdnb4rn14K-p5DzfceXIs4TEkbZMCZufVi9hIizRt6OrSKX3b2hbRHOPRPwtiCfcIpN8dmrToz-kroaOXc9nog==')

722        1812 LOAD_CONST              90 ('DFSzswVLP3RR9kGEtWd7JbJ92U6S')

724        1814 LOAD_CONST              91 ('DFSzswVLk6UANJGEtWp3xbJ92UIX')

726        1816 LOAD_CONST              92 ('_02B4Z6wo00001qvYUFwAAIDArHJl-y89yw6r2FTAAMyOac')

638        1818 LOAD_CONST              93 (('relevant_law', 'report_desc', 'report_signature', 'root_referer', ' legal_jurisdiction', ' nickname', 'trusted', 'video_id', 'video_owner', 'webcast_language', 'msToken', 'msToken', 'X-Bogus', 'X-Bogus', '_signature'))
           1820 BUILD_CONST_KEY_MAP     15
           1822 DICT_UPDATE              1
           1824 PRECALL                  1
           1828 CALL                     1
           1838 STORE_FAST              27 (pro1)

728        1840 LOAD_CONST              94 ('https://www.tiktok.com/aweme/v2/aweme/feedback/?%s')
           1842 LOAD_FAST               27 (pro1)
           1844 BINARY_OP                6 (%)
           1848 STORE_FAST              28 (url)

732        1850 LOAD_CONST              95 ('ttwid=')
           1852 LOAD_GLOBAL             52 (ttwid)
           1864 FORMAT_VALUE             0
           1866 LOAD_CONST              96 ('; sid_tt=')
           1868 BUILD_STRING             3
           1870 LOAD_FAST                1 (sessionid)
           1872 BINARY_OP                0 (+)
           1876 LOAD_CONST              97 ('; sessionid=')
           1878 BINARY_OP                0 (+)
           1882 LOAD_FAST                1 (sessionid)
           1884 BINARY_OP                0 (+)
           1888 LOAD_CONST              98 ('; sessionid_ss=')
           1890 BINARY_OP                0 (+)
           1894 LOAD_FAST                1 (sessionid)
           1896 BINARY_OP                0 (+)
           1900 LOAD_CONST              99 (';')
           1902 BINARY_OP                0 (+)

734        1906 LOAD_CONST             100 ('https://www.tiktok.com/@')
           1908 LOAD_GLOBAL             54 (g)
           1920 BINARY_OP                0 (+)
           1924 LOAD_CONST             101 ('/video/')
           1926 BINARY_OP                0 (+)
           1930 LOAD_FAST                0 (aweme_id)
           1932 BINARY_OP                0 (+)

736        1936 LOAD_CONST             102 ('same-origin')

738        1938 LOAD_CONST             103 ('Mozilla/5.0 (Windows NT 10.0; Win64; x64) AppleWebKit/537.36 (KHTML, like Gecko) Chrome/120.0.0.0 Safari/537.36')

730        1940 LOAD_CONST             104 (('Cookie', 'Referer', 'Sec-Fetch-Site', 'User-Agent'))
           1942 BUILD_CONST_KEY_MAP      4
           1944 STORE_FAST              29 (h)

741     >> 1946 LOAD_GLOBAL             42 (aobsh)
           1958 LOAD_CONST             105 ('2')
           1960 COMPARE_OP               2 (==)
           1966 EXTENDED_ARG             2
           1968 POP_JUMP_FORWARD_IF_FALSE   601 (to 3172)

742        1970 LOAD_GLOBAL             56 (xxx)
           1982 LOAD_CONST             106 ('14')
           1984 COMPARE_OP               2 (==)
           1990 EXTENDED_ARG             1
           1992 POP_JUMP_FORWARD_IF_FALSE   263 (to 2520)

743        1994 LOAD_GLOBAL             47 (NULL + urlencode)
           2006 BUILD_MAP                0

744        2008 LOAD_CONST             107 ('logout_reporter_email')
           2010 LOAD_CONST             108 ('')

743        2012 MAP_ADD                  1

745        2014 LOAD_CONST              73 ('reason')
           2016 LOAD_CONST             109 ('9013')

743        2018 MAP_ADD                  1

746        2020 LOAD_CONST             110 ('enter_from')
           2022 LOAD_CONST             111 ('homepage_hot')

743        2024 MAP_ADD                  1

747        2026 LOAD_CONST              70 ('owner_id')
           2028 LOAD_GLOBAL             50 (id)

743        2040 MAP_ADD                  1

748        2042 LOAD_CONST              75 ('report_type')
           2044 LOAD_CONST              57 ('video')

743        2046 MAP_ADD                  1

749        2048 LOAD_CONST              66 ('object_id')
           2050 LOAD_FAST                0 (aweme_id)

743        2052 MAP_ADD                  1

750        2054 LOAD_CONST             112 ('no_hw')
           2056 LOAD_CONST              31 ('1')

743        2058 MAP_ADD                  1

751        2060 LOAD_CONST             113 ('submit_type')
           2062 LOAD_CONST              31 ('1')

743        2064 MAP_ADD                  1

752        2066 LOAD_CONST             114 ('isFirst')
           2068 LOAD_CONST              31 ('1')

743        2070 MAP_ADD                  1

753        2072 LOAD_CONST             115 ('trusted_flagger_email')
           2074 LOAD_CONST             108 ('')

743        2076 MAP_ADD                  1

754        2078 LOAD_CONST             116 ('report_signature')           2080 LOAD_GLOBAL             59 (NULL + names)
           2092 LOAD_ATTR               30 (get_last_name)
           2102 PRECALL                  0
           2106 CALL                     0
           2116 FORMAT_VALUE             0
           2118 LOAD_CONST             117 (' ')
           2120 LOAD_GLOBAL             59 (NULL + names)
           2132 LOAD_ATTR               30 (get_last_name)
           2142 PRECALL                  0
           2146 CALL                     0
           2156 FORMAT_VALUE             0
           2158 LOAD_CONST             117 (' ')
           2160 LOAD_GLOBAL             59 (NULL + names)
           2172 LOAD_ATTR               30 (get_last_name)
           2182 PRECALL                  0
           2186 CALL                     0
           2196 FORMAT_VALUE             0
           2198 BUILD_STRING             5

743        2200 MAP_ADD                  1

755        2202 LOAD_CONST             118 ('extra_log_params')           2204 LOAD_CONST             119 ('%7B%22last_from_group_id%22%3A%22')
           2206 LOAD_FAST                0 (aweme_id)
           2208 BINARY_OP                0 (+)
           2212 LOAD_CONST             120 ('%22%2C%22is_ecom%22%3A%220%22%7D')
           2214 BINARY_OP                0 (+)

743        2218 MAP_ADD                  1

756        2220 LOAD_CONST             121 ('report_desc')
           2222 LOAD_GLOBAL             62 (ktab)
           2234 FORMAT_VALUE             0

743        2236 MAP_ADD                  1

757        2238 LOAD_CONST             122 ('category')
           2240 LOAD_CONST             108 ('')

743        2242 MAP_ADD                  1

758        2244 LOAD_CONST             123 ('legal_jurisdiction')
           2246 LOAD_CONST             124 ('dk')

743        2248 MAP_ADD                  1

759        2250 LOAD_CONST             125 ('iid')
           2252 LOAD_FAST                7 (install_id)

743        2254 MAP_ADD                  1

760        2256 LOAD_CONST              52 ('device_id')
           2258 LOAD_FAST                8 (device_id)

743        2260 MAP_ADD                  1
           2262 BUILD_MAP                0

761        2264 LOAD_CONST             126 ('ac')
           2266 LOAD_CONST             127 ('wifi')

743        2268 MAP_ADD                  1

762        2270 LOAD_CONST              50 ('channel')
           2272 LOAD_CONST             128 ('googleplay')

743        2274 MAP_ADD                  1

763        2276 LOAD_CONST              34 ('aid')
           2278 LOAD_CONST             129 ('1233')

743        2280 MAP_ADD                  1

764        2282 LOAD_CONST              37 ('app_name')
           2284 LOAD_CONST             130 ('musical_ly')

743        2286 MAP_ADD                  1

765        2288 LOAD_CONST             131 ('version_code')
           2290 LOAD_CONST             132 ('330304')

743        2292 MAP_ADD                  1

766        2294 LOAD_CONST             133 ('version_name')
           2296 LOAD_CONST             134 ('33.3.4')

743        2298 MAP_ADD                  1

767        2300 LOAD_CONST              53 ('device_platform')
           2302 LOAD_CONST             135 ('android')

743        2304 MAP_ADD                  1

768        2306 LOAD_CONST              68 ('os')
           2308 LOAD_CONST             135 ('android')

743        2310 MAP_ADD                  1

769        2312 LOAD_CONST             136 ('ab_version')
           2314 LOAD_CONST             134 ('33.3.4')

743        2316 MAP_ADD                  1

770        2318 LOAD_CONST             137 ('ssmix')
           2320 LOAD_CONST             138 ('a')

743        2322 MAP_ADD                  1

771        2324 LOAD_CONST             139 ('device_type')
           2326 LOAD_FAST               20 (type1)

743        2328 MAP_ADD                  1

772        2330 LOAD_CONST             140 ('device_brand')
           2332 LOAD_FAST               21 (brand)

743        2334 MAP_ADD                  1

773        2336 LOAD_CONST             141 ('language')
           2338 LOAD_FAST               11 (webcast_language)

743        2340 MAP_ADD                  1

774        2342 LOAD_CONST             142 ('os_api')
           2344 LOAD_CONST             143 ('28')

743        2346 MAP_ADD                  1

775        2348 LOAD_CONST             144 ('os_version')
           2350 LOAD_CONST             145 ('9')

743        2352 MAP_ADD                  1

776        2354 LOAD_CONST             146 ('openudid')
           2356 LOAD_FAST                9 (openudid)

743        2358 MAP_ADD                  1

777        2360 LOAD_CONST             147 ('manifest_version_code')
           2362 LOAD_CONST             148 ('2023303040')

743        2364 MAP_ADD                  1
           2366 DICT_UPDATE              1
           2368 BUILD_MAP                0

778        2370 LOAD_CONST             149 ('resolution')
           2372 LOAD_FAST               15 (screen_width)
           2374 FORMAT_VALUE             0
           2376 LOAD_CONST             150 ('*')
           2378 LOAD_FAST               14 (screen_height)
           2380 FORMAT_VALUE             0
           2382 BUILD_STRING             3

743        2384 MAP_ADD                  1

779        2386 LOAD_CONST             151 ('dpi')
           2388 LOAD_CONST             152 ('191')

743        2390 MAP_ADD                  1

780        2392 LOAD_CONST             153 ('update_version_code')
           2394 LOAD_CONST             148 ('2023303040')

743        2396 MAP_ADD                  1

781        2398 LOAD_CONST             154 ('_rticket')
           2400 LOAD_FAST                3 (_rticket)

743        2402 MAP_ADD                  1

782        2404 LOAD_CONST             155 ('is_pad')
           2406 LOAD_CONST              40 ('0')

743        2408 MAP_ADD                  1

783        2410 LOAD_CONST             156 ('current_region')
           2412 LOAD_FAST               12 (current_region)

743        2414 MAP_ADD                  1

784        2416 LOAD_CONST             157 ('app_type')
           2418 LOAD_CONST             158 ('normal')

743        2420 MAP_ADD                  1

785        2422 LOAD_CONST             159 ('sys_region')
           2424 LOAD_FAST               13 (region)

743        2426 MAP_ADD                  1

786        2428 LOAD_CONST             160 ('mcc_mnc')
           2430 LOAD_CONST             161 ('21890')

743        2432 MAP_ADD                  1

787        2434 LOAD_CONST             162 ('timezone_name')
           2436 LOAD_FAST               10 (tz_name)

743        2438 MAP_ADD                  1

788        2440 LOAD_CONST             163 ('residence')
           2442 LOAD_FAST               12 (current_region)

743        2444 MAP_ADD                  1

789        2446 LOAD_CONST              36 ('app_language')
           2448 LOAD_FAST               11 (webcast_language)

743        2450 MAP_ADD                  1

790        2452 LOAD_CONST             164 ('carrier_region')
           2454 LOAD_FAST               12 (current_region)

743        2456 MAP_ADD                  1

791        2458 LOAD_CONST             165 ('ac2')
           2460 LOAD_CONST             127 ('wifi')

743        2462 MAP_ADD                  1

792        2464 LOAD_CONST             166 ('uoo')
           2466 LOAD_CONST              40 ('0')

743        2468 MAP_ADD                  1

793        2470 LOAD_CONST             167 ('op_region')
           2472 LOAD_FAST               12 (current_region)

743        2474 MAP_ADD                  1

794        2476 LOAD_CONST             168 ('timezone_offset')
           2478 LOAD_FAST               23 (off)

743        2480 MAP_ADD                  1
           2482 DICT_UPDATE              1

795        2484 LOAD_CONST             134 ('33.3.4')

796        2486 LOAD_CONST             169 ('arm64-v8a')

797        2488 LOAD_FAST               11 (webcast_language)

798        2490 LOAD_FAST               13 (region)

799        2492 LOAD_FAST                4 (ts)

800        2494 LOAD_FAST                6 (uid)

743        2496 LOAD_CONST             170 (('build_number', 'host_abi', 'locale', 'region', 'ts', 'cdid'))
           2498 BUILD_CONST_KEY_MAP      6
           2500 DICT_UPDATE              1
           2502 PRECALL                  1
           2506 CALL                     1
           2516 STORE_FAST              30 (pro)
           2518 JUMP_FORWARD           205 (to 2930)

804     >> 2520 LOAD_GLOBAL             47 (NULL + urlencode)
           2532 BUILD_MAP                0

805        2534 LOAD_CONST              73 ('reason')
           2536 LOAD_GLOBAL             64 (reason1)
           2548 LOAD_CONST               3 (0)
           2550 BINARY_SUBSCR

804        2560 MAP_ADD                  1

806        2562 LOAD_CONST             110 ('enter_from')
           2564 LOAD_CONST             111 ('homepage_hot')

804        2566 MAP_ADD                  1

807        2568 LOAD_CONST              70 ('owner_id')
           2570 LOAD_GLOBAL             50 (id)

804        2582 MAP_ADD                  1

808        2584 LOAD_CONST              75 ('report_type')
           2586 LOAD_CONST              57 ('video')

804        2588 MAP_ADD                  1

809        2590 LOAD_CONST              66 ('object_id')
           2592 LOAD_FAST                0 (aweme_id)

804        2594 MAP_ADD                  1

810        2596 LOAD_CONST             171 ('uri')
           2598 LOAD_CONST             108 ('')

804        2600 MAP_ADD                  1

811        2602 LOAD_CONST             112 ('no_hw')
           2604 LOAD_CONST              31 ('1')

804        2606 MAP_ADD                  1

812        2608 LOAD_CONST             172 ('current_video_play_time')
           2610 LOAD_CONST             173 ('12')

804        2612 MAP_ADD                  1

813        2614 LOAD_CONST             114 ('isFirst')
           2616 LOAD_CONST              31 ('1')

804        2618 MAP_ADD                  1

814        2620 LOAD_CONST             118 ('extra_log_params')           2622 LOAD_CONST             119 ('%7B%22last_from_group_id%22%3A%22')
           2624 LOAD_FAST                0 (aweme_id)
           2626 BINARY_OP                0 (+)
           2630 LOAD_CONST             120 ('%22%2C%22is_ecom%22%3A%220%22%7D')
           2632 BINARY_OP                0 (+)

804        2636 MAP_ADD                  1

815        2638 LOAD_CONST             121 ('report_desc')
           2640 LOAD_CONST             108 ('')

804        2642 MAP_ADD                  1

816        2644 LOAD_CONST             122 ('category')
           2646 LOAD_CONST             108 ('')

804        2648 MAP_ADD                  1

817        2650 LOAD_CONST             125 ('iid')
           2652 LOAD_FAST                7 (install_id)

804        2654 MAP_ADD                  1

818        2656 LOAD_CONST              52 ('device_id')
           2658 LOAD_FAST                8 (device_id)

804        2660 MAP_ADD                  1

819        2662 LOAD_CONST             126 ('ac')
           2664 LOAD_CONST             127 ('wifi')

804        2666 MAP_ADD                  1

820        2668 LOAD_CONST              50 ('channel')
           2670 LOAD_CONST             128 ('googleplay')

804        2672 MAP_ADD                  1

821        2674 LOAD_CONST              34 ('aid')
           2676 LOAD_CONST             129 ('1233')

804        2678 MAP_ADD                  1
           2680 BUILD_MAP                0

822        2682 LOAD_CONST              37 ('app_name')
           2684 LOAD_CONST             130 ('musical_ly')

804        2686 MAP_ADD                  1

823        2688 LOAD_CONST             131 ('version_code')
           2690 LOAD_CONST             132 ('330304')

804        2692 MAP_ADD                  1

824        2694 LOAD_CONST             133 ('version_name')
           2696 LOAD_CONST             134 ('33.3.4')

804        2698 MAP_ADD                  1

825        2700 LOAD_CONST              53 ('device_platform')
           2702 LOAD_CONST             135 ('android')

804        2704 MAP_ADD                  1

826        2706 LOAD_CONST              68 ('os')
           2708 LOAD_CONST             135 ('android')

804        2710 MAP_ADD                  1

827        2712 LOAD_CONST             136 ('ab_version')
           2714 LOAD_CONST             134 ('33.3.4')

804        2716 MAP_ADD                  1

828        2718 LOAD_CONST             137 ('ssmix')
           2720 LOAD_CONST             138 ('a')

804        2722 MAP_ADD                  1

829        2724 LOAD_CONST             139 ('device_type')
           2726 LOAD_FAST               20 (type1)

804        2728 MAP_ADD                  1

830        2730 LOAD_CONST             140 ('device_brand')
           2732 LOAD_FAST               21 (brand)

804        2734 MAP_ADD                  1

831        2736 LOAD_CONST             141 ('language')
           2738 LOAD_FAST               11 (webcast_language)

804        2740 MAP_ADD                  1

832        2742 LOAD_CONST             142 ('os_api')
           2744 LOAD_CONST             143 ('28')

804        2746 MAP_ADD                  1

833        2748 LOAD_CONST             144 ('os_version')
           2750 LOAD_CONST             145 ('9')

804        2752 MAP_ADD                  1

834        2754 LOAD_CONST             146 ('openudid')
           2756 LOAD_FAST                9 (openudid)

804        2758 MAP_ADD                  1

835        2760 LOAD_CONST             147 ('manifest_version_code')
           2762 LOAD_CONST             148 ('2023303040')

804        2764 MAP_ADD                  1

836        2766 LOAD_CONST             149 ('resolution')
           2768 LOAD_FAST               15 (screen_width)
           2770 FORMAT_VALUE             0
           2772 LOAD_CONST             150 ('*')
           2774 LOAD_FAST               14 (screen_height)
           2776 FORMAT_VALUE             0
           2778 BUILD_STRING             3

804        2780 MAP_ADD                  1

837        2782 LOAD_CONST             151 ('dpi')
           2784 LOAD_CONST             152 ('191')

804        2786 MAP_ADD                  1

838        2788 LOAD_CONST             153 ('update_version_code')
           2790 LOAD_CONST             148 ('2023303040')

804        2792 MAP_ADD                  1
           2794 DICT_UPDATE              1
           2796 BUILD_MAP                0

839        2798 LOAD_CONST             154 ('_rticket')
           2800 LOAD_FAST                3 (_rticket)

804        2802 MAP_ADD                  1

840        2804 LOAD_CONST             155 ('is_pad')
           2806 LOAD_CONST              40 ('0')

804        2808 MAP_ADD                  1

841        2810 LOAD_CONST             156 ('current_region')
           2812 LOAD_FAST               12 (current_region)

804        2814 MAP_ADD                  1

842        2816 LOAD_CONST             157 ('app_type')
           2818 LOAD_CONST             158 ('normal')

804        2820 MAP_ADD                  1

843        2822 LOAD_CONST             159 ('sys_region')
           2824 LOAD_FAST               13 (region)

804        2826 MAP_ADD                  1

844        2828 LOAD_CONST             160 ('mcc_mnc')
           2830 LOAD_CONST             161 ('21890')

804        2832 MAP_ADD                  1

845        2834 LOAD_CONST             162 ('timezone_name')
           2836 LOAD_FAST               10 (tz_name)

804        2838 MAP_ADD                  1

846        2840 LOAD_CONST             163 ('residence')
           2842 LOAD_FAST               12 (current_region)

804        2844 MAP_ADD                  1

847        2846 LOAD_CONST              36 ('app_language')
           2848 LOAD_FAST               11 (webcast_language)

804        2850 MAP_ADD                  1

848        2852 LOAD_CONST             164 ('carrier_region')
           2854 LOAD_FAST               12 (current_region)

804        2856 MAP_ADD                  1

849        2858 LOAD_CONST             165 ('ac2')
           2860 LOAD_CONST             127 ('wifi')

804        2862 MAP_ADD                  1

850        2864 LOAD_CONST             166 ('uoo')
           2866 LOAD_CONST              40 ('0')

804        2868 MAP_ADD                  1

851        2870 LOAD_CONST             167 ('op_region')
           2872 LOAD_FAST               12 (current_region)

804        2874 MAP_ADD                  1

852        2876 LOAD_CONST             168 ('timezone_offset')
           2878 LOAD_FAST               23 (off)

804        2880 MAP_ADD                  1

853        2882 LOAD_CONST             174 ('build_number')
           2884 LOAD_CONST             134 ('33.3.4')

804        2886 MAP_ADD                  1

854        2888 LOAD_CONST             175 ('host_abi')
           2890 LOAD_CONST             169 ('arm64-v8a')

804        2892 MAP_ADD                  1

855        2894 LOAD_CONST             176 ('locale')
           2896 LOAD_FAST               11 (webcast_language)

804        2898 MAP_ADD                  1
           2900 DICT_UPDATE              1

856        2902 LOAD_FAST               13 (region)

857        2904 LOAD_FAST                4 (ts)

858        2906 LOAD_FAST                6 (uid)

804        2908 LOAD_CONST             177 (('region', 'ts', 'cdid'))
           2910 BUILD_CONST_KEY_MAP      3
           2912 DICT_UPDATE              1
           2914 PRECALL                  1
           2918 CALL                     1
           2928 STORE_FAST              30 (pro)

859     >> 2930 LOAD_CONST             178 ('https://api22-normal-c-useast1a.tiktokv.com/aweme/v2/aweme/feedback/?')
           2932 STORE_FAST              31 (u)

860        2934 LOAD_FAST               31 (u)
           2936 LOAD_FAST               30 (pro)
           2938 BINARY_OP                0 (+)
           2942 STORE_FAST              28 (url)

861        2944 BUILD_STRING             0
           2946 STORE_FAST              32 (payload)

862        2948 LOAD_GLOBAL             67 (NULL + ttsign)
           2960 LOAD_FAST               28 (url)
           2962 LOAD_METHOD             15 (split)
           2984 LOAD_CONST             179 ('?')
           2986 PRECALL                  1
           2990 CALL                     1
           3000 LOAD_CONST              24 (1)
           3002 BINARY_SUBSCR
           3012 LOAD_FAST               32 (payload)
           3014 LOAD_CONST               0 (None)
           3016 PRECALL                  3
           3020 CALL                     3
           3030 LOAD_METHOD             34 (get_value)
           3052 PRECALL                  0
           3056 CALL                     0
           3066 STORE_FAST              33 (signed)

863        3068 LOAD_FAST               33 (signed)
           3070 LOAD_CONST             180 ('x-gorgon')
           3072 BINARY_SUBSCR
           3082 STORE_FAST              34 (x_gorgon)

864        3084 LOAD_FAST               33 (signed)
           3086 LOAD_CONST             181 ('x-khronos')
           3088 BINARY_SUBSCR
           3098 STORE_FAST              35 (x_khronos)

865        3100 LOAD_FAST               33 (signed)
           3102 LOAD_CONST             182 ('x-ss-req-ticket')
           3104 BINARY_SUBSCR
           3114 STORE_FAST              36 (xss)

869        3116 LOAD_CONST             183 ('sid_tt=')
           3118 LOAD_FAST                1 (sessionid)
           3120 FORMAT_VALUE             0
           3122 LOAD_CONST              97 ('; sessionid=')
           3124 LOAD_FAST                1 (sessionid)
           3126 FORMAT_VALUE             0
           3128 LOAD_CONST              98 ('; sessionid_ss=')
           3130 LOAD_FAST                1 (sessionid)
           3132 FORMAT_VALUE             0
           3134 LOAD_CONST              99 (';')
           3136 BUILD_STRING             7

871        3138 LOAD_CONST             184 ('com.zhiliaoapp.musically/2023306030 (Linux; U; Android 12; ')
           3140 LOAD_FAST               13 (region)
           3142 FORMAT_VALUE             0
           3144 LOAD_CONST             185 ('; ')
           3146 LOAD_FAST               20 (type1)
           3148 FORMAT_VALUE             0
           3150 LOAD_CONST             186 ('; Build/NRD90M.')
           3152 LOAD_FAST               22 (dev)
           3154 FORMAT_VALUE             0
           3156 LOAD_CONST             187 ('KSU1AQDC;tt-ok/3.12.13.4-tiktok)')
           3158 BUILD_STRING             7

873        3160 LOAD_FAST               34 (x_gorgon)

874        3162 LOAD_FAST               35 (x_khronos)

875        3164 LOAD_FAST               36 (xss)

867        3166 LOAD_CONST             188 (('Cookie', 'User-Agent', 'X-Gorgon', 'X-Khronos', 'X-SS-REQ-TICKET'))
           3168 BUILD_CONST_KEY_MAP      5
           3170 STORE_FAST              29 (h)

877     >> 3172 NOP

878        3174 LOAD_GLOBAL             71 (NULL + requests)
           3186 LOAD_ATTR               36 (get)
           3196 LOAD_FAST               28 (url)
           3198 LOAD_FAST               29 (h)
           3200 LOAD_CONST             189 ('socks5://')
           3202 LOAD_GLOBAL              1 (NULL + str)
           3214 LOAD_GLOBAL              3 (NULL + random)
           3226 LOAD_ATTR                2 (choice)
           3236 LOAD_GLOBAL              6 (ls)
           3248 PRECALL                  1
           3252 CALL                     1
           3262 PRECALL                  1
           3266 CALL                     1
           3276 FORMAT_VALUE             0
           3278 BUILD_STRING             2
           3280 LOAD_CONST             190 ('socks4://')
           3282 LOAD_GLOBAL              1 (NULL + str)
           3294 LOAD_GLOBAL              3 (NULL + random)
           3306 LOAD_ATTR                2 (choice)
           3316 LOAD_GLOBAL              6 (ls)
           3328 PRECALL                  1
           3332 CALL                     1
           3342 PRECALL                  1
           3346 CALL                     1
           3356 FORMAT_VALUE             0
           3358 BUILD_STRING             2
           3360 LOAD_CONST             191 ('http://')
           3362 LOAD_GLOBAL              1 (NULL + str)
           3374 LOAD_GLOBAL              3 (NULL + random)
           3386 LOAD_ATTR                2 (choice)
           3396 LOAD_GLOBAL              6 (ls)
           3408 PRECALL                  1
           3412 CALL                     1
           3422 PRECALL                  1
           3426 CALL                     1
           3436 FORMAT_VALUE             0
           3438 BUILD_STRING             2
           3440 LOAD_CONST             192 (('https', 'https', 'https'))
           3442 BUILD_CONST_KEY_MAP      3
           3444 KW_NAMES               193
           3446 PRECALL                  3
           3450 CALL                     3
           3460 LOAD_ATTR               37 (text)
           3470 STORE_FAST              37 (r)

879        3472 LOAD_GLOBAL             76 (tr)
           3484 LOAD_CONST              24 (1)
           3486 BINARY_OP               13 (+=)
           3490 STORE_GLOBAL            38 (tr)

880        3492 LOAD_FAST                0 (aweme_id)
           3494 LOAD_GLOBAL             78 (soso)
           3506 CONTAINS_OP              0
           3508 POP_JUMP_FORWARD_IF_FALSE     1 (to 3512)

881        3510 JUMP_FORWARD            26 (to 3564)

883     >> 3512 LOAD_GLOBAL             78 (soso)
           3524 LOAD_METHOD             40 (append)
           3546 LOAD_FAST                0 (aweme_id)
           3548 PRECALL                  1
           3552 CALL                     1
           3562 POP_TOP

884     >> 3564 LOAD_FAST                1 (sessionid)
           3566 LOAD_GLOBAL             82 (loop)
           3578 CONTAINS_OP              0
           3580 POP_JUMP_FORWARD_IF_FALSE     1 (to 3584)

885        3582 JUMP_FORWARD            26 (to 3636)

887     >> 3584 LOAD_GLOBAL             82 (loop)
           3596 LOAD_METHOD             40 (append)
           3618 LOAD_FAST                1 (sessionid)
           3620 PRECALL                  1
           3624 CALL                     1
           3634 POP_TOP

888     >> 3636 LOAD_GLOBAL              3 (NULL + random)
           3648 LOAD_ATTR                2 (choice)
           3658 LOAD_GLOBAL             84 (F)
           3670 LOAD_GLOBAL             86 (J)
           3682 LOAD_GLOBAL             88 (Z)
           3694 LOAD_GLOBAL             90 (C)
           3706 LOAD_GLOBAL             92 (B)
           3718 LOAD_GLOBAL             94 (L)
           3730 LOAD_GLOBAL             96 (J1)
           3742 LOAD_GLOBAL             98 (J2)
           3754 LOAD_GLOBAL            100 (J21)
           3766 LOAD_GLOBAL            102 (J22)
           3778 LOAD_GLOBAL            104 (F1)
           3790 LOAD_GLOBAL            106 (C1)
           3802 LOAD_GLOBAL            108 (P1)
           3814 BUILD_LIST              13
           3816 PRECALL                  1
           3820 CALL                     1
           3830 STORE_FAST              38 (bi)

889        3832 LOAD_GLOBAL            111 (NULL + print)
           3844 LOAD_FAST               38 (bi)
           3846 LOAD_CONST             194 ('\r ')
           3848 LOAD_GLOBAL            113 (NULL + len)
           3860 LOAD_GLOBAL             78 (soso)
           3872 PRECALL                  1
           3876 CALL                     1
           3886 FORMAT_VALUE             0
           3888 LOAD_CONST             195 ('/')
           3890 LOAD_GLOBAL            113 (NULL + len)
           3902 LOAD_GLOBAL            114 (tar)
           3914 PRECALL                  1
           3918 CALL                     1
           3928 FORMAT_VALUE             0
           3930 LOAD_CONST             196 (' ❌ :')
           3932 LOAD_GLOBAL             84 (F)
           3944 FORMAT_VALUE             0
           3946 LOAD_CONST             197 ('[')
           3948 LOAD_GLOBAL             76 (tr)
           3960 FORMAT_VALUE             0
           3962 LOAD_CONST             198 ('] ')
           3964 LOAD_FAST               38 (bi)
           3966 FORMAT_VALUE             0
           3968 LOAD_CONST             199 ('تم البلاغ✅ :')
           3970 LOAD_GLOBAL             88 (Z)
           3982 FORMAT_VALUE             0
           3984 LOAD_CONST             197 ('[')
           3986 LOAD_GLOBAL            116 (fa)
           3998 FORMAT_VALUE             0
           4000 LOAD_CONST             200 (']')
           4002 LOAD_FAST               38 (bi)
           4004 FORMAT_VALUE             0
           4006 LOAD_CONST             117 (' ')
           4008 LOAD_GLOBAL            113 (NULL + len)
           4020 LOAD_GLOBAL             82 (loop)
           4032 PRECALL                  1
           4036 CALL                     1
           4046 FORMAT_VALUE             0
           4048 LOAD_CONST             195 ('/')
           4050 LOAD_GLOBAL            113 (NULL + len)
           4062 LOAD_GLOBAL            118 (sisn)
           4074 PRECALL                  1
           4078 CALL                     1
           4088 FORMAT_VALUE             0
           4090 BUILD_STRING            20
           4092 BINARY_OP                0 (+)
           4096 LOAD_CONST             117 (' ')
           4098 KW_NAMES               201
           4100 PRECALL                  2
           4104 CALL                     2
           4114 POP_TOP
           4116 LOAD_GLOBAL            120 (sys)
           4128 LOAD_ATTR               61 (stdout)
           4138 LOAD_METHOD             62 (flush)
           4160 PRECALL                  0
           4164 CALL                     0
           4174 POP_TOP
           4176 LOAD_CONST               0 (None)
           4178 RETURN_VALUE
        >> 4180 PUSH_EXC_INFO

890        4182 POP_TOP

891        4184 LOAD_GLOBAL            116 (fa)
           4196 LOAD_CONST              24 (1)
           4198 BINARY_OP               13 (+=)
           4202 STORE_GLOBAL            58 (fa)

892        4204 LOAD_GLOBAL              3 (NULL + random)
           4216 LOAD_ATTR                2 (choice)
           4226 LOAD_GLOBAL             84 (F)
           4238 LOAD_GLOBAL             86 (J)
           4250 LOAD_GLOBAL             88 (Z)
           4262 LOAD_GLOBAL             90 (C)
           4274 LOAD_GLOBAL             92 (B)
           4286 LOAD_GLOBAL             94 (L)
           4298 LOAD_GLOBAL             96 (J1)
           4310 LOAD_GLOBAL             98 (J2)
           4322 LOAD_GLOBAL            100 (J21)
           4334 LOAD_GLOBAL            102 (J22)
           4346 LOAD_GLOBAL            104 (F1)
           4358 LOAD_GLOBAL            106 (C1)
           4370 LOAD_GLOBAL            108 (P1)
           4382 BUILD_LIST              13
           4384 PRECALL                  1
           4388 CALL                     1
           4398 STORE_FAST              38 (bi)

893        4400 LOAD_GLOBAL            111 (NULL + print)
           4412 LOAD_FAST               38 (bi)
           4414 LOAD_CONST             194 ('\r ')
           4416 LOAD_GLOBAL            113 (NULL + len)
           4428 LOAD_GLOBAL             78 (soso)
           4440 PRECALL                  1
           4444 CALL                     1
           4454 FORMAT_VALUE             0
           4456 LOAD_CONST             195 ('/')
           4458 LOAD_GLOBAL            113 (NULL + len)
           4470 LOAD_GLOBAL            114 (tar)
           4482 PRECALL                  1
           4486 CALL                     1
           4496 FORMAT_VALUE             0
           4498 LOAD_CONST             196 (' ❌ :')
           4500 LOAD_GLOBAL             84 (F)
           4512 FORMAT_VALUE             0
           4514 LOAD_CONST             197 ('[')
           4516 LOAD_GLOBAL             76 (tr)
           4528 FORMAT_VALUE             0
           4530 LOAD_CONST             198 ('] ')
           4532 LOAD_FAST               38 (bi)
           4534 FORMAT_VALUE             0
           4536 LOAD_CONST             202 ('تم البلاغ ✅ :')
           4538 LOAD_GLOBAL             88 (Z)
           4550 FORMAT_VALUE             0
           4552 LOAD_CONST             197 ('[')
           4554 LOAD_GLOBAL            116 (fa)
           4566 FORMAT_VALUE             0
           4568 LOAD_CONST             200 (']')
           4570 LOAD_FAST               38 (bi)
           4572 FORMAT_VALUE             0
           4574 LOAD_CONST             117 (' ')
           4576 LOAD_GLOBAL            113 (NULL + len)
           4588 LOAD_GLOBAL             82 (loop)
           4600 PRECALL                  1
           4604 CALL                     1
           4614 FORMAT_VALUE             0
           4616 LOAD_CONST             195 ('/')
           4618 LOAD_GLOBAL            113 (NULL + len)
           4630 LOAD_GLOBAL            118 (sisn)
           4642 PRECALL                  1
           4646 CALL                     1
           4656 FORMAT_VALUE             0
           4658 BUILD_STRING            20
           4660 BINARY_OP                0 (+)
           4664 LOAD_CONST             117 (' ')
           4666 KW_NAMES               201
           4668 PRECALL                  2
           4672 CALL                     2
           4682 POP_TOP
           4684 LOAD_GLOBAL            120 (sys)
           4696 LOAD_ATTR               61 (stdout)
           4706 LOAD_METHOD             62 (flush)
           4728 PRECALL                  0
           4732 CALL                     0
           4742 POP_TOP
           4744 POP_EXCEPT
           4746 LOAD_CONST               0 (None)
           4748 RETURN_VALUE
        >> 4750 COPY                     3
           4752 POP_EXCEPT
           4754 RERAISE                  1
ExceptionTable:
  3174 to 4174 -> 4180 [0]
  4180 to 4742 -> 4750 [1] lasti